Workbook

Sheet FM_Dashboard
A1: AKA | B1: AGA KHAN ACADEMY | FACILITY MANAGEMENT MIS DASHBOARD
A2: HYDERABAD · FM | B2: ="Calendar 2026 • live MIS data Jan-26 to "&MIS_Calc!$B$6&" • Water · Energy · Solar · HVAC · Treatment · Service desk · Manpower • "&TEXT(MIS_Calc!$B$15,"#,##0")&" occupants • "&TEXT(MIS_Calc!$B$7,"#,##0")&" m² built-up" -> Calendar 2026 • live MIS data Jan-26 to Aug-26 • Water · Energy · Solar · HVAC · Treatment · Service desk · Manpower • 1,354 occupants • 52,652 m² built-up
B4: MONTH | H4: FACILITY | P4: ="Showing: "&MIS_Calc!$B$3&" • Facility drill: "&MIS_Calc!$B$4&" • Data completeness "&IF(MIS_Calc!$F$80="","n/a",TEXT(MIS_Calc!$F$80,"0%")) -> Showing: Aug-26 • Facility drill: All Facilities • Data completeness 88%
A5: ▶ FM Dashboard | B5: 📅 Select ▸ | D5: Aug-26 | H5: 🏢 Drill ▸ | J5: All Facilities | P5: Pick a month (or 2026 YTD) from the yellow drop-down; the facility drop-down drives the drill-down charts & highlights the scorecard. 'vs 2025' compares the monthly average with the Avg-2025 row of each source sheet.
A7: Per-Capita Pyramid | B7: 💧 WATER CONSUMED (kL) | F7: 🚰 LPCD (L / person / day) | J7: ⛲ BOREWELL DRAW (kL) | N7: ⚡ HT GRID ENERGY (kWh) | R7: ₹ ENERGY BILL (₹ Lakh) | V7: 🏢 EPI (kWh / m² / month)
B8: =IF(MIS_Calc!$E$44="","NO DATA",MIS_Calc!$E$44) -> 14026 | F8: =IF(MIS_Calc!$F$46="","NO DATA",MIS_Calc!$F$46) -> 334.15924 | J8: =IF(MIS_Calc!$E$47="","NO DATA",MIS_Calc!$E$47) -> 11995 | N8: =IF(MIS_Calc!$E$51="","NO DATA",MIS_Calc!$E$51) -> 146382 | R8: =IF(MIS_Calc!$E$54="","NO DATA",MIS_Calc!$E$54/100000) -> 18.29571 | V8: =IF(MIS_Calc!$F$58="","NO DATA",MIS_Calc!$F$58) -> 2.7801652
A9: Monthly KPI | B9: =IF($B$8="NO DATA","no data for this month","Avg/month "&TEXT(MIS_Calc!$F$44,"#,##0")&" • "&IF(MIS_Calc!$J$44="","vs Avg-2025 –","vs Avg-2025 "&TEXT(MIS_Calc!$J$44,"+0%;-0%;0%"))) -> Avg/month 14,026 • vs Avg-2025 -86% | F9: =IF(MIS_Calc!$F$46="","","Benchmark "&MIS_Calc!$B$8&" • "&IF(MIS_Calc!$F$46<=MIS_Calc!$B$8,"✔ within","▲ "&TEXT(MIS_Calc!$F$46/MIS_Calc!$B$8,"0.0")&"× benchmark")) -> Benchmark 135 • ▲ 2.5× benchmark | J9: =IF($J$8="NO DATA","no data for this month","STP recycled "&IF(MIS_Calc!$E$48="","–",TEXT(MIS_Calc!$E$48,"#,##0"))&" kL ("&TEXT(MIS_Calc!$F$90,"0%")&" of inlet)") -> STP recycled 2,683 kL (18% of inlet) | N9: =IF($N$8="NO DATA","no data for this month","Avg/month "&TEXT(MIS_Calc!$F$51,"#,##0")&" • "&IF(MIS_Calc!$J$51="","vs Avg-2025 –","vs Avg-2025 "&TEXT(MIS_Calc!$J$51,"+0%;-0%;0%"))) -> Avg/month 1,46,382 • vs Avg-2025 +10% | R9: =IF($R$8="NO DATA","no data for this month","₹"&TEXT(MIS_Calc!$F$55,"0.00")&"/kVAh • "&IF(MIS_Calc!$J$54="","bill vs Avg-2025 –","bill vs Avg-2025 "&TEXT(MIS_Calc!$J$54,"+0%;-0%;0%"))) -> ₹11.70/kVAh • bill vs Avg-2025 +5% | V9: =IF(MIS_Calc!$F$58="","","Benchmark ≤ "&MIS_Calc!$B$9&" • "&IF(MIS_Calc!$F$58<=MIS_Calc!$B$9,"✔ on target","▲ above")) -> Benchmark ≤ 8 • ✔ on target
A11: Complaints | B11: 🔌 POWER FACTOR | F11: ☀ SOLAR GENERATION (kWh) | J11: ❄ HVAC ENERGY (kWh) | N11: 🎫 COMPLAINTS RECEIVED | R11: 👷 TECH DEPLOYMENT | V11: 🚿 WTP TREATED WATER (kL)
B12: =IF(MIS_Calc!$F$53="","NO DATA",MIS_Calc!$F$53) -> 0.93618573 | F12: =IF(MIS_Calc!$E$59="","NO DATA",MIS_Calc!$E$59) -> 115911 | J12: =IF(MIS_Calc!$E$65="","NO DATA",MIS_Calc!$E$65) -> 21957.88 | N12: =IF(MIS_Calc!$E$40="","NO DATA",MIS_Calc!$E$40) -> 216 | R12: =IF(MIS_Calc!$F$77="","NO DATA",MIS_Calc!$F$77) -> 0.8484375 | V12: =IF(MIS_Calc!$E$49="","NO DATA",MIS_Calc!$E$49) -> 10986
A13: Water - Bldg | B13: =IF(MIS_Calc!$F$53="","","Target "&MIS_Calc!$B$10&" • "&IF(MIS_Calc!$F$53>=MIS_Calc!$B$10,"✔ OK","▲ below target")&" • MD "&TEXT(MIS_Calc!$F$85,"0%")&" of sanctioned") -> Target 0.95 • ▲ below target • MD 37% of sanctioned | F13: =IF($F$12="NO DATA","no data for this month","Savings ₹"&TEXT(N(MIS_Calc!$E$61)/100000,"#,##0.0")&" L • "&IF(MIS_Calc!$J$59="","vs Avg-2025 –","vs Avg-2025 "&TEXT(MIS_Calc!$J$59,"+0%;-0%;0%"))) -> Savings ₹13.7 L • vs Avg-2025 +35% | J13: =IF($J$12="NO DATA","no data for this month",IF(MIS_Calc!$J$65="","vs Avg-2025 –","vs Avg-2025 "&TEXT(MIS_Calc!$J$65,"+0%;-0%;0%"))) -> vs Avg-2025 +5% | N13: =IF(MIS_Calc!$E$40="","Not logged for this month • latest entry "&IFERROR(LOOKUP(2,1/(MIS_Calc!$C$21:$C$32<>""),MIS_Calc!$A$21:$A$32),"–"),"Closure "&TEXT(MIS_Calc!$F$98,"0%")&" • Pending "&IF(MIS_Calc!$E$42="","–",MIS_Calc!$E$42)&" • "&MIS_Calc!$G$40&" months logged") -> Closure 68% • Pending – • 5 months logged | R13: =IF($R$12="NO DATA","no data for this month","Target "&TEXT(MIS_Calc!$B$11,"0%")&" • Present "&TEXT(MIS_Calc!$E$75,"#,##0")&" / "&TEXT(MIS_Calc!$E$76,"#,##0")&" man-days") -> Target 90% • Present 543 / 640 man-days | V13: =IF($V$12="NO DATA","no data for this month","Avg/month "&TEXT(MIS_Calc!$F$49,"#,##0")&" • "&IF(MIS_Calc!$J$49="","vs Avg-2025 –","vs Avg-2025 "&TEXT(MIS_Calc!$J$49,"+0%;-0%;0%"))&" • Drip "&IF(MIS_Calc!$E$50="","–",TEXT(MIS_Calc!$E$50,"#,##0"))&" kL") -> Avg/month 10,986 • vs Avg-2025 +2% • Drip 2,501 kL
A15: LPCD
A17: Water Quality
A19: Power
A21: EPI
A23: Power - Bldg
A25: Solar
A27: HVAC
A29: DG / Outages
A31: Tech Manpower
A33: Attendance
A35: Building Master
A37: Calc engine
B99: 🏢 FACILITY SCORECARD (month filter applies • selected facility highlighted • LPCD and kWh/person are per resident student, residences only; SR-1+SR-2 and SR-3+SR-4 are each one block)
B100: Facility | E100: Group | G100: Water kL / mo | I100: Water vs baseline | K100: Water share | M100: Power kWh / mo | O100: Power vs Avg-2025 | Q100: Power share | S100: Water YTD kL | U100: Power YTD kWh | W100: LPCD | Y100: kWh / person
B101: =IF(MIS_Calc!A194="","–",MIS_Calc!A194) -> SR-1 | E101: =IF(MIS_Calc!B194="","–",MIS_Calc!B194) -> Residence | G101: =IF(MIS_Calc!AA194="","–",MIS_Calc!AA194) -> 329 | I101: =IF(MIS_Calc!AC194="","–",MIS_Calc!AC194) -> -0.15315315 | K101: =IF(MIS_Calc!AL194="","–",MIS_Calc!AL194) -> 0.046812749 | M101: =IF(MIS_Calc!AD194="","–",MIS_Calc!AD194) -> 4790 | O101: =IF(MIS_Calc!AF194="","–",MIS_Calc!AF194) -> 0.81990881 | Q101: =IF(MIS_Calc!AM194="","–",MIS_Calc!AM194) -> 0.033102972 | S101: =IF(MIS_Calc!AP194="","–",MIS_Calc!AP194) -> 1817 | U101: =IF(MIS_Calc!AQ194="","–",MIS_Calc!AQ194) -> 32957 | W101: =IF(MIS_Calc!AI194="","–",MIS_Calc!AI194) -> 713.01446 | Y101: =IF(MIS_Calc!AJ194="","–",MIS_Calc!AJ194) -> 326.96552
B102: =IF(MIS_Calc!A195="","–",MIS_Calc!A195) -> SR-2 | E102: =IF(MIS_Calc!B195="","–",MIS_Calc!B195) -> Residence | G102: =IF(MIS_Calc!AA195="","–",MIS_Calc!AA195) -> 312 | I102: =IF(MIS_Calc!AC195="","–",MIS_Calc!AC195) -> 0.56521739 | K102: =IF(MIS_Calc!AL195="","–",MIS_Calc!AL195) -> 0.044393853 | M102: =IF(MIS_Calc!AD195="","–",MIS_Calc!AD195) -> 4692 | O102: =IF(MIS_Calc!AF195="","–",MIS_Calc!AF195) -> 0.55034832 | Q102: =IF(MIS_Calc!AM195="","–",MIS_Calc!AM195) -> 0.032425708 | S102: =IF(MIS_Calc!AP195="","–",MIS_Calc!AP195) -> 1531 | U102: =IF(MIS_Calc!AQ195="","–",MIS_Calc!AQ195) -> 33862 | W102: =IF(MIS_Calc!AI195="","–",MIS_Calc!AI195) -> with SR-1 | Y102: =IF(MIS_Calc!AJ195="","–",MIS_Calc!AJ195) -> with SR-1
B103: =IF(MIS_Calc!A196="","–",MIS_Calc!A196) -> SR-3 | E103: =IF(MIS_Calc!B196="","–",MIS_Calc!B196) -> Residence | G103: =IF(MIS_Calc!AA196="","–",MIS_Calc!AA196) -> 64 | I103: =IF(MIS_Calc!AC196="","–",MIS_Calc!AC196) -> -0.62645914 | K103: =IF(MIS_Calc!AL196="","–",MIS_Calc!AL196) -> 0.0091064314 | M103: =IF(MIS_Calc!AD196="","–",MIS_Calc!AD196) -> 5092 | O103: =IF(MIS_Calc!AF196="","–",MIS_Calc!AF196) -> 0.58292316 | Q103: =IF(MIS_Calc!AM196="","–",MIS_Calc!AM196) -> 0.035190048 | S103: =IF(MIS_Calc!AP196="","–",MIS_Calc!AP196) -> 628 | U103: =IF(MIS_Calc!AQ196="","–",MIS_Calc!AQ196) -> 30031 | W103: =IF(MIS_Calc!AI196="","–",MIS_Calc!AI196) -> 252.19941 | Y103: =IF(MIS_Calc!AJ196="","–",MIS_Calc!AJ196) -> 348.48485
B104: =IF(MIS_Calc!A197="","–",MIS_Calc!A197) -> SR-4 | E104: =IF(MIS_Calc!B197="","–",MIS_Calc!B197) -> Residence | G104: =IF(MIS_Calc!AA197="","–",MIS_Calc!AA197) -> 194 | I104: =IF(MIS_Calc!AC197="","–",MIS_Calc!AC197) -> 0.19691517 | K104: =IF(MIS_Calc!AL197="","–",MIS_Calc!AL197) -> 0.02760387 | M104: =IF(MIS_Calc!AD197="","–",MIS_Calc!AD197) -> 6408 | O104: =IF(MIS_Calc!AF197="","–",MIS_Calc!AF197) -> 0.77765448 | Q104: =IF(MIS_Calc!AM197="","–",MIS_Calc!AM197) -> 0.044284727 | S104: =IF(MIS_Calc!AP197="","–",MIS_Calc!AP197) -> 1740 | U104: =IF(MIS_Calc!AQ197="","–",MIS_Calc!AQ197) -> 51868 | W104: =IF(MIS_Calc!AI197="","–",MIS_Calc!AI197) -> with SR-3 | Y104: =IF(MIS_Calc!AJ197="","–",MIS_Calc!AJ197) -> with SR-3
B105: =IF(MIS_Calc!A198="","–",MIS_Calc!A198) -> SR-9/10 A | E105: =IF(MIS_Calc!B198="","–",MIS_Calc!B198) -> Residence | G105: =IF(MIS_Calc!AA198="","–",MIS_Calc!AA198) -> 1468 | I105: =IF(MIS_Calc!AC198="","–",MIS_Calc!AC198) -> 2.2 | K105: =IF(MIS_Calc!AL198="","–",MIS_Calc!AL198) -> 0.20887877 | M105: =IF(MIS_Calc!AD198="","–",MIS_Calc!AD198) -> 3576 | O105: =IF(MIS_Calc!AF198="","–",MIS_Calc!AF198) -> -0.36872952 | Q105: =IF(MIS_Calc!AM198="","–",MIS_Calc!AM198) -> 0.0247132 | S105: =IF(MIS_Calc!AP198="","–",MIS_Calc!AP198) -> 7012 | U105: =IF(MIS_Calc!AQ198="","–",MIS_Calc!AQ198) -> 43986 | W105: =IF(MIS_Calc!AI198="","–",MIS_Calc!AI198) -> 1076.2463 | Y105: =IF(MIS_Calc!AJ198="","–",MIS_Calc!AJ198) -> 81.272727
B106: =IF(MIS_Calc!A199="","–",MIS_Calc!A199) -> SR-9/10 B | E106: =IF(MIS_Calc!B199="","–",MIS_Calc!B199) -> Residence | G106: =IF(MIS_Calc!AA199="","–",MIS_Calc!AA199) -> 45 | I106: =IF(MIS_Calc!AC199="","–",MIS_Calc!AC199) -> -0.90093561 | K106: =IF(MIS_Calc!AL199="","–",MIS_Calc!AL199) -> 0.0064029596 | M106: =IF(MIS_Calc!AD199="","–",MIS_Calc!AD199) -> 12306 | O106: =IF(MIS_Calc!AF199="","–",MIS_Calc!AF199) -> 1.2501577 | Q106: =IF(MIS_Calc!AM199="","–",MIS_Calc!AM199) -> 0.085044921 | S106: =IF(MIS_Calc!AP199="","–",MIS_Calc!AP199) -> 999 | U106: =IF(MIS_Calc!AQ199="","–",MIS_Calc!AQ199) -> 67455 | W106: =IF(MIS_Calc!AI199="","–",MIS_Calc!AI199) -> 85.388994 | Y106: =IF(MIS_Calc!AJ199="","–",MIS_Calc!AJ199) -> 723.88235
B107: =IF(MIS_Calc!A200="","–",MIS_Calc!A200) -> SR-11/12 CA | E107: =IF(MIS_Calc!B200="","–",MIS_Calc!B200) -> Residence | G107: =IF(MIS_Calc!AA200="","–",MIS_Calc!AA200) -> 710 | I107: =IF(MIS_Calc!AC200="","–",MIS_Calc!AC200) -> 1.0805861 | K107: =IF(MIS_Calc!AL200="","–",MIS_Calc!AL200) -> 0.10102447 | M107: =IF(MIS_Calc!AD200="","–",MIS_Calc!AD200) -> 5498 | O107: =IF(MIS_Calc!AF200="","–",MIS_Calc!AF200) -> 0.19537331 | Q107: =IF(MIS_Calc!AM200="","–",MIS_Calc!AM200) -> 0.037995853 | S107: =IF(MIS_Calc!AP200="","–",MIS_Calc!AP200) -> 3147 | U107: =IF(MIS_Calc!AQ200="","–",MIS_Calc!AQ200) -> 50546 | W107: =IF(MIS_Calc!AI200="","–",MIS_Calc!AI200) -> 558.61526 | Y107: =IF(MIS_Calc!AJ200="","–",MIS_Calc!AJ200) -> 134.09756
B108: =IF(MIS_Calc!A201="","–",MIS_Calc!A201) -> SR-11/12 CB | E108: =IF(MIS_Calc!B201="","–",MIS_Calc!B201) -> Residence | G108: =IF(MIS_Calc!AA201="","–",MIS_Calc!AA201) -> 0 | I108: =IF(MIS_Calc!AC201="","–",MIS_Calc!AC201) -> -1 | K108: =IF(MIS_Calc!AL201="","–",MIS_Calc!AL201) -> 0 | M108: =IF(MIS_Calc!AD201="","–",MIS_Calc!AD201) -> 8718 | O108: =IF(MIS_Calc!AF201="","–",MIS_Calc!AF201) -> 0.67562009 | Q108: =IF(MIS_Calc!AM201="","–",MIS_Calc!AM201) -> 0.060248791 | S108: =IF(MIS_Calc!AP201="","–",MIS_Calc!AP201) -> 1205 | U108: =IF(MIS_Calc!AQ201="","–",MIS_Calc!AQ201) -> 68631 | W108: =IF(MIS_Calc!AI201="","–",MIS_Calc!AI201) -> 0 | Y108: =IF(MIS_Calc!AJ201="","–",MIS_Calc!AJ201) -> 311.35714
B109: =IF(MIS_Calc!A202="","–",MIS_Calc!A202) -> Junior School | E109: =IF(MIS_Calc!B202="","–",MIS_Calc!B202) -> Academic | G109: =IF(MIS_Calc!AA202="","–",MIS_Calc!AA202) -> 120 | I109: =IF(MIS_Calc!AC202="","–",MIS_Calc!AC202) -> -0.76608187 | K109: =IF(MIS_Calc!AL202="","–",MIS_Calc!AL202) -> 0.017074559 | M109: =IF(MIS_Calc!AD202="","–",MIS_Calc!AD202) -> 10905 | O109: =IF(MIS_Calc!AF202="","–",MIS_Calc!AF202) -> 0.29232957 | Q109: =IF(MIS_Calc!AM202="","–",MIS_Calc!AM202) -> 0.07536282 | S109: =IF(MIS_Calc!AP202="","–",MIS_Calc!AP202) -> 358 | U109: =IF(MIS_Calc!AQ202="","–",MIS_Calc!AQ202) -> 79142 | W109: =IF(MIS_Calc!AI202="","–",MIS_Calc!AI202) -> – | Y109: =IF(MIS_Calc!AJ202="","–",MIS_Calc!AJ202) -> –
B110: =IF(MIS_Calc!A203="","–",MIS_Calc!A203) -> Senior School 1 & 3 | E110: =IF(MIS_Calc!B203="","–",MIS_Calc!B203) -> Academic | G110: =IF(MIS_Calc!AA203="","–",MIS_Calc!AA203) -> 82 | I110: =IF(MIS_Calc!AC203="","–",MIS_Calc!AC203) -> -0.82419153 | K110: =IF(MIS_Calc!AL203="","–",MIS_Calc!AL203) -> 0.011667615 | M110: =IF(MIS_Calc!AD203="","–",MIS_Calc!AD203) -> 8760 | O110: =IF(MIS_Calc!AF203="","–",MIS_Calc!AF203) -> -0.089507509 | Q110: =IF(MIS_Calc!AM203="","–",MIS_Calc!AM203) -> 0.060539046 | S110: =IF(MIS_Calc!AP203="","–",MIS_Calc!AP203) -> 482 | U110: =IF(MIS_Calc!AQ203="","–",MIS_Calc!AQ203) -> 86779 | W110: =IF(MIS_Calc!AI203="","–",MIS_Calc!AI203) -> – | Y110: =IF(MIS_Calc!AJ203="","–",MIS_Calc!AJ203) -> –
B111: =IF(MIS_Calc!A204="","–",MIS_Calc!A204) -> Senior School 2 | E111: =IF(MIS_Calc!B204="","–",MIS_Calc!B204) -> Academic | G111: =IF(MIS_Calc!AA204="","–",MIS_Calc!AA204) -> 45 | I111: =IF(MIS_Calc!AC204="","–",MIS_Calc!AC204) -> 0.33004926 | K111: =IF(MIS_Calc!AL204="","–",MIS_Calc!AL204) -> 0.0064029596 | M111: =IF(MIS_Calc!AD204="","–",MIS_Calc!AD204) -> 8229 | O111: =IF(MIS_Calc!AF204="","–",MIS_Calc!AF204) -> 0.095046409 | Q111: =IF(MIS_Calc!AM204="","–",MIS_Calc!AM204) -> 0.056869385 | S111: =IF(MIS_Calc!AP204="","–",MIS_Calc!AP204) -> 558 | U111: =IF(MIS_Calc!AQ204="","–",MIS_Calc!AQ204) -> 69436 | W111: =IF(MIS_Calc!AI204="","–",MIS_Calc!AI204) -> – | Y111: =IF(MIS_Calc!AJ204="","–",MIS_Calc!AJ204) -> –
B112: =IF(MIS_Calc!A205="","–",MIS_Calc!A205) -> Academy Building | E112: =IF(MIS_Calc!B205="","–",MIS_Calc!B205) -> Academic | G112: =IF(MIS_Calc!AA205="","–",MIS_Calc!AA205) -> 38 | I112: =IF(MIS_Calc!AC205="","–",MIS_Calc!AC205) -> 3.3428571 | K112: =IF(MIS_Calc!AL205="","–",MIS_Calc!AL205) -> 0.0054069437 | M112: =IF(MIS_Calc!AD205="","–",MIS_Calc!AD205) -> 18300 | O112: =IF(MIS_Calc!AF205="","–",MIS_Calc!AF205) -> -0.0058850158 | Q112: =IF(MIS_Calc!AM205="","–",MIS_Calc!AM205) -> 0.12646856 | S112: =IF(MIS_Calc!AP205="","–",MIS_Calc!AP205) -> 809 | U112: =IF(MIS_Calc!AQ205="","–",MIS_Calc!AQ205) -> 154300 | W112: =IF(MIS_Calc!AI205="","–",MIS_Calc!AI205) -> – | Y112: =IF(MIS_Calc!AJ205="","–",MIS_Calc!AJ205) -> –
... B118: =IF(MIS_Calc!A211="","–",MIS_Calc!A211) -> Laundry | E118: =IF(MIS_Calc!B211="","–",MIS_Calc!B211) -> Support | G118: =IF(MIS_Calc!AA211="","–",MIS_Calc!AA211) -> 135 | I118: =IF(MIS_Calc!AC211="","–",MIS_Calc!AC211) -> – | K118: =IF(MIS_Calc!AL211="","–",MIS_Calc!AL211) -> 0.019208879 | M118: =IF(MIS_Calc!AD211="","–",MIS_Calc!AD211) -> 3382 | O118: =IF(MIS_Calc!AF211="","–",MIS_Calc!AF211) -> 0.24958433 | Q118: =IF(MIS_Calc!AM211="","–",MIS_Calc!AM211) -> 0.023372495 | S118: =IF(MIS_Calc!AP211="","–",MIS_Calc!AP211) -> 690 | U118: =IF(MIS_Calc!AQ211="","–",MIS_Calc!AQ211) -> 23054 | W118: =IF(MIS_Calc!AI211="","–",MIS_Calc!AI211) -> – | Y118: =IF(MIS_Calc!AJ211="","–",MIS_Calc!AJ211) -> –
B119: METERED FACILITIES | G119: =SUM(MIS_Calc!AA194:AA211) -> 7028 | K119: =IF(COUNT(K101:K118)=0,"–",SUM(K101:K118)) -> 1 | M119: =SUM(MIS_Calc!AD194:AD211) -> 144700 | Q119: =IF(COUNT(Q101:Q118)=0,"–",SUM(Q101:Q118)) -> 1 | S119: =SUM(MIS_Calc!AP194:AP211) -> 36687 | U119: =SUM(MIS_Calc!AQ194:AQ211) -> 1083778.7
B121: 🚨 WATCHLIST (live, follows month filter) | N121: 🔎 DATA-QUALITY FINDINGS IN SOURCE SHEETS (please verify)
B122: LPCD vs benchmark (L/person/day) | J122: =MIS_Calc!$F$46 -> 334.15924 | L122: =IF(MIS_Calc!$F$46="","–",IF(MIS_Calc!$F$46>MIS_Calc!$B$8,"▲ Act","✔ OK")) -> ▲ Act | N122: 1. DG Units Generated, Mar–Aug 2026: total units are typed (11–56 kWh) and do not equal 500 kVA + 750 kVA (44–150 kWh), while diesel reads 8,735–17,820 L against 266–1,523 L in Jan–Feb — verify against the DG log.
B123: Power factor vs 0.95 target | J123: =MIS_Calc!$F$53 -> 0.93618573 | L123: =IF(MIS_Calc!$F$53="","–",IF(MIS_Calc!$F$53<MIS_Calc!$B$10,"▲ Act","✔ OK")) -> ▲ Act | N123: 2. Complaints summary: no entries for Mar–May 2026, and the pending column is blank from Jun-26 — please verify.
B124: EPI vs 8 kWh/m² benchmark | J124: =MIS_Calc!$F$58 -> 2.7801652 | L124: =IF(MIS_Calc!$F$58="","–",IF(MIS_Calc!$F$58>MIS_Calc!$B$9,"▲ Act","✔ OK")) -> ✔ OK | N124: 3. WQ sheet: Bore 08 and Bore 10 values look shifted by one row (e.g. Turbidity 912/840 NTU, pH 360/150).
B125: Technical deployment vs 90% target | J125: =MIS_Calc!$F$77 -> 0.8484375 | L125: =IF(MIS_Calc!$F$77="","–",IF(MIS_Calc!$F$77<MIS_Calc!$B$11,"▲ Act","✔ OK")) -> ▲ Act | N125: ="4. Building wise water: "&COUNTIF('Building wise water'!$Z$11:$Z$39,"VERIFY*")&" meters flag 'VERIFY AVG-2025 (>3× prior yrs)'; building comparisons therefore use the median 2023–25 baseline." -> 4. Building wise water: 13 meters flag 'VERIFY AVG-2025 (>3× prior yrs)'; building comparisons therefore use the median 2023–25 baseline.
B126: Months of complaint data missing (to latest month) | J126: =MATCH(MIS_Calc!$B$6,MIS_Calc!$A$21:$A$32,0)-MIS_Calc!$G$40 -> 3 | L126: =IF(MATCH(MIS_Calc!$B$6,MIS_Calc!$A$21:$A$32,0)-MIS_Calc!$G$40>0,"▲ Act","✔ OK") -> ▲ Act | N126: 5. Technical manpower cost invoices are logged only for Jan–Feb 2026.
B127: Months of tech-manpower invoices missing | J127: =MATCH(MIS_Calc!$B$6,MIS_Calc!$A$21:$A$32,0)-MIS_Calc!$G$73 -> 6 | L127: =IF(MATCH(MIS_Calc!$B$6,MIS_Calc!$A$21:$A$32,0)-MIS_Calc!$G$73>0,"▲ Act","✔ OK") -> ▲ Act | N127: 6. LPCD sheet Avg-2025 (2,432 L/person/day; 100,169 kL/month) is more than 2× Avg-2023/2024, so water comparisons against 2025 overstate the 2026 improvement.
B128: Data completeness vs 80% | J128: =MIS_Calc!$F$80 -> 0.875 | L128: =IF(MIS_Calc!$F$80="","–",IF(MIS_Calc!$F$80<0.8,"▲ Act","✔ OK")) -> ✔ OK | N128: 7. LPCD sheet water (e.g. Jan-26 40,704 kL) is about twice the metered inlet on Building wise water (borewells + STP outlet 18,598 kL) — confirm which basis LPCD should use.
B129: Water-meter data-quality flags open | J129: ='Building wise water'!W5 -> 14 | L129: =IF('Building wise water'!W5>0,"▲ Act","✔ OK") -> ▲ Act | N129: 8. Solar Power: Apr-26 export (227,564 kWh) exceeds generation (136,018 kWh) and Jun–Aug export equals generation exactly; savings are computed from export — verify the export readings.
B130: Borewell/WQ parameters above limit | J130: =SUM(WQ!D60:M60) -> 8 | L130: =IF(SUM(WQ!D60:M60)>0,"▲ Act","✔ OK") -> ▲ Act | N130: 9. Building_Master: resident-student headcount (192, 2026-27 roster) is entered for the SR residences only. Other facilities' occupants and all floor areas are blank, and staff living in the residences are not counted, so residence LPCD is per student.
B131: HVAC energy vs Avg-2025 | J131: =MIS_Calc!$J$65 -> 0.048655456 | L131: =IF(MIS_Calc!$J$65="","–",IF(MIS_Calc!$J$65>0.1,"▲ Act","✔ OK")) -> ✔ OK
B132: HT energy bill vs Avg-2025 | J132: =MIS_Calc!$J$54 -> 0.050692959 | L132: =IF(MIS_Calc!$J$54="","–",IF(MIS_Calc!$J$54>0.1,"▲ Act","✔ OK")) -> ✔ OK
B133: Power failures per month (vs Avg-2025) | J133: =MIS_Calc!$F$63 -> 1 | L133: =IF(MIS_Calc!$F$63="","–",IF(MIS_Calc!$F$63>N(MIS_Calc!$H$63)*1.2,"▲ Act","✔ OK")) -> ✔ OK
B135: Sources: Complaints summary, LPCD, Building wise water, Power data, EPI, Power Building wise, Solar Power, HVAC consumption, Technical manpower cost, Attendance, DG Units Generated, WQ, Monthly KPI Report — all linked live via MIS_Calc. Benchmarks: LPCD 135 (LPCD sheet), EPI 8 (EPI sheet), PF 0.95 & deployment 90% (MIS_Calc B10:B11).

Sheet PerCapita_Pyramid
A1: AKA | B1: ▲ AGA KHAN ACADEMY | PER-CAPITA PERFORMANCE PYRAMID
A2: OFFICIAL MIS | B2: ="Live MIS data Jan-26 to "&MIS_Calc!$B$6&" • "&TEXT(MIS_Calc!$B$15,"#,##0")&" occupants (LPCD sheet) • "&TEXT(MIS_Calc!$B$7,"#,##0")&" m² • 100 = Avg-2025 baseline, above 100 = better" -> Live MIS data Jan-26 to Aug-26 • 1,354 occupants (LPCD sheet) • 52,652 m² • 100 = Avg-2025 baseline, above 100 = better
B4: MONTH | H4: ="Showing: "&MIS_Calc!$B$5&" | population base "&TEXT(MIS_Calc!$B$15,"#,##0")&" persons • "&TEXT(MIS_Calc!$B$14,"0.0")&" days" -> Showing: Aug-26 | population base 1,354 persons • 31.0 days
A5: FM Dashboard | B5: 📅 Select ▸ | D5: Aug-26 | H5: Per-person figures divide by campus occupants from the LPCD sheet; building pyramids use absolute kL / kWh per month (residence LPCD on FM_Dashboard uses the resident-student headcount in Building_Master). KPIs with no data for the month or no 2025 baseline are shown but not scored.
A7: ▶ Per-Capita Pyramid | B7: ▲ PERFORMANCE PYRAMID — apex index → pillars → categories → key per-capita KPIs → operational detail (score 100 = Avg-2025 • above 100 = better)
A9: Monthly KPI | B9: TIER 1 · APEX One composite score for the campus vs its own 2025 performance | K9: ▲ PER-CAPITA PERFORMANCE INDEX | R9: ="Scored on "&SUM(MIS_Calc!$L$279:$L$309)&" core per-capita KPIs across 6 domains"&CHAR(10)&MIS_Calc!E322 -> Scored on 18 core per-capita KPIs across 6 domains 8 better • 4 in line • 7 watch • 7 no data
K10: =IF(MIS_Calc!C322="","–",MIS_Calc!C322) -> 105.20448
A11: Complaints | K11: =MIS_Calc!D322 -> ✔ Better than 2025
K12: =IF(MIS_Calc!C322="","INDEX SCORE • 100 = Avg-2025","INDEX SCORE • 100 = Avg-2025 • "&TEXT(MIS_Calc!C322-100,"+0.0;-0.0;0")&" pts vs 2025") -> INDEX SCORE • 100 = Avg-2025 • +5.2 pts vs 2025
A13: Water - Bldg
B14: TIER 2 · PILLARS Utilities · Sustainability · Operations | H14: ⚡💧 UTILITIES | L14: ☀♻ SUSTAINABILITY | P14: 🛠 OPERATIONS | U14: Pillar = average of its two category scores Colour key (pillar → category → KPI tile → chart): Blue = Utilities • Green = Sustainability Purple = Operations
A15: LPCD | H15: =IF(MIS_Calc!C319="","–",MIS_Calc!C319) -> 121.90229 | L15: =IF(MIS_Calc!C320="","–",MIS_Calc!C320) -> 113.27106 | P15: =IF(MIS_Calc!C321="","–",MIS_Calc!C321) -> 80.44009
H16: =MIS_Calc!D319 -> ✔ Better than 2025 | L16: =MIS_Calc!D320 -> ✔ Better than 2025 | P16: =MIS_Calc!D321 -> ▲ Below 2025
A17: Water Quality | H17: ="PILLAR SCORE = avg(Energy, Water)" -> PILLAR SCORE = avg(Energy, Water) | L17: ="PILLAR SCORE = avg(Solar, Treatment)" -> PILLAR SCORE = avg(Solar, Treatment) | P17: ="PILLAR = avg(Service Desk, People & Cost)" -> PILLAR = avg(Service Desk, People & Cost)
A19: Power | B19: TIER 3 · CATEGORIES 6 MIS domains | E19: ⚡ ENERGY | H19: 💧 WATER | K19: ☀ SOLAR | N19: ♻ TREATMENT & REUSE | Q19: 🎫 SERVICE DESK | T19: 👷 PEOPLE & COST | W19: Score = avg of core KPI scores (each capped 50–150)
E20: =IF(MIS_Calc!C313="","–",MIS_Calc!C313) -> 93.80458 | H20: =IF(MIS_Calc!C314="","–",MIS_Calc!C314) -> 150 | K20: =IF(MIS_Calc!C315="","–",MIS_Calc!C315) -> 128.75928 | N20: =IF(MIS_Calc!C316="","–",MIS_Calc!C316) -> 97.782835 | Q20: =IF(MIS_Calc!C317="","–",MIS_Calc!C317) -> 58.796296 | T20: =IF(MIS_Calc!C318="","–",MIS_Calc!C318) -> 102.08388
A21: EPI | E21: =IF(MIS_Calc!F313="","no data this month",TEXT(MIS_Calc!F313,MIS_Calc!M279)&" kWh/p/mo") -> 108.1 kWh/p/mo | H21: =IF(MIS_Calc!F314="","no data this month",TEXT(MIS_Calc!F314,MIS_Calc!M286)&" LPCD") -> 334.2 LPCD | K21: =IF(MIS_Calc!F315="","no data this month",TEXT(MIS_Calc!F315,MIS_Calc!M292)&" kWh/p/mo") -> 85.6 kWh/p/mo | N21: =IF(MIS_Calc!F316="","no data this month",TEXT(MIS_Calc!F316,MIS_Calc!M288)&" L/p/day STP") -> 63.9 L/p/day STP | Q21: =IF(MIS_Calc!F317="","no data this month",TEXT(MIS_Calc!F317,MIS_Calc!M299)&" /100p/mo") -> 15.95 /100p/mo | T21: =IF(MIS_Calc!F318="",IF(MIS_Calc!C318="","no data this month","OPEX not yet invoiced"),TEXT(MIS_Calc!F318,MIS_Calc!M306)&" ₹ OPEX/p/mo") -> OPEX not yet invoiced
E22: ="SCORE • "&MIS_Calc!G313&" of "&COUNTIFS(MIS_Calc!$B$279:$B$309,MIS_Calc!B313,MIS_Calc!$L$279:$L$309,1)&" KPIs" -> SCORE • 5 of 5 KPIs | H22: ="SCORE • "&MIS_Calc!G314&" of "&COUNTIFS(MIS_Calc!$B$279:$B$309,MIS_Calc!B314,MIS_Calc!$L$279:$L$309,1)&" KPIs" -> SCORE • 2 of 2 KPIs | K22: ="SCORE • "&MIS_Calc!G315&" of "&COUNTIFS(MIS_Calc!$B$279:$B$309,MIS_Calc!B315,MIS_Calc!$L$279:$L$309,1)&" KPIs" -> SCORE • 2 of 2 KPIs | N22: ="SCORE • "&MIS_Calc!G316&" of "&COUNTIFS(MIS_Calc!$B$279:$B$309,MIS_Calc!B316,MIS_Calc!$L$279:$L$309,1)&" KPIs" -> SCORE • 2 of 2 KPIs | Q22: ="SCORE • "&MIS_Calc!G317&" of "&COUNTIFS(MIS_Calc!$B$279:$B$309,MIS_Calc!B317,MIS_Calc!$L$279:$L$309,1)&" KPIs" -> SCORE • 2 of 3 KPIs | T22: ="SCORE • "&MIS_Calc!G318&" of "&COUNTIFS(MIS_Calc!$B$279:$B$309,MIS_Calc!B318,MIS_Calc!$L$279:$L$309,1)&" KPIs" -> SCORE • 1 of 4 KPIs
A23: Power - Bldg
B24: TIER 4 · 12 KEY KPIs grouped by pillar — Utilities (6) · Sustainability (2) · Operations (4) (selected month / YTD average • Δ vs Avg-2025)
A25: Solar | B25: ⚡ Grid kWh | D25: ₹ Energy | F25: ❄ HVAC | H25: 🏢 EPI | J25: 💧 LPCD | L25: ⛲ Borewell | N25: ☀ Solar | P25: ♻ STP | R25: 🎫 Complaints | T25: ✅ Closure | V25: 💰 OPEX | X25: 👷 Staff
B26: =IF(MIS_Calc!E279="","–",MIS_Calc!E279) -> 108.11078 | D26: =IF(MIS_Calc!E280="","–",MIS_Calc!E280) -> 1351.2341 | F26: =IF(MIS_Calc!E282="","–",MIS_Calc!E282) -> 16.217046 | H26: =IF(MIS_Calc!E281="","–",MIS_Calc!E281) -> 2.7801652 | J26: =IF(MIS_Calc!E286="","–",MIS_Calc!E286) -> 334.15924 | L26: =IF(MIS_Calc!E287="","–",MIS_Calc!E287) -> 285.77214 | N26: =IF(MIS_Calc!E292="","–",MIS_Calc!E292) -> 85.606352 | P26: =IF(MIS_Calc!E288="","–",MIS_Calc!E288) -> 63.920522 | R26: =IF(MIS_Calc!E299="","–",MIS_Calc!E299) -> 15.952733 | T26: =IF(MIS_Calc!E300="","–",MIS_Calc!E300) -> 0.67592593 | V26: =IF(MIS_Calc!E306="","–",MIS_Calc!E306) -> – | X26: =IF(MIS_Calc!E308="","–",MIS_Calc!E308) -> 50.148148
A27: HVAC | B27: kWh/p/mo | D27: ₹/p/mo | F27: kWh/p/mo | H27: kWh/m²/mo | J27: L/p/day | L27: L/p/day | N27: kWh/p/mo | P27: L/p/day | R27: /100p/mo | T27: % closed | V27: ₹/p/mo | X27: persons/tech
B28: =IF(MIS_Calc!H279="","–",TEXT(MIS_Calc!H279,"+0%;-0%;0%")&" "&LEFT(MIS_Calc!J279,1)) -> +10% ▲ | D28: =IF(MIS_Calc!H280="","–",TEXT(MIS_Calc!H280,"+0%;-0%;0%")&" "&LEFT(MIS_Calc!J280,1)) -> +5% ▲ | F28: =IF(MIS_Calc!H282="","–",TEXT(MIS_Calc!H282,"+0%;-0%;0%")&" "&LEFT(MIS_Calc!J282,1)) -> +5% ● | H28: =IF(MIS_Calc!H281="","–",TEXT(MIS_Calc!H281,"+0%;-0%;0%")&" "&LEFT(MIS_Calc!J281,1)) -> +10% ▲ | J28: =IF(MIS_Calc!H286="","–",TEXT(MIS_Calc!H286,"+0%;-0%;0%")&" "&LEFT(MIS_Calc!J286,1)) -> -86% ✔ | L28: =IF(MIS_Calc!H287="","–",TEXT(MIS_Calc!H287,"+0%;-0%;0%")&" "&LEFT(MIS_Calc!J287,1)) -> -60% ✔ | N28: =IF(MIS_Calc!H292="","–",TEXT(MIS_Calc!H292,"+0%;-0%;0%")&" "&LEFT(MIS_Calc!J292,1)) -> +35% ✔ | P28: =IF(MIS_Calc!H288="","–",TEXT(MIS_Calc!H288,"+0%;-0%;0%")&" "&LEFT(MIS_Calc!J288,1)) -> -42% ▲ | R28: =IF(MIS_Calc!H299="","–",TEXT(MIS_Calc!H299,"+0%;-0%;0%")&" "&LEFT(MIS_Calc!J299,1)) -> +154% ▲ | T28: =IF(MIS_Calc!H300="","–",TEXT(MIS_Calc!H300,"+0%;-0%;0%")&" "&LEFT(MIS_Calc!J300,1)) -> -32% ▲ | V28: =IF(MIS_Calc!H306="","–",TEXT(MIS_Calc!H306,"+0%;-0%;0%")&" "&LEFT(MIS_Calc!J306,1)) -> – | X28: =IF(MIS_Calc!H308="","–",TEXT(MIS_Calc!H308,"+0%;-0%;0%")&" "&LEFT(MIS_Calc!J308,1)) -> –
A29: DG / Outages | B29: =IF(OR(MIS_Calc!F279="",MIS_Calc!F279="–"),"2025 avg: –","2025 avg: "&TEXT(MIS_Calc!F279,MIS_Calc!M279)) -> 2025 avg: 98.1 | D29: =IF(OR(MIS_Calc!F280="",MIS_Calc!F280="–"),"2025 avg: –","2025 avg: "&TEXT(MIS_Calc!F280,MIS_Calc!M280)) -> 2025 avg: 1,286 | F29: =IF(OR(MIS_Calc!F282="",MIS_Calc!F282="–"),"2025 avg: –","2025 avg: "&TEXT(MIS_Calc!F282,MIS_Calc!M282)) -> 2025 avg: 15.46 | H29: =IF(OR(MIS_Calc!F281="",MIS_Calc!F281="–"),"2025 avg: –","2025 avg: "&TEXT(MIS_Calc!F281,MIS_Calc!M281)) -> 2025 avg: 2.52 | J29: =IF(OR(MIS_Calc!F286="",MIS_Calc!F286="–"),"2025 avg: –","2025 avg: "&TEXT(MIS_Calc!F286,MIS_Calc!M286)) -> 2025 avg: 2432.2 | L29: =IF(OR(MIS_Calc!F287="",MIS_Calc!F287="–"),"2025 avg: –","2025 avg: "&TEXT(MIS_Calc!F287,MIS_Calc!M287)) -> 2025 avg: 718.3 | N29: =IF(OR(MIS_Calc!F292="",MIS_Calc!F292="–"),"2025 avg: –","2025 avg: "&TEXT(MIS_Calc!F292,MIS_Calc!M292)) -> 2025 avg: 63.4 | P29: =IF(OR(MIS_Calc!F288="",MIS_Calc!F288="–"),"2025 avg: –","2025 avg: "&TEXT(MIS_Calc!F288,MIS_Calc!M288)) -> 2025 avg: 110.1 | R29: =IF(OR(MIS_Calc!F299="",MIS_Calc!F299="–"),"2025 avg: –","2025 avg: "&TEXT(MIS_Calc!F299,MIS_Calc!M299)) -> 2025 avg: 6.28 | T29: =IF(OR(MIS_Calc!F300="",MIS_Calc!F300="–"),"2025 avg: –","2025 avg: "&TEXT(MIS_Calc!F300,MIS_Calc!M300)) -> 2025 avg: 100.0% | V29: =IF(OR(MIS_Calc!F306="",MIS_Calc!F306="–"),"2025 avg: –","2025 avg: "&TEXT(MIS_Calc!F306,MIS_Calc!M306)) -> 2025 avg: 1,840 | X29: =IF(OR(MIS_Calc!F308="",MIS_Calc!F308="–"),"2025 avg: –","2025 avg: "&TEXT(MIS_Calc!F308,MIS_Calc!M308)) -> 2025 avg: –
A31: Tech Manpower | B31: TIER 5 · OPERATIONAL DETAIL — pyramids (apex = smallest of the top-10) & butterflies (back-to-back comparisons)
A33: Attendance
A35: Building Master
A37: Calc engine
B93: 💧 WATER HEATMAP — building meter × month (kL) • darker red = higher use • Δ vs median 2023–25 baseline
B94: Building | F94: Jan-26 | G94: Feb-26 | H94: Mar-26 | I94: Apr-26 | J94: May-26 | K94: Jun-26 | L94: Jul-26 | M94: Aug-26 | N94: Sep-26 | O94: Oct-26 | P94: Nov-26 | Q94: Dec-26 | R94: Avg 2026 | T94: Baseline | V94: Δ | X94: Share
B95: =MIS_Calc!A112 -> SR-1 | F95: =IF(MIS_Calc!C112="","",MIS_Calc!C112) -> 264 | G95: =IF(MIS_Calc!D112="","",MIS_Calc!D112) -> 239 | H95: =IF(MIS_Calc!E112="","",MIS_Calc!E112) -> 280 | I95: =IF(MIS_Calc!F112="","",MIS_Calc!F112) -> 201 | J95: =IF(MIS_Calc!G112="","",MIS_Calc!G112) -> 189 | K95: =IF(MIS_Calc!H112="","",MIS_Calc!H112) -> 91 | L95: =IF(MIS_Calc!I112="","",MIS_Calc!I112) -> 224 | M95: =IF(MIS_Calc!J112="","",MIS_Calc!J112) -> 329 | ... Q95: =IF(MIS_Calc!N112="","",MIS_Calc!N112) | R95: =MIS_Calc!W112 -> 227.125 | T95: =IF(MIS_Calc!P112="","–",MIS_Calc!P112) -> 388.5 | V95: =IFERROR(IF(OR(MIS_Calc!W112="",MIS_Calc!P112="",MIS_Calc!P112=0),"–",MIS_Calc!W112/MIS_Calc!P112-1),"–") -> -0.41537967 | X95: =IFERROR(MIS_Calc!W112/SUM(MIS_Calc!$W$112:$W$131),"–") -> 0.04952708
B96: =MIS_Calc!A113 -> SR-2 | F96: =IF(MIS_Calc!C113="","",MIS_Calc!C113) -> 267 | G96: =IF(MIS_Calc!D113="","",MIS_Calc!D113) -> 427 | H96: =IF(MIS_Calc!E113="","",MIS_Calc!E113) -> 111 | I96: =IF(MIS_Calc!F113="","",MIS_Calc!F113) -> 100 | J96: =IF(MIS_Calc!G113="","",MIS_Calc!G113) -> 102 | K96: =IF(MIS_Calc!H113="","",MIS_Calc!H113) -> 87 | L96: =IF(MIS_Calc!I113="","",MIS_Calc!I113) -> 125 | M96: =IF(MIS_Calc!J113="","",MIS_Calc!J113) -> 312 | ... Q96: =IF(MIS_Calc!N113="","",MIS_Calc!N113) | R96: =MIS_Calc!W113 -> 191.375 | T96: =IF(MIS_Calc!P113="","–",MIS_Calc!P113) -> 199.33333 | V96: =IFERROR(IF(OR(MIS_Calc!W113="",MIS_Calc!P113="",MIS_Calc!P113=0),"–",MIS_Calc!W113/MIS_Calc!P113-1),"–") -> -0.039924749 | X96: =IFERROR(MIS_Calc!W113/SUM(MIS_Calc!$W$112:$W$131),"–") -> 0.041731403
B97: =MIS_Calc!A114 -> SR-3 | F97: =IF(MIS_Calc!C114="","",MIS_Calc!C114) -> 205 | G97: =IF(MIS_Calc!D114="","",MIS_Calc!D114) -> 111 | H97: =IF(MIS_Calc!E114="","",MIS_Calc!E114) -> 8 | I97: =IF(MIS_Calc!F114="","",MIS_Calc!F114) -> 60 | J97: =IF(MIS_Calc!G114="","",MIS_Calc!G114) -> 58 | K97: =IF(MIS_Calc!H114="","",MIS_Calc!H114) -> 60 | L97: =IF(MIS_Calc!I114="","",MIS_Calc!I114) -> 62 | M97: =IF(MIS_Calc!J114="","",MIS_Calc!J114) -> 64 | ... Q97: =IF(MIS_Calc!N114="","",MIS_Calc!N114) | R97: =MIS_Calc!W114 -> 78.5 | T97: =IF(MIS_Calc!P114="","–",MIS_Calc!P114) -> 171.33333 | V97: =IFERROR(IF(OR(MIS_Calc!W114="",MIS_Calc!P114="",MIS_Calc!P114=0),"–",MIS_Calc!W114/MIS_Calc!P114-1),"–") -> -0.54182879 | X97: =IFERROR(MIS_Calc!W114/SUM(MIS_Calc!$W$112:$W$131),"–") -> 0.01711778
B98: =MIS_Calc!A115 -> SR-4 | F98: =IF(MIS_Calc!C115="","",MIS_Calc!C115) -> 136 | G98: =IF(MIS_Calc!D115="","",MIS_Calc!D115) -> 136 | H98: =IF(MIS_Calc!E115="","",MIS_Calc!E115) -> 337 | I98: =IF(MIS_Calc!F115="","",MIS_Calc!F115) -> 337 | J98: =IF(MIS_Calc!G115="","",MIS_Calc!G115) -> 233 | K98: =IF(MIS_Calc!H115="","",MIS_Calc!H115) -> 221 | L98: =IF(MIS_Calc!I115="","",MIS_Calc!I115) -> 146 | M98: =IF(MIS_Calc!J115="","",MIS_Calc!J115) -> 194 | ... Q98: =IF(MIS_Calc!N115="","",MIS_Calc!N115) | R98: =MIS_Calc!W115 -> 217.5 | T98: =IF(MIS_Calc!P115="","–",MIS_Calc!P115) -> 162.08333 | V98: =IFERROR(IF(OR(MIS_Calc!W115="",MIS_Calc!P115="",MIS_Calc!P115=0),"–",MIS_Calc!W115/MIS_Calc!P115-1),"–") -> 0.34190231 | X98: =IFERROR(MIS_Calc!W115/SUM(MIS_Calc!$W$112:$W$131),"–") -> 0.047428244
B99: =MIS_Calc!A116 -> SR-9-10B1A | F99: =IF(MIS_Calc!C116="","",MIS_Calc!C116) -> 568 | G99: =IF(MIS_Calc!D116="","",MIS_Calc!D116) -> 716 | H99: =IF(MIS_Calc!E116="","",MIS_Calc!E116) -> 835 | I99: =IF(MIS_Calc!F116="","",MIS_Calc!F116) -> 1045 | J99: =IF(MIS_Calc!G116="","",MIS_Calc!G116) -> 781 | K99: =IF(MIS_Calc!H116="","",MIS_Calc!H116) -> 279 | L99: =IF(MIS_Calc!I116="","",MIS_Calc!I116) -> 1320 | M99: =IF(MIS_Calc!J116="","",MIS_Calc!J116) -> 1468 | ... Q99: =IF(MIS_Calc!N116="","",MIS_Calc!N116) | R99: =MIS_Calc!W116 -> 876.5 | T99: =IF(MIS_Calc!P116="","–",MIS_Calc!P116) -> 458.75 | V99: =IFERROR(IF(OR(MIS_Calc!W116="",MIS_Calc!P116="",MIS_Calc!P116=0),"–",MIS_Calc!W116/MIS_Calc!P116-1),"–") -> 0.9106267 | X99: =IFERROR(MIS_Calc!W116/SUM(MIS_Calc!$W$112:$W$131),"–") -> 0.19113037
B100: =MIS_Calc!A117 -> SR-9-10B1B | F100: =IF(MIS_Calc!C117="","",MIS_Calc!C117) -> 209 | G100: =IF(MIS_Calc!D117="","",MIS_Calc!D117) -> 73 | H100: =IF(MIS_Calc!E117="","",MIS_Calc!E117) -> 268 | I100: =IF(MIS_Calc!F117="","",MIS_Calc!F117) -> 149 | J100: =IF(MIS_Calc!G117="","",MIS_Calc!G117) -> 167 | K100: =IF(MIS_Calc!H117="","",MIS_Calc!H117) -> 46 | L100: =IF(MIS_Calc!I117="","",MIS_Calc!I117) -> 42 | M100: =IF(MIS_Calc!J117="","",MIS_Calc!J117) -> 45 | ... Q100: =IF(MIS_Calc!N117="","",MIS_Calc!N117) | R100: =MIS_Calc!W117 -> 124.875 | T100: =IF(MIS_Calc!P117="","–",MIS_Calc!P117) -> 454.25 | V100: =IFERROR(IF(OR(MIS_Calc!W117="",MIS_Calc!P117="",MIS_Calc!P117=0),"–",MIS_Calc!W117/MIS_Calc!P117-1),"–") -> -0.72509631 | X100: =IFERROR(MIS_Calc!W117/SUM(MIS_Calc!$W$112:$W$131),"–") -> 0.027230354
B101: =MIS_Calc!A118 -> SR-11-12CA | F101: =IF(MIS_Calc!C118="","",MIS_Calc!C118) -> 233 | G101: =IF(MIS_Calc!D118="","",MIS_Calc!D118) -> 285 | H101: =IF(MIS_Calc!E118="","",MIS_Calc!E118) -> 337 | I101: =IF(MIS_Calc!F118="","",MIS_Calc!F118) -> 377 | J101: =IF(MIS_Calc!G118="","",MIS_Calc!G118) -> 358 | K101: =IF(MIS_Calc!H118="","",MIS_Calc!H118) -> 200 | L101: =IF(MIS_Calc!I118="","",MIS_Calc!I118) -> 647 | M101: =IF(MIS_Calc!J118="","",MIS_Calc!J118) -> 710 | ... Q101: =IF(MIS_Calc!N118="","",MIS_Calc!N118) | R101: =MIS_Calc!W118 -> 393.375 | T101: =IF(MIS_Calc!P118="","–",MIS_Calc!P118) -> 341.25 | V101: =IFERROR(IF(OR(MIS_Calc!W118="",MIS_Calc!P118="",MIS_Calc!P118=0),"–",MIS_Calc!W118/MIS_Calc!P118-1),"–") -> 0.15274725 | X101: =IFERROR(MIS_Calc!W118/SUM(MIS_Calc!$W$112:$W$131),"–") -> 0.085779704
B102: =MIS_Calc!A119 -> SR-11-12CB | F102: =IF(MIS_Calc!C119="","",MIS_Calc!C119) -> 0 | G102: =IF(MIS_Calc!D119="","",MIS_Calc!D119) -> 101 | H102: =IF(MIS_Calc!E119="","",MIS_Calc!E119) -> 450 | I102: =IF(MIS_Calc!F119="","",MIS_Calc!F119) -> 399 | J102: =IF(MIS_Calc!G119="","",MIS_Calc!G119) -> 205 | K102: =IF(MIS_Calc!H119="","",MIS_Calc!H119) -> 50 | L102: =IF(MIS_Calc!I119="","",MIS_Calc!I119) -> 0 | M102: =IF(MIS_Calc!J119="","",MIS_Calc!J119) -> 0 | ... Q102: =IF(MIS_Calc!N119="","",MIS_Calc!N119) | R102: =MIS_Calc!W119 -> 150.625 | T102: =IF(MIS_Calc!P119="","–",MIS_Calc!P119) -> 463.08333 | V102: =IFERROR(IF(OR(MIS_Calc!W119="",MIS_Calc!P119="",MIS_Calc!P119=0),"–",MIS_Calc!W119/MIS_Calc!P119-1),"–") -> -0.67473457 | X102: =IFERROR(MIS_Calc!W119/SUM(MIS_Calc!$W$112:$W$131),"–") -> 0.032845422
B103: =MIS_Calc!A120 -> Junior School-1&2 | F103: =IF(MIS_Calc!C120="","",MIS_Calc!C120) -> 0 | G103: =IF(MIS_Calc!D120="","",MIS_Calc!D120) -> 0 | H103: =IF(MIS_Calc!E120="","",MIS_Calc!E120) -> 1 | I103: =IF(MIS_Calc!F120="","",MIS_Calc!F120) -> 0 | J103: =IF(MIS_Calc!G120="","",MIS_Calc!G120) -> 0 | K103: =IF(MIS_Calc!H120="","",MIS_Calc!H120) -> 1 | L103: =IF(MIS_Calc!I120="","",MIS_Calc!I120) -> 0 | M103: =IF(MIS_Calc!J120="","",MIS_Calc!J120) -> 0 | ... Q103: =IF(MIS_Calc!N120="","",MIS_Calc!N120) | R103: =MIS_Calc!W120 -> 0.25 | T103: =IF(MIS_Calc!P120="","–",MIS_Calc!P120) -> 204.33333 | V103: =IFERROR(IF(OR(MIS_Calc!W120="",MIS_Calc!P120="",MIS_Calc!P120=0),"–",MIS_Calc!W120/MIS_Calc!P120-1),"–") -> -0.99877651 | X103: =IFERROR(MIS_Calc!W120/SUM(MIS_Calc!$W$112:$W$131),"–") -> 5.4515223e-05
B104: =MIS_Calc!A121 -> Junior School-3 | F104: =IF(MIS_Calc!C121="","",MIS_Calc!C121) -> 27 | G104: =IF(MIS_Calc!D121="","",MIS_Calc!D121) -> 22 | H104: =IF(MIS_Calc!E121="","",MIS_Calc!E121) -> 40 | I104: =IF(MIS_Calc!F121="","",MIS_Calc!F121) -> 25 | J104: =IF(MIS_Calc!G121="","",MIS_Calc!G121) -> 28 | K104: =IF(MIS_Calc!H121="","",MIS_Calc!H121) -> 7 | L104: =IF(MIS_Calc!I121="","",MIS_Calc!I121) -> 87 | M104: =IF(MIS_Calc!J121="","",MIS_Calc!J121) -> 120 | ... Q104: =IF(MIS_Calc!N121="","",MIS_Calc!N121) | R104: =MIS_Calc!W121 -> 44.5 | T104: =IF(MIS_Calc!P121="","–",MIS_Calc!P121) -> 308.66667 | V104: =IFERROR(IF(OR(MIS_Calc!W121="",MIS_Calc!P121="",MIS_Calc!P121=0),"–",MIS_Calc!W121/MIS_Calc!P121-1),"–") -> -0.85583153 | X104: =IFERROR(MIS_Calc!W121/SUM(MIS_Calc!$W$112:$W$131),"–") -> 0.0097037098
B105: =MIS_Calc!A122 -> Senior School-1 | F105: =IF(MIS_Calc!C122="","",MIS_Calc!C122) -> 101 | G105: =IF(MIS_Calc!D122="","",MIS_Calc!D122) -> 50 | H105: =IF(MIS_Calc!E122="","",MIS_Calc!E122) -> 61 | I105: =IF(MIS_Calc!F122="","",MIS_Calc!F122) -> 90 | J105: =IF(MIS_Calc!G122="","",MIS_Calc!G122) -> 7 | K105: =IF(MIS_Calc!H122="","",MIS_Calc!H122) -> 0 | L105: =IF(MIS_Calc!I122="","",MIS_Calc!I122) -> 78 | M105: =IF(MIS_Calc!J122="","",MIS_Calc!J122) -> 82 | ... Q105: =IF(MIS_Calc!N122="","",MIS_Calc!N122) | R105: =MIS_Calc!W122 -> 58.625 | T105: =IF(MIS_Calc!P122="","–",MIS_Calc!P122) -> 367.5 | V105: =IFERROR(IF(OR(MIS_Calc!W122="",MIS_Calc!P122="",MIS_Calc!P122=0),"–",MIS_Calc!W122/MIS_Calc!P122-1),"–") -> -0.84047619 | X105: =IFERROR(MIS_Calc!W122/SUM(MIS_Calc!$W$112:$W$131),"–") -> 0.01278382
B106: =MIS_Calc!A123 -> Senior School-2 | F106: =IF(MIS_Calc!C123="","",MIS_Calc!C123) -> 33 | G106: =IF(MIS_Calc!D123="","",MIS_Calc!D123) -> 41 | H106: =IF(MIS_Calc!E123="","",MIS_Calc!E123) -> 15 | I106: =IF(MIS_Calc!F123="","",MIS_Calc!F123) -> 121 | J106: =IF(MIS_Calc!G123="","",MIS_Calc!G123) -> 272 | K106: =IF(MIS_Calc!H123="","",MIS_Calc!H123) -> 5 | L106: =IF(MIS_Calc!I123="","",MIS_Calc!I123) -> 26 | M106: =IF(MIS_Calc!J123="","",MIS_Calc!J123) -> 45 | ... Q106: =IF(MIS_Calc!N123="","",MIS_Calc!N123) | R106: =MIS_Calc!W123 -> 69.75 | T106: =IF(MIS_Calc!P123="","–",MIS_Calc!P123) -> 33.833333 | V106: =IFERROR(IF(OR(MIS_Calc!W123="",MIS_Calc!P123="",MIS_Calc!P123=0),"–",MIS_Calc!W123/MIS_Calc!P123-1),"–") -> 1.0615764 | X106: =IFERROR(MIS_Calc!W123/SUM(MIS_Calc!$W$112:$W$131),"–") -> 0.015209747
... B114: =MIS_Calc!A131 -> Laundry | F114: =IF(MIS_Calc!C131="","",MIS_Calc!C131) -> 94 | G114: =IF(MIS_Calc!D131="","",MIS_Calc!D131) -> 98 | H114: =IF(MIS_Calc!E131="","",MIS_Calc!E131) -> 104 | I114: =IF(MIS_Calc!F131="","",MIS_Calc!F131) -> 15 | J114: =IF(MIS_Calc!G131="","",MIS_Calc!G131) -> 87 | K114: =IF(MIS_Calc!H131="","",MIS_Calc!H131) -> 68 | L114: =IF(MIS_Calc!I131="","",MIS_Calc!I131) -> 89 | M114: =IF(MIS_Calc!J131="","",MIS_Calc!J131) -> 135 | ... Q114: =IF(MIS_Calc!N131="","",MIS_Calc!N131) | R114: =MIS_Calc!W131 -> 86.25 | T114: =IF(MIS_Calc!P131="","–",MIS_Calc!P131) -> – | V114: =IFERROR(IF(OR(MIS_Calc!W131="",MIS_Calc!P131="",MIS_Calc!P131=0),"–",MIS_Calc!W131/MIS_Calc!P131-1),"–") -> – | X114: =IFERROR(MIS_Calc!W131/SUM(MIS_Calc!$W$112:$W$131),"–") -> 0.018807752
B117: ⚡ POWER HEATMAP — building meter × month (kWh) • darker red = higher use • Δ vs Avg-2025
B118: Building | F118: Jan-26 | G118: Feb-26 | H118: Mar-26 | I118: Apr-26 | J118: May-26 | K118: Jun-26 | L118: Jul-26 | M118: Aug-26 | N118: Sep-26 | O118: Oct-26 | P118: Nov-26 | Q118: Dec-26 | R118: Avg 2026 | T118: Avg 2025 | V118: Δ | X118: Share
B119: =MIS_Calc!A136 -> SR1,2,3&4 Emergency | F119: =IF(MIS_Calc!C136="","",MIS_Calc!C136) -> 480 | G119: =IF(MIS_Calc!D136="","",MIS_Calc!D136) -> 525 | H119: =IF(MIS_Calc!E136="","",MIS_Calc!E136) -> 675 | I119: =IF(MIS_Calc!F136="","",MIS_Calc!F136) -> 653 | J119: =IF(MIS_Calc!G136="","",MIS_Calc!G136) -> 647 | K119: =IF(MIS_Calc!H136="","",MIS_Calc!H136) -> 573 | L119: =IF(MIS_Calc!I136="","",MIS_Calc!I136) -> 631 | M119: =IF(MIS_Calc!J136="","",MIS_Calc!J136) -> 815 | ... Q119: =IF(MIS_Calc!N136="","",MIS_Calc!N136) | R119: =MIS_Calc!W136 -> 624.875 | T119: =IF(MIS_Calc!O136="","–",MIS_Calc!O136) -> 537.83333 | V119: =IFERROR(IF(OR(MIS_Calc!W136="",MIS_Calc!O136="",MIS_Calc!O136=0),"–",MIS_Calc!W136/MIS_Calc!O136-1),"–") -> 0.16183762 | X119: =IFERROR(MIS_Calc!W136/SUM(MIS_Calc!$W$136:$W$160),"–") -> 0.0039646341
B120: =MIS_Calc!A137 -> SR 9&10A,B 11-12A,B Emergency | F120: =IF(MIS_Calc!C137="","",MIS_Calc!C137) -> 1154 | G120: =IF(MIS_Calc!D137="","",MIS_Calc!D137) -> 1119 | H120: =IF(MIS_Calc!E137="","",MIS_Calc!E137) -> 1257 | I120: =IF(MIS_Calc!F137="","",MIS_Calc!F137) -> 1253 | J120: =IF(MIS_Calc!G137="","",MIS_Calc!G137) -> 1203 | K120: =IF(MIS_Calc!H137="","",MIS_Calc!H137) -> 1054 | L120: =IF(MIS_Calc!I137="","",MIS_Calc!I137) -> 1234 | M120: =IF(MIS_Calc!J137="","",MIS_Calc!J137) -> 1331 | ... Q120: =IF(MIS_Calc!N137="","",MIS_Calc!N137) | R120: =MIS_Calc!W137 -> 1200.625 | T120: =IF(MIS_Calc!O137="","–",MIS_Calc!O137) -> 1150.25 | V120: =IFERROR(IF(OR(MIS_Calc!W137="",MIS_Calc!O137="",MIS_Calc!O137=0),"–",MIS_Calc!W137/MIS_Calc!O137-1),"–") -> 0.043794827 | X120: =IFERROR(MIS_Calc!W137/SUM(MIS_Calc!$W$136:$W$160),"–") -> 0.0076175856
B121: =MIS_Calc!A138 -> Laundry | F121: =IF(MIS_Calc!C138="","",MIS_Calc!C138) -> 2447 | G121: =IF(MIS_Calc!D138="","",MIS_Calc!D138) -> 2920 | H121: =IF(MIS_Calc!E138="","",MIS_Calc!E138) -> 3006 | I121: =IF(MIS_Calc!F138="","",MIS_Calc!F138) -> 3383 | J121: =IF(MIS_Calc!G138="","",MIS_Calc!G138) -> 2839 | K121: =IF(MIS_Calc!H138="","",MIS_Calc!H138) -> 2202 | L121: =IF(MIS_Calc!I138="","",MIS_Calc!I138) -> 2875 | M121: =IF(MIS_Calc!J138="","",MIS_Calc!J138) -> 3382 | ... Q121: =IF(MIS_Calc!N138="","",MIS_Calc!N138) | R121: =MIS_Calc!W138 -> 2881.75 | T121: =IF(MIS_Calc!O138="","–",MIS_Calc!O138) -> 2706.5 | V121: =IFERROR(IF(OR(MIS_Calc!W138="",MIS_Calc!O138="",MIS_Calc!O138=0),"–",MIS_Calc!W138/MIS_Calc!O138-1),"–") -> 0.064751524 | X121: =IFERROR(MIS_Calc!W138/SUM(MIS_Calc!$W$136:$W$160),"–") -> 0.018283792
B122: =MIS_Calc!A139 -> Substation | F122: =IF(MIS_Calc!C139="","",MIS_Calc!C139) -> 436 | G122: =IF(MIS_Calc!D139="","",MIS_Calc!D139) -> 602 | H122: =IF(MIS_Calc!E139="","",MIS_Calc!E139) -> 993.3 | I122: =IF(MIS_Calc!F139="","",MIS_Calc!F139) -> 961.7 | J122: =IF(MIS_Calc!G139="","",MIS_Calc!G139) -> 1173 | K122: =IF(MIS_Calc!H139="","",MIS_Calc!H139) -> 1030 | L122: =IF(MIS_Calc!I139="","",MIS_Calc!I139) -> 836 | M122: =IF(MIS_Calc!J139="","",MIS_Calc!J139) -> 933 | ... Q122: =IF(MIS_Calc!N139="","",MIS_Calc!N139) | R122: =MIS_Calc!W139 -> 870.625 | T122: =IF(MIS_Calc!O139="","–",MIS_Calc!O139) -> 667.50833 | V122: =IFERROR(IF(OR(MIS_Calc!W139="",MIS_Calc!O139="",MIS_Calc!O139=0),"–",MIS_Calc!W139/MIS_Calc!O139-1),"–") -> 0.30429083 | X122: =IFERROR(MIS_Calc!W139/SUM(MIS_Calc!$W$136:$W$160),"–") -> 0.0055238401
B123: =MIS_Calc!A140 -> SR-1 | F123: =IF(MIS_Calc!C140="","",MIS_Calc!C140) -> 2273 | G123: =IF(MIS_Calc!D140="","",MIS_Calc!D140) -> 3173 | H123: =IF(MIS_Calc!E140="","",MIS_Calc!E140) -> 4616 | I123: =IF(MIS_Calc!F140="","",MIS_Calc!F140) -> 6151 | J123: =IF(MIS_Calc!G140="","",MIS_Calc!G140) -> 5274 | K123: =IF(MIS_Calc!H140="","",MIS_Calc!H140) -> 2391 | L123: =IF(MIS_Calc!I140="","",MIS_Calc!I140) -> 4289 | M123: =IF(MIS_Calc!J140="","",MIS_Calc!J140) -> 4790 | ... Q123: =IF(MIS_Calc!N140="","",MIS_Calc!N140) | R123: =MIS_Calc!W140 -> 4119.625 | T123: =IF(MIS_Calc!O140="","–",MIS_Calc!O140) -> 2632 | V123: =IFERROR(IF(OR(MIS_Calc!W140="",MIS_Calc!O140="",MIS_Calc!O140=0),"–",MIS_Calc!W140/MIS_Calc!O140-1),"–") -> 0.56520707 | X123: =IFERROR(MIS_Calc!W140/SUM(MIS_Calc!$W$136:$W$160),"–") -> 0.026137717
B124: =MIS_Calc!A141 -> SR-2 | F124: =IF(MIS_Calc!C141="","",MIS_Calc!C141) -> 2426 | G124: =IF(MIS_Calc!D141="","",MIS_Calc!D141) -> 2719 | H124: =IF(MIS_Calc!E141="","",MIS_Calc!E141) -> 4525 | I124: =IF(MIS_Calc!F141="","",MIS_Calc!F141) -> 6080 | J124: =IF(MIS_Calc!G141="","",MIS_Calc!G141) -> 7229 | K124: =IF(MIS_Calc!H141="","",MIS_Calc!H141) -> 2576 | L124: =IF(MIS_Calc!I141="","",MIS_Calc!I141) -> 3615 | M124: =IF(MIS_Calc!J141="","",MIS_Calc!J141) -> 4692 | ... Q124: =IF(MIS_Calc!N141="","",MIS_Calc!N141) | R124: =MIS_Calc!W141 -> 4232.75 | T124: =IF(MIS_Calc!O141="","–",MIS_Calc!O141) -> 3026.4167 | V124: =IFERROR(IF(OR(MIS_Calc!W141="",MIS_Calc!O141="",MIS_Calc!O141=0),"–",MIS_Calc!W141/MIS_Calc!O141-1),"–") -> 0.39860121 | X124: =IFERROR(MIS_Calc!W141/SUM(MIS_Calc!$W$136:$W$160),"–") -> 0.026855459
B125: =MIS_Calc!A142 -> SR-3 | F125: =IF(MIS_Calc!C142="","",MIS_Calc!C142) -> 1858 | G125: =IF(MIS_Calc!D142="","",MIS_Calc!D142) -> 3608 | H125: =IF(MIS_Calc!E142="","",MIS_Calc!E142) -> 3486 | I125: =IF(MIS_Calc!F142="","",MIS_Calc!F142) -> 4748 | J125: =IF(MIS_Calc!G142="","",MIS_Calc!G142) -> 4922 | K125: =IF(MIS_Calc!H142="","",MIS_Calc!H142) -> 2227 | L125: =IF(MIS_Calc!I142="","",MIS_Calc!I142) -> 4090 | M125: =IF(MIS_Calc!J142="","",MIS_Calc!J142) -> 5092 | ... Q125: =IF(MIS_Calc!N142="","",MIS_Calc!N142) | R125: =MIS_Calc!W142 -> 3753.875 | T125: =IF(MIS_Calc!O142="","–",MIS_Calc!O142) -> 3216.8333 | V125: =IFERROR(IF(OR(MIS_Calc!W142="",MIS_Calc!O142="",MIS_Calc!O142=0),"–",MIS_Calc!W142/MIS_Calc!O142-1),"–") -> 0.16694731 | X125: =IFERROR(MIS_Calc!W142/SUM(MIS_Calc!$W$136:$W$160),"–") -> 0.023817149
B126: =MIS_Calc!A143 -> SR-4 | F126: =IF(MIS_Calc!C143="","",MIS_Calc!C143) -> 3035 | G126: =IF(MIS_Calc!D143="","",MIS_Calc!D143) -> 5027 | H126: =IF(MIS_Calc!E143="","",MIS_Calc!E143) -> 7021 | I126: =IF(MIS_Calc!F143="","",MIS_Calc!F143) -> 9892 | J126: =IF(MIS_Calc!G143="","",MIS_Calc!G143) -> 10722 | K126: =IF(MIS_Calc!H143="","",MIS_Calc!H143) -> 2915 | L126: =IF(MIS_Calc!I143="","",MIS_Calc!I143) -> 6848 | M126: =IF(MIS_Calc!J143="","",MIS_Calc!J143) -> 6408 | ... Q126: =IF(MIS_Calc!N143="","",MIS_Calc!N143) | R126: =MIS_Calc!W143 -> 6483.5 | T126: =IF(MIS_Calc!O143="","–",MIS_Calc!O143) -> 3604.75 | V126: =IFERROR(IF(OR(MIS_Calc!W143="",MIS_Calc!O143="",MIS_Calc!O143=0),"–",MIS_Calc!W143/MIS_Calc!O143-1),"–") -> 0.79859907 | X126: =IFERROR(MIS_Calc!W143/SUM(MIS_Calc!$W$136:$W$160),"–") -> 0.041135755
B127: =MIS_Calc!A144 -> SR-9-10A | F127: =IF(MIS_Calc!C144="","",MIS_Calc!C144) -> 2936 | G127: =IF(MIS_Calc!D144="","",MIS_Calc!D144) -> 4122 | H127: =IF(MIS_Calc!E144="","",MIS_Calc!E144) -> 8610 | I127: =IF(MIS_Calc!F144="","",MIS_Calc!F144) -> 13623 | J127: =IF(MIS_Calc!G144="","",MIS_Calc!G144) -> 4475 | K127: =IF(MIS_Calc!H144="","",MIS_Calc!H144) -> 2951 | L127: =IF(MIS_Calc!I144="","",MIS_Calc!I144) -> 3693 | M127: =IF(MIS_Calc!J144="","",MIS_Calc!J144) -> 3576 | ... Q127: =IF(MIS_Calc!N144="","",MIS_Calc!N144) | R127: =MIS_Calc!W144 -> 5498.25 | T127: =IF(MIS_Calc!O144="","–",MIS_Calc!O144) -> 5664.7667 | V127: =IFERROR(IF(OR(MIS_Calc!W144="",MIS_Calc!O144="",MIS_Calc!O144=0),"–",MIS_Calc!W144/MIS_Calc!O144-1),"–") -> -0.02939515 | X127: =IFERROR(MIS_Calc!W144/SUM(MIS_Calc!$W$136:$W$160),"–") -> 0.034884656
B128: =MIS_Calc!A145 -> SR-9-10B | F128: =IF(MIS_Calc!C145="","",MIS_Calc!C145) -> 4053 | G128: =IF(MIS_Calc!D145="","",MIS_Calc!D145) -> 6416 | H128: =IF(MIS_Calc!E145="","",MIS_Calc!E145) -> 9833 | I128: =IF(MIS_Calc!F145="","",MIS_Calc!F145) -> 14587 | J128: =IF(MIS_Calc!G145="","",MIS_Calc!G145) -> 12517 | K128: =IF(MIS_Calc!H145="","",MIS_Calc!H145) -> 1965 | L128: =IF(MIS_Calc!I145="","",MIS_Calc!I145) -> 5778 | M128: =IF(MIS_Calc!J145="","",MIS_Calc!J145) -> 12306 | ... Q128: =IF(MIS_Calc!N145="","",MIS_Calc!N145) | R128: =MIS_Calc!W145 -> 8431.875 | T128: =IF(MIS_Calc!O145="","–",MIS_Calc!O145) -> 5468.95 | V128: =IFERROR(IF(OR(MIS_Calc!W145="",MIS_Calc!O145="",MIS_Calc!O145=0),"–",MIS_Calc!W145/MIS_Calc!O145-1),"–") -> 0.54177219 | X128: =IFERROR(MIS_Calc!W145/SUM(MIS_Calc!$W$136:$W$160),"–") -> 0.053497578
B129: =MIS_Calc!A146 -> SR-11-12CA | F129: =IF(MIS_Calc!C146="","",MIS_Calc!C146) -> 3981 | G129: =IF(MIS_Calc!D146="","",MIS_Calc!D146) -> 5304 | H129: =IF(MIS_Calc!E146="","",MIS_Calc!E146) -> 7352 | I129: =IF(MIS_Calc!F146="","",MIS_Calc!F146) -> 9602 | J129: =IF(MIS_Calc!G146="","",MIS_Calc!G146) -> 9997 | K129: =IF(MIS_Calc!H146="","",MIS_Calc!H146) -> 4369 | L129: =IF(MIS_Calc!I146="","",MIS_Calc!I146) -> 4443 | M129: =IF(MIS_Calc!J146="","",MIS_Calc!J146) -> 5498 | ... Q129: =IF(MIS_Calc!N146="","",MIS_Calc!N146) | R129: =MIS_Calc!W146 -> 6318.25 | T129: =IF(MIS_Calc!O146="","–",MIS_Calc!O146) -> 4599.4 | V129: =IFERROR(IF(OR(MIS_Calc!W146="",MIS_Calc!O146="",MIS_Calc!O146=0),"–",MIS_Calc!W146/MIS_Calc!O146-1),"–") -> 0.37371179 | X129: =IFERROR(MIS_Calc!W146/SUM(MIS_Calc!$W$136:$W$160),"–") -> 0.040087297
B130: =MIS_Calc!A147 -> SR-11-12CB | F130: =IF(MIS_Calc!C147="","",MIS_Calc!C147) -> 4068 | G130: =IF(MIS_Calc!D147="","",MIS_Calc!D147) -> 7064 | H130: =IF(MIS_Calc!E147="","",MIS_Calc!E147) -> 10129 | I130: =IF(MIS_Calc!F147="","",MIS_Calc!F147) -> 13778 | J130: =IF(MIS_Calc!G147="","",MIS_Calc!G147) -> 14594 | K130: =IF(MIS_Calc!H147="","",MIS_Calc!H147) -> 3887 | L130: =IF(MIS_Calc!I147="","",MIS_Calc!I147) -> 6393 | M130: =IF(MIS_Calc!J147="","",MIS_Calc!J147) -> 8718 | ... Q130: =IF(MIS_Calc!N147="","",MIS_Calc!N147) | R130: =MIS_Calc!W147 -> 8578.875 | T130: =IF(MIS_Calc!O147="","–",MIS_Calc!O147) -> 5202.85 | V130: =IFERROR(IF(OR(MIS_Calc!W147="",MIS_Calc!O147="",MIS_Calc!O147=0),"–",MIS_Calc!W147/MIS_Calc!O147-1),"–") -> 0.64887994 | X130: =IFERROR(MIS_Calc!W147/SUM(MIS_Calc!$W$136:$W$160),"–") -> 0.054430247
... B143: =MIS_Calc!A160 -> Nursary | F143: =IF(MIS_Calc!C160="","",MIS_Calc!C160) -> 780 | G143: =IF(MIS_Calc!D160="","",MIS_Calc!D160) -> 1440 | H143: =IF(MIS_Calc!E160="","",MIS_Calc!E160) -> 3957 | I143: =IF(MIS_Calc!F160="","",MIS_Calc!F160) -> 8560.3 | J143: =IF(MIS_Calc!G160="","",MIS_Calc!G160) -> 7497.7 | K143: =IF(MIS_Calc!H160="","",MIS_Calc!H160) -> 2035.8 | L143: =IF(MIS_Calc!I160="","",MIS_Calc!I160) -> 2497.9 | M143: =IF(MIS_Calc!J160="","",MIS_Calc!J160) -> 4852 | ... Q143: =IF(MIS_Calc!N160="","",MIS_Calc!N160) | R143: =MIS_Calc!W160 -> 3952.5875 | T143: =IF(MIS_Calc!O160="","–",MIS_Calc!O160) -> 2515.2083 | V143: =IFERROR(IF(OR(MIS_Calc!W160="",MIS_Calc!O160="",MIS_Calc!O160=0),"–",MIS_Calc!W160/MIS_Calc!O160-1),"–") -> 0.57147519 | X143: =IFERROR(MIS_Calc!W160/SUM(MIS_Calc!$W$136:$W$160),"–") -> 0.025077917
B146: 📋 PER-CAPITA KPI MATRIX — ALL MIS DOMAINS (selected month / YTD average vs Avg-2025 and Avg-2024 baselines)
B147: Domain | F147: KPI | K147: Unit | O147: Selected | Q147: Avg 2025 | S147: Avg 2024 | U147: Δ vs 2025 | W147: Status
B148: Energy | F148: Grid energy per person | K148: kWh/person/month | O148: =IF(MIS_Calc!E279="","–",MIS_Calc!E279) -> 108.11078 | Q148: =IF(MIS_Calc!F279="","–",MIS_Calc!F279) -> 98.064623 | S148: =IF(MIS_Calc!G279="","–",MIS_Calc!G279) -> 136.58604 | U148: =IF(MIS_Calc!H279="","–",MIS_Calc!H279) -> 0.10244428 | W148: =MIS_Calc!J279 -> ▲ Watch
F149: Energy bill per person | K149: ₹/person/month | O149: =IF(MIS_Calc!E280="","–",MIS_Calc!E280) -> 1351.2341 | Q149: =IF(MIS_Calc!F280="","–",MIS_Calc!F280) -> 1286.0409 | S149: =IF(MIS_Calc!G280="","–",MIS_Calc!G280) -> 1705.8823 | U149: =IF(MIS_Calc!H280="","–",MIS_Calc!H280) -> 0.050692959 | W149: =MIS_Calc!J280 -> ▲ Watch
F150: EPI | K150: kWh/m²/month | O150: =IF(MIS_Calc!E281="","–",MIS_Calc!E281) -> 2.7801652 | Q150: =IF(MIS_Calc!F281="","–",MIS_Calc!F281) -> 2.5218193 | S150: =IF(MIS_Calc!G281="","–",MIS_Calc!G281) -> 3.5124319 | U150: =IF(MIS_Calc!H281="","–",MIS_Calc!H281) -> 0.10244428 | W150: =MIS_Calc!J281 -> ▲ Watch
F151: HVAC energy per person | K151: kWh/person/month | O151: =IF(MIS_Calc!E282="","–",MIS_Calc!E282) -> 16.217046 | Q151: =IF(MIS_Calc!F282="","–",MIS_Calc!F282) -> 15.464608 | S151: =IF(MIS_Calc!G282="","–",MIS_Calc!G282) -> 52.585403 | U151: =IF(MIS_Calc!H282="","–",MIS_Calc!H282) -> 0.048655456 | W151: =MIS_Calc!J282 -> ● In line
F153: Power factor | K153: ratio | O153: =IF(MIS_Calc!E284="","–",MIS_Calc!E284) -> 0.93618573 | Q153: =IF(MIS_Calc!F284="","–",MIS_Calc!F284) -> 0.9644206 | S153: =IF(MIS_Calc!G284="","–",MIS_Calc!G284) -> 0.98417165 | U153: =IF(MIS_Calc!H284="","–",MIS_Calc!H284) -> -0.02927652 | W153: =MIS_Calc!J284 -> ● In line
F154: Max-demand utilisation (info) | K154: % of sanctioned | O154: =IF(MIS_Calc!E285="","–",MIS_Calc!E285) -> 0.37225705 | Q154: =IF(MIS_Calc!F285="","–",MIS_Calc!F285) -> 0.40049634 | S154: =IF(MIS_Calc!G285="","–",MIS_Calc!G285) -> 0.87539185 | U154: =IF(MIS_Calc!H285="","–",MIS_Calc!H285) -> -0.07051073 | W154: =MIS_Calc!J285 -> ✔ Better
B155: Water | F155: LPCD | K155: L/person/day | O155: =IF(MIS_Calc!E286="","–",MIS_Calc!E286) -> 334.15924 | Q155: =IF(MIS_Calc!F286="","–",MIS_Calc!F286) -> 2432.213 | S155: =IF(MIS_Calc!G286="","–",MIS_Calc!G286) -> 1153.4701 | U155: =IF(MIS_Calc!H286="","–",MIS_Calc!H286) -> -0.86261103 | W155: =MIS_Calc!J286 -> ✔ Better
F156: Borewell draw per person | K156: L/person/day | O156: =IF(MIS_Calc!E287="","–",MIS_Calc!E287) -> 285.77214 | Q156: =IF(MIS_Calc!F287="","–",MIS_Calc!F287) -> 718.26294 | S156: =IF(MIS_Calc!G287="","–",MIS_Calc!G287) -> 420.01659 | U156: =IF(MIS_Calc!H287="","–",MIS_Calc!H287) -> -0.60213436 | W156: =MIS_Calc!J287 -> ✔ Better
B157: Treatment & Reuse | F157: STP recycled per person | K157: L/person/day | O157: =IF(MIS_Calc!E288="","–",MIS_Calc!E288) -> 63.920522 | Q157: =IF(MIS_Calc!F288="","–",MIS_Calc!F288) -> 110.11109 | S157: =IF(MIS_Calc!G288="","–",MIS_Calc!G288) -> 87.023735 | U157: =IF(MIS_Calc!H288="","–",MIS_Calc!H288) -> -0.41949059 | W157: =MIS_Calc!J288 -> ▲ Watch
F158: STP share of inlet water | K158: % | O158: =IF(MIS_Calc!E289="","–",MIS_Calc!E289) -> 0.18279057 | Q158: =IF(MIS_Calc!F289="","–",MIS_Calc!F289) -> 0.13292436 | S158: =IF(MIS_Calc!G289="","–",MIS_Calc!G289) -> 0.1716308 | U158: =IF(MIS_Calc!H289="","–",MIS_Calc!H289) -> 0.37514729 | W158: =MIS_Calc!J289 -> ✔ Better
F159: WTP treated water per person (info) | K159: L/person/day | O159: =IF(MIS_Calc!E290="","–",MIS_Calc!E290) -> 261.73345 | Q159: =IF(MIS_Calc!F290="","–",MIS_Calc!F290) -> 260.26993 | S159: =IF(MIS_Calc!G290="","–",MIS_Calc!G290) -> 297.74185 | U159: =IF(MIS_Calc!H290="","–",MIS_Calc!H290) -> 0.0056231172 | W159: =MIS_Calc!J290 -> ● In line
F160: Drip irrigation per person (info) | K160: L/person/day | O160: =IF(MIS_Calc!E291="","–",MIS_Calc!E291) -> 59.584505 | Q160: =IF(MIS_Calc!F291="","–",MIS_Calc!F291) -> 146.54094 | S160: =IF(MIS_Calc!G291="","–",MIS_Calc!G291) -> 97.353352 | U160: =IF(MIS_Calc!H291="","–",MIS_Calc!H291) -> -0.59339347 | W160: =MIS_Calc!J291 -> ✔ Better
B161: Solar & Renewables | F161: Solar generation per person | K161: kWh/person/month | O161: =IF(MIS_Calc!E292="","–",MIS_Calc!E292) -> 85.606352 | Q161: =IF(MIS_Calc!F292="","–",MIS_Calc!F292) -> 63.396504 | S161: =IF(MIS_Calc!G292="","–",MIS_Calc!G292) -> – | U161: =IF(MIS_Calc!H292="","–",MIS_Calc!H292) -> 0.35033237 | W161: =MIS_Calc!J292 -> ✔ Better
F162: Solar offset of grid energy | K162: % | O162: =IF(MIS_Calc!E293="","–",MIS_Calc!E293) -> 0.79183916 | Q162: =IF(MIS_Calc!F293="","–",MIS_Calc!F293) -> 0.6464768 | S162: =IF(MIS_Calc!G293="","–",MIS_Calc!G293) -> – | U162: =IF(MIS_Calc!H293="","–",MIS_Calc!H293) -> 0.22485317 | W162: =MIS_Calc!J293 -> ✔ Better
F163: Solar savings per person (info) | K163: ₹/person/month | O163: =IF(MIS_Calc!E294="","–",MIS_Calc!E294) -> 1010.1549 | Q163: =IF(MIS_Calc!F294="","–",MIS_Calc!F294) -> – | S163: =IF(MIS_Calc!G294="","–",MIS_Calc!G294) -> – | U163: =IF(MIS_Calc!H294="","–",MIS_Calc!H294) -> – | W163: =MIS_Calc!J294 -> – no data/baseline
B168: Service Desk | F168: Complaints per 100 persons | K168: per 100 persons/month | O168: =IF(MIS_Calc!E299="","–",MIS_Calc!E299) -> 15.952733 | Q168: =IF(MIS_Calc!F299="","–",MIS_Calc!F299) -> 6.2776957 | S168: =IF(MIS_Calc!G299="","–",MIS_Calc!G299) -> 10.678237 | U168: =IF(MIS_Calc!H299="","–",MIS_Calc!H299) -> 1.5411765 | W168: =MIS_Calc!J299 -> ▲ Watch
F169: Closure rate | K169: % | O169: =IF(MIS_Calc!E300="","–",MIS_Calc!E300) -> 0.67592593 | Q169: =IF(MIS_Calc!F300="","–",MIS_Calc!F300) -> 1 | S169: =IF(MIS_Calc!G300="","–",MIS_Calc!G300) -> 0.98559078 | U169: =IF(MIS_Calc!H300="","–",MIS_Calc!H300) -> -0.32407407 | W169: =MIS_Calc!J300 -> ▲ Watch
F170: Pending complaints per 1,000 persons | K170: per 1,000 persons | O170: =IF(MIS_Calc!E301="","–",MIS_Calc!E301) -> – | Q170: =IF(MIS_Calc!F301="","–",MIS_Calc!F301) -> 0 | S170: =IF(MIS_Calc!G301="","–",MIS_Calc!G301) -> 0 | U170: =IF(MIS_Calc!H301="","–",MIS_Calc!H301) -> – | W170: =MIS_Calc!J301 -> – no data/baseline
F171: Emergency share of complaints (info) | K171: % | O171: =IF(MIS_Calc!E302="","–",MIS_Calc!E302) -> 0.032407407 | Q171: =IF(MIS_Calc!F302="","–",MIS_Calc!F302) -> 0.023529412 | S171: =IF(MIS_Calc!G302="","–",MIS_Calc!G302) -> 0.011527378 | U171: =IF(MIS_Calc!H302="","–",MIS_Calc!H302) -> 0.37731481 | W171: =MIS_Calc!J302 -> ▲ Watch
B172: Manpower & Cost | F172: Deployment % | K172: % | O172: =IF(MIS_Calc!E303="","–",MIS_Calc!E303) -> 0.8484375 | Q172: =IF(MIS_Calc!F303="","–",MIS_Calc!F303) -> 0.83111797 | S172: =IF(MIS_Calc!G303="","–",MIS_Calc!G303) -> 0.86282579 | U172: =IF(MIS_Calc!H303="","–",MIS_Calc!H303) -> 0.020838837 | W172: =MIS_Calc!J303 -> ● In line
F173: Overtime per 100 man-days present | K173: hrs/100 man-days | O173: =IF(MIS_Calc!E304="","–",MIS_Calc!E304) -> – | Q173: =IF(MIS_Calc!F304="","–",MIS_Calc!F304) -> 22.182701 | S173: =IF(MIS_Calc!G304="","–",MIS_Calc!G304) -> 34.976153 | U173: =IF(MIS_Calc!H304="","–",MIS_Calc!H304) -> – | W173: =MIS_Calc!J304 -> – no data/baseline
F174: Technical manpower cost per person | K174: ₹/person/month | O174: =IF(MIS_Calc!E305="","–",MIS_Calc!E305) -> – | Q174: =IF(MIS_Calc!F305="","–",MIS_Calc!F305) -> 553.98024 | S174: =IF(MIS_Calc!G305="","–",MIS_Calc!G305) -> 579.20236 | U174: =IF(MIS_Calc!H305="","–",MIS_Calc!H305) -> – | W174: =MIS_Calc!J305 -> – no data/baseline
F175: ="Tracked OPEX per person"&IF(AND(MIS_Calc!$B$5="2026 YTD",MIS_Calc!$G$106<MIS_Calc!$G$82)," ("&MIS_Calc!$G$106&" of "&MIS_Calc!$G$82&" months invoiced)","") -> Tracked OPEX per person | K175: ₹/person/month | O175: =IF(MIS_Calc!E306="","–",MIS_Calc!E306) -> – | Q175: =IF(MIS_Calc!F306="","–",MIS_Calc!F306) -> 1840.0211 | S175: =IF(MIS_Calc!G306="","–",MIS_Calc!G306) -> 2285.0847 | U175: =IF(MIS_Calc!H306="","–",MIS_Calc!H306) -> – | W175: =MIS_Calc!J306 -> – no data/baseline
F176: Technical manpower budget use (info) | K176: % | O176: =IF(MIS_Calc!E307="","–",MIS_Calc!E307) -> – | Q176: =IF(MIS_Calc!F307="","–",MIS_Calc!F307) -> 0.69482839 | S176: =IF(MIS_Calc!G307="","–",MIS_Calc!G307) -> 0.76701289 | U176: =IF(MIS_Calc!H307="","–",MIS_Calc!H307) -> – | W176: =MIS_Calc!J307 -> – no data/baseline
F177: Persons served per technician (info) | K177: persons/technician | O177: =IF(MIS_Calc!E308="","–",MIS_Calc!E308) -> 50.148148 | Q177: =IF(MIS_Calc!F308="","–",MIS_Calc!F308) -> – | S177: =IF(MIS_Calc!G308="","–",MIS_Calc!G308) -> – | U177: =IF(MIS_Calc!H308="","–",MIS_Calc!H308) -> – | W177: =MIS_Calc!J308 -> – no data/baseline
F178: DG energy per person (info) | K178: kWh/person/month | O178: =IF(MIS_Calc!E309="","–",MIS_Calc!E309) -> 0.0081240768 | Q178: =IF(MIS_Calc!F309="","–",MIS_Calc!F309) -> 0.36504633 | S178: =IF(MIS_Calc!G309="","–",MIS_Calc!G309) -> 0.73015953 | U178: =IF(MIS_Calc!H309="","–",MIS_Calc!H309) -> -0.97774508 | W178: =MIS_Calc!J309 -> ✔ Better
B180: Method: per-person = monthly quantity ÷ occupants (LPCD sheet, 1,354); L/person/day uses calendar days. Scores compare the selection with the Avg-2025 row of each source sheet (capped 50–150, direction-aware: lower is better for consumption & cost, higher for PF, STP, solar, closure, deployment). '(info)' KPIs are shown but not scored (no 2025 baseline or known data issue). Tracked OPEX = HT energy bill + technical manpower cost (shown only for months where both are logged).

Sheet Complaints summary
A1: COMPLAINTS SUMMARY · Service Desk Performance 2026 vs 2023–2025
B3: Month | C3: Number of complains received | D3: Priority | F3: Complaints closed | G3: % Emergency | H3: %Non-Critical | I3: Pending | J3: Daily average Nos of Complaints
D4: Emergency | E4: Non Critical
B5: Avg 2023 | C5: 156.75 | D5: 46.5 | E5: 110.25 | F5: 155 | G5: =IF(OR(C5="",C5=0),"",D5/C5) -> 0.29665072 | H5: =IF(OR(C5="",C5=0),"",E5/C5) -> 0.70334928 | I5: 0 | J5: 5.1271825
B6: Avg 2024 | C6: 144.58333 | D6: 1.6666667 | E6: 142.91667 | F6: 142.5 | G6: =IF(OR(C6="",C6=0),"",D6/C6) -> 0.011527378 | H6: =IF(OR(C6="",C6=0),"",E6/C6) -> 0.98847262 | I6: 0 | J6: 4.6639785
B7: Avg 2025 | C7: 85 | D7: 2 | E7: 83 | F7: 85 | G7: =IF(OR(C7="",C7=0),"",D7/C7) -> 0.023529412 | H7: =IF(OR(C7="",C7=0),"",E7/C7) -> 0.97647059 | I7: 0 | J7: 2.7715054
B8: 46023 | C8: 144 | D8: 8 | E8: 122 | F8: 139 | G8: =IF(OR(C8="",C8=0),"",D8/C8) -> 0.055555556 | H8: =IF(OR(C8="",C8=0),"",E8/C8) -> 0.84722222 | I8: 1 | J8: =IF(C8="","",C8/DAY(EOMONTH(B8,0))) -> 4.6451613
B9: 46054 | C9: 122 | D9: 0 | E9: 122 | F9: 119 | G9: =IF(OR(C9="",C9=0),"",D9/C9) -> 0 | H9: =IF(OR(C9="",C9=0),"",E9/C9) -> 1 | I9: 3 | J9: =IF(C9="","",C9/DAY(EOMONTH(B9,0))) -> 4.3571429
B10: 46082 | G10: =IF(OR(C10="",C10=0),"",D10/C10) | H10: =IF(OR(C10="",C10=0),"",E10/C10) | J10: =IF(C10="","",C10/DAY(EOMONTH(B10,0)))
B11: 46113 | G11: =IF(OR(C11="",C11=0),"",D11/C11) | H11: =IF(OR(C11="",C11=0),"",E11/C11) | J11: =IF(C11="","",C11/DAY(EOMONTH(B11,0)))
B12: 46143 | G12: =IF(OR(C12="",C12=0),"",D12/C12) | H12: =IF(OR(C12="",C12=0),"",E12/C12) | J12: =IF(C12="","",C12/DAY(EOMONTH(B12,0)))
B13: 46174 | C13: 155 | D13: 5 | E13: 150 | F13: 155 | G13: =IF(OR(C13="",C13=0),"",D13/C13) -> 0.032258065 | H13: =IF(OR(C13="",C13=0),"",E13/C13) -> 0.96774194 | J13: =IF(C13="","",C13/DAY(EOMONTH(B13,0))) -> 5.1666667
B14: 46204 | C14: 168 | D14: 6 | E14: 162 | F14: 127 | G14: =IF(OR(C14="",C14=0),"",D14/C14) -> 0.035714286 | H14: =IF(OR(C14="",C14=0),"",E14/C14) -> 0.96428571 | J14: =IF(C14="","",C14/DAY(EOMONTH(B14,0))) -> 5.4193548
B15: 46235 | C15: 216 | D15: 7 | E15: 156 | F15: 146 | G15: =IF(OR(C15="",C15=0),"",D15/C15) -> 0.032407407 | H15: =IF(OR(C15="",C15=0),"",E15/C15) -> 0.72222222 | J15: =IF(C15="","",C15/DAY(EOMONTH(B15,0))) -> 6.9677419
B16: 46266 | G16: =IF(OR(C16="",C16=0),"",D16/C16) | H16: =IF(OR(C16="",C16=0),"",E16/C16) | J16: =IF(C16="","",C16/DAY(EOMONTH(B16,0)))
B17: 46296 | G17: =IF(OR(C17="",C17=0),"",D17/C17) | H17: =IF(OR(C17="",C17=0),"",E17/C17) | J17: =IF(C17="","",C17/DAY(EOMONTH(B17,0)))
B18: 46327 | G18: =IF(OR(C18="",C18=0),"",D18/C18) | H18: =IF(OR(C18="",C18=0),"",E18/C18) | J18: =IF(C18="","",C18/DAY(EOMONTH(B18,0)))
B19: 46357 | G19: =IF(OR(C19="",C19=0),"",D19/C19) | H19: =IF(OR(C19="",C19=0),"",E19/C19) | J19: =IF(C19="","",C19/DAY(EOMONTH(B19,0)))
B20: Avg 2026 | C20: =IFERROR(AVERAGE(C8:C19),"") -> 161 | D20: =IFERROR(AVERAGE(D8:D19),"") -> 5.2 | E20: =IFERROR(AVERAGE(E8:E19),"") -> 142.4 | F20: =IFERROR(AVERAGE(F8:F19),"") -> 137.2 | G20: =IFERROR(SUM(D8:D19)/SUM(C8:C19),"") -> 0.032298137 | H20: =IFERROR(SUM(E8:E19)/SUM(C8:C19),"") -> 0.88447205 | I20: =IFERROR(AVERAGE(I8:I19),"") -> 2 | J20: =IFERROR(AVERAGE(J8:J19),"") -> 5.3112135
B21: Total 2026 YTD | C21: =SUM(C8:C19) -> 805 | D21: =SUM(D8:D19) -> 26 | E21: =SUM(E8:E19) -> 712 | F21: =SUM(F8:F19) -> 686 | I21: =SUM(I8:I19) -> 4
O26: AUDIT SNAPSHOT (live)
O27: AUDIT SNAPSHOT | P27: Baseline | Q27: Current (latest)
O28: Total Complaints | P28: 111 | Q28: =IFERROR(INDEX(C8:C19,MATCH(9.99E+307,C8:C19)),"") -> 216
O29: Completed | P29: 111 | Q29: =IFERROR(INDEX(F8:F19,MATCH(9.99E+307,C8:C19)),"") -> 146
O30: Pending | P30: 0 | Q30: =IFERROR(INDEX(I8:I19,MATCH(9.99E+307,C8:C19)),"") -> 0

Sheet Building wise water
B1: BUILDING-WISE WATER CONSUMPTION (kL) · 2026 monthly vs 2023–2025 averages
B2: Flow hierarchy: Borewells + STP outlet → WTP / drip irrigation / sports field → building sub-meters downstream of WTP. Blue = monthly meter entry · Baseline = MEDIAN of the 2023–25 monthly averages (robust to the suspect Avg-2025 building values) · tiles follow the month selected on FM_Dashboard (latest logged month when 2026 YTD is selected).
B4: ="BUILDINGS · "&UPPER(SUBSTITUTE(INDEX($I$9:$T$9,IFERROR(MATCH(MIS_Calc!$B$3,$I$9:$T$9,0),IFERROR(MATCH(9.99E+307,$I$31:$T$31),1))),"-"," 20"))&" (kL)" -> BUILDINGS · AUG 2026 (kL) | E4: BUILDINGS · 2026 YTD AVG (kL/month) | I4: ="WTP OUTPUT · "&UPPER(SUBSTITUTE(INDEX($I$9:$T$9,IFERROR(MATCH(MIS_Calc!$B$3,$I$9:$T$9,0),IFERROR(MATCH(9.99E+307,$I$31:$T$31),1))),"-"," 20"))&" (kL)" -> WTP OUTPUT · AUG 2026 (kL) | N4: TOP BUILDING · 2026 YTD AVG | S4: METERS REPORTING · SELECTED MONTH | W4: DATA-QUALITY FLAGS OPEN
B5: =IF(INDEX($I$31:$T$31,IFERROR(MATCH(MIS_Calc!$B$3,$I$9:$T$9,0),IFERROR(MATCH(9.99E+307,$I$31:$T$31),1)))="","—",INDEX($I$31:$T$31,IFERROR(MATCH(MIS_Calc!$B$3,$I$9:$T$9,0),IFERROR(MATCH(9.99E+307,$I$31:$T$31),1)))) -> 7028 | E5: =IF($U$31="","—",$U$31) -> 4585.875 | I5: =IF(INDEX($I$33:$T$33,IFERROR(MATCH(MIS_Calc!$B$3,$I$9:$T$9,0),IFERROR(MATCH(9.99E+307,$I$31:$T$31),1)))="","—",INDEX($I$33:$T$33,IFERROR(MATCH(MIS_Calc!$B$3,$I$9:$T$9,0),IFERROR(MATCH(9.99E+307,$I$31:$T$31),1)))) -> 10986 | N5: =INDEX($C$11:$C$30,MATCH(MAX($U$11:$U$30),$U$11:$U$30,0)) -> SR-9-10B1A | S5: =INDEX($I$45:$T$45,IFERROR(MATCH(MIS_Calc!$B$3,$I$9:$T$9,0),IFERROR(MATCH(9.99E+307,$I$31:$T$31),1))) -> 24 | W5: =COUNTIF($Z$11:$Z$39,"?*")-COUNTIF($Z$11:$Z$39,"OK") -> 14
B7: =IF(OR(INDEX($I$31:$T$31,IFERROR(MATCH(MIS_Calc!$B$3,$I$9:$T$9,0),IFERROR(MATCH(9.99E+307,$I$31:$T$31),1)))="",$H$31=""),"no reading for this month","vs baseline "&TEXT(INDEX($I$31:$T$31,IFERROR(MATCH(MIS_Calc!$B$3,$I$9:$T$9,0),IFERROR(MATCH(9.99E+307,$I$31:$T$31),1)))/$H$31-1,"+0%;-0%")) -> vs baseline +19% | E7: =IF($X$31="","","vs baseline "&TEXT($X$31,"+0%;-0%")&" · "&COUNT($I$31:$T$31)&" months logged") -> vs baseline -22% · 8 months logged | I7: =IF(INDEX($I$44:$T$44,IFERROR(MATCH(MIS_Calc!$B$3,$I$9:$T$9,0),IFERROR(MATCH(9.99E+307,$I$31:$T$31),1)))="","coverage n/a","building meters cover "&TEXT(INDEX($I$44:$T$44,IFERROR(MATCH(MIS_Calc!$B$3,$I$9:$T$9,0),IFERROR(MATCH(9.99E+307,$I$31:$T$31),1))),"0%")&" of WTP output") -> building meters cover 64% of WTP output | N7: =TEXT(MAX($U$11:$U$30),"#,##0")&" kL/month · "&TEXT(MAX($U$11:$U$30)/$U$31,"0%")&" of building use" -> 877 kL/month · 19% of building use | S7: ="latest month logged: "&IFERROR(INDEX($I$9:$T$9,MATCH(9.99E+307,$I$31:$T$31)),"—") -> latest month logged: Aug-26 | W7: =COUNTIF($Z$11:$Z$39,"VERIFY*")&" verify Avg-2025 · "&COUNTIF($Z$11:$Z$39,"MISSING*")&" missing month(s) · "&(COUNTIF($Z$11:$Z$39,"?*")-COUNTIF($Z$11:$Z$39,"OK")-COUNTIF($Z$11:$Z$39,"VERIFY*")-COUNTIF($Z$11:$Z$39,"MISSING*"))&" other" -> 13 verify Avg-2025 · 1 missing month(s) · 0 other
B9: S No | C9: Location | D9: Group | E9: Avg 2023 | F9: Avg 2024 | G9: Avg 2025 | H9: Baseline (median 23–25) | I9: Jan-26 | J9: Feb-26 | K9: Mar-26 | L9: Apr-26 | M9: May-26 | N9: Jun-26 | O9: Jul-26 | P9: Aug-26 | Q9: Sep-26 | R9: Oct-26 | S9: Nov-26 | T9: Dec-26 | U9: Avg 2026 YTD | V9: Total 2026 YTD | W9: Δ YTD vs Avg 2025 | X9: Δ YTD vs Baseline | Y9: Months logged | Z9: Data-quality flag
B10: A · BUILDING SUB-METERS (downstream of WTP)
B11: 1 | C11: SR-1 | D11: Residence | E11: 145.16667 | F11: 388.5 | G11: 1180.5833 | H11: =IF(COUNT(E11:G11)=0,"",MEDIAN(E11:G11)) -> 388.5 | I11: 264 | J11: 239 | K11: 280 | L11: 201 | M11: 189 | N11: 91 | O11: 224 | P11: 329 | U11: =IF(COUNT(I11:T11)=0,"",AVERAGE(I11:T11)) -> 227.125 | V11: =IF(COUNT(I11:T11)=0,"",SUM(I11:T11)) -> 1817 | W11: =IF(OR(U11="",N(G11)=0),"",U11/G11-1) -> -0.80761629 | X11: =IF(OR(U11="",N(H11)=0),"",U11/H11-1) -> -0.41537967 | Y11: =COUNT(I11:T11) -> 8 | Z11: =IF(COUNT(I11:T11)=0,"NO 2026 DATA",IF(COUNT(I11:T11)<MATCH(9.99E+307,I11:T11)-MATCH(TRUE,INDEX(ISNUMBER(I11:T11),0),0)+1,"MISSING MONTH(S)",IF(AND(COUNT(E11:F11)=2,N(G11)>3*MAX(E11:F11)),"VERIFY AVG-2025 (>3× prior yrs)",IF(AND(N(H11)>=500,MIN(I11:T11)<0.1*N(H11)),"CHECK OUTLIER MONTH",IF(AND(N(H11)>=50,LOOKUP(9.99E+307,I11:T11)=0),"LATEST = 0 · CHECK METER","OK"))))) -> VERIFY AVG-2025 (>3× prior yrs)
B12: 2 | C12: SR-2 | D12: Residence | E12: 178.58333 | F12: 199.33333 | G12: 1194.8333 | H12: =IF(COUNT(E12:G12)=0,"",MEDIAN(E12:G12)) -> 199.33333 | I12: 267 | J12: 427 | K12: 111 | L12: 100 | M12: 102 | N12: 87 | O12: 125 | P12: 312 | U12: =IF(COUNT(I12:T12)=0,"",AVERAGE(I12:T12)) -> 191.375 | V12: =IF(COUNT(I12:T12)=0,"",SUM(I12:T12)) -> 1531 | W12: =IF(OR(U12="",N(G12)=0),"",U12/G12-1) -> -0.83983122 | X12: =IF(OR(U12="",N(H12)=0),"",U12/H12-1) -> -0.039924749 | Y12: =COUNT(I12:T12) -> 8 | Z12: =IF(COUNT(I12:T12)=0,"NO 2026 DATA",IF(COUNT(I12:T12)<MATCH(9.99E+307,I12:T12)-MATCH(TRUE,INDEX(ISNUMBER(I12:T12),0),0)+1,"MISSING MONTH(S)",IF(AND(COUNT(E12:F12)=2,N(G12)>3*MAX(E12:F12)),"VERIFY AVG-2025 (>3× prior yrs)",IF(AND(N(H12)>=500,MIN(I12:T12)<0.1*N(H12)),"CHECK OUTLIER MONTH",IF(AND(N(H12)>=50,LOOKUP(9.99E+307,I12:T12)=0),"LATEST = 0 · CHECK METER","OK"))))) -> VERIFY AVG-2025 (>3× prior yrs)
B13: 3 | C13: SR-3 | D13: Residence | E13: 103.08333 | F13: 171.33333 | G13: 1274.9167 | H13: =IF(COUNT(E13:G13)=0,"",MEDIAN(E13:G13)) -> 171.33333 | I13: 205 | J13: 111 | K13: 8 | L13: 60 | M13: 58 | N13: 60 | O13: 62 | P13: 64 | U13: =IF(COUNT(I13:T13)=0,"",AVERAGE(I13:T13)) -> 78.5 | V13: =IF(COUNT(I13:T13)=0,"",SUM(I13:T13)) -> 628 | W13: =IF(OR(U13="",N(G13)=0),"",U13/G13-1) -> -0.93842735 | X13: =IF(OR(U13="",N(H13)=0),"",U13/H13-1) -> -0.54182879 | Y13: =COUNT(I13:T13) -> 8 | Z13: =IF(COUNT(I13:T13)=0,"NO 2026 DATA",IF(COUNT(I13:T13)<MATCH(9.99E+307,I13:T13)-MATCH(TRUE,INDEX(ISNUMBER(I13:T13),0),0)+1,"MISSING MONTH(S)",IF(AND(COUNT(E13:F13)=2,N(G13)>3*MAX(E13:F13)),"VERIFY AVG-2025 (>3× prior yrs)",IF(AND(N(H13)>=500,MIN(I13:T13)<0.1*N(H13)),"CHECK OUTLIER MONTH",IF(AND(N(H13)>=50,LOOKUP(9.99E+307,I13:T13)=0),"LATEST = 0 · CHECK METER","OK"))))) -> VERIFY AVG-2025 (>3× prior yrs)
B14: 4 | C14: SR-4 | D14: Residence | E14: 105.5 | F14: 162.08333 | G14: 1677.1667 | H14: =IF(COUNT(E14:G14)=0,"",MEDIAN(E14:G14)) -> 162.08333 | I14: 136 | J14: 136 | K14: 337 | L14: 337 | M14: 233 | N14: 221 | O14: 146 | P14: 194 | U14: =IF(COUNT(I14:T14)=0,"",AVERAGE(I14:T14)) -> 217.5 | V14: =IF(COUNT(I14:T14)=0,"",SUM(I14:T14)) -> 1740 | W14: =IF(OR(U14="",N(G14)=0),"",U14/G14-1) -> -0.870317 | X14: =IF(OR(U14="",N(H14)=0),"",U14/H14-1) -> 0.34190231 | Y14: =COUNT(I14:T14) -> 8 | Z14: =IF(COUNT(I14:T14)=0,"NO 2026 DATA",IF(COUNT(I14:T14)<MATCH(9.99E+307,I14:T14)-MATCH(TRUE,INDEX(ISNUMBER(I14:T14),0),0)+1,"MISSING MONTH(S)",IF(AND(COUNT(E14:F14)=2,N(G14)>3*MAX(E14:F14)),"VERIFY AVG-2025 (>3× prior yrs)",IF(AND(N(H14)>=500,MIN(I14:T14)<0.1*N(H14)),"CHECK OUTLIER MONTH",IF(AND(N(H14)>=50,LOOKUP(9.99E+307,I14:T14)=0),"LATEST = 0 · CHECK METER","OK"))))) -> VERIFY AVG-2025 (>3× prior yrs)
B15: 5 | C15: SR-9-10B1A | D15: Residence | E15: 455.5 | F15: 458.75 | G15: 2503.1667 | H15: =IF(COUNT(E15:G15)=0,"",MEDIAN(E15:G15)) -> 458.75 | I15: 568 | J15: 716 | K15: 835 | L15: 1045 | M15: 781 | N15: 279 | O15: 1320 | P15: 1468 | U15: =IF(COUNT(I15:T15)=0,"",AVERAGE(I15:T15)) -> 876.5 | V15: =IF(COUNT(I15:T15)=0,"",SUM(I15:T15)) -> 7012 | W15: =IF(OR(U15="",N(G15)=0),"",U15/G15-1) -> -0.64984353 | X15: =IF(OR(U15="",N(H15)=0),"",U15/H15-1) -> 0.9106267 | Y15: =COUNT(I15:T15) -> 8 | Z15: =IF(COUNT(I15:T15)=0,"NO 2026 DATA",IF(COUNT(I15:T15)<MATCH(9.99E+307,I15:T15)-MATCH(TRUE,INDEX(ISNUMBER(I15:T15),0),0)+1,"MISSING MONTH(S)",IF(AND(COUNT(E15:F15)=2,N(G15)>3*MAX(E15:F15)),"VERIFY AVG-2025 (>3× prior yrs)",IF(AND(N(H15)>=500,MIN(I15:T15)<0.1*N(H15)),"CHECK OUTLIER MONTH",IF(AND(N(H15)>=50,LOOKUP(9.99E+307,I15:T15)=0),"LATEST = 0 · CHECK METER","OK"))))) -> VERIFY AVG-2025 (>3× prior yrs)
B16: 6 | C16: SR-9-10B1B | D16: Residence | E16: 415.41667 | F16: 454.25 | G16: 2943.25 | H16: =IF(COUNT(E16:G16)=0,"",MEDIAN(E16:G16)) -> 454.25 | I16: 209 | J16: 73 | K16: 268 | L16: 149 | M16: 167 | N16: 46 | O16: 42 | P16: 45 | U16: =IF(COUNT(I16:T16)=0,"",AVERAGE(I16:T16)) -> 124.875 | V16: =IF(COUNT(I16:T16)=0,"",SUM(I16:T16)) -> 999 | W16: =IF(OR(U16="",N(G16)=0),"",U16/G16-1) -> -0.95757241 | X16: =IF(OR(U16="",N(H16)=0),"",U16/H16-1) -> -0.72509631 | Y16: =COUNT(I16:T16) -> 8 | Z16: =IF(COUNT(I16:T16)=0,"NO 2026 DATA",IF(COUNT(I16:T16)<MATCH(9.99E+307,I16:T16)-MATCH(TRUE,INDEX(ISNUMBER(I16:T16),0),0)+1,"MISSING MONTH(S)",IF(AND(COUNT(E16:F16)=2,N(G16)>3*MAX(E16:F16)),"VERIFY AVG-2025 (>3× prior yrs)",IF(AND(N(H16)>=500,MIN(I16:T16)<0.1*N(H16)),"CHECK OUTLIER MONTH",IF(AND(N(H16)>=50,LOOKUP(9.99E+307,I16:T16)=0),"LATEST = 0 · CHECK METER","OK"))))) -> VERIFY AVG-2025 (>3× prior yrs)
B17: 7 | C17: SR-11-12CA | D17: Residence | E17: 341.25 | F17: 328.75 | G17: 2175.4167 | H17: =IF(COUNT(E17:G17)=0,"",MEDIAN(E17:G17)) -> 341.25 | I17: 233 | J17: 285 | K17: 337 | L17: 377 | M17: 358 | N17: 200 | O17: 647 | P17: 710 | U17: =IF(COUNT(I17:T17)=0,"",AVERAGE(I17:T17)) -> 393.375 | V17: =IF(COUNT(I17:T17)=0,"",SUM(I17:T17)) -> 3147 | W17: =IF(OR(U17="",N(G17)=0),"",U17/G17-1) -> -0.81917257 | X17: =IF(OR(U17="",N(H17)=0),"",U17/H17-1) -> 0.15274725 | Y17: =COUNT(I17:T17) -> 8 | Z17: =IF(COUNT(I17:T17)=0,"NO 2026 DATA",IF(COUNT(I17:T17)<MATCH(9.99E+307,I17:T17)-MATCH(TRUE,INDEX(ISNUMBER(I17:T17),0),0)+1,"MISSING MONTH(S)",IF(AND(COUNT(E17:F17)=2,N(G17)>3*MAX(E17:F17)),"VERIFY AVG-2025 (>3× prior yrs)",IF(AND(N(H17)>=500,MIN(I17:T17)<0.1*N(H17)),"CHECK OUTLIER MONTH",IF(AND(N(H17)>=50,LOOKUP(9.99E+307,I17:T17)=0),"LATEST = 0 · CHECK METER","OK"))))) -> VERIFY AVG-2025 (>3× prior yrs)
B18: 8 | C18: SR-11-12CB | D18: Residence | E18: 388.33333 | F18: 463.08333 | G18: 2811.4167 | H18: =IF(COUNT(E18:G18)=0,"",MEDIAN(E18:G18)) -> 463.08333 | I18: 0 | J18: 101 | K18: 450 | L18: 399 | M18: 205 | N18: 50 | O18: 0 | P18: 0 | U18: =IF(COUNT(I18:T18)=0,"",AVERAGE(I18:T18)) -> 150.625 | V18: =IF(COUNT(I18:T18)=0,"",SUM(I18:T18)) -> 1205 | W18: =IF(OR(U18="",N(G18)=0),"",U18/G18-1) -> -0.94642381 | X18: =IF(OR(U18="",N(H18)=0),"",U18/H18-1) -> -0.67473457 | Y18: =COUNT(I18:T18) -> 8 | Z18: =IF(COUNT(I18:T18)=0,"NO 2026 DATA",IF(COUNT(I18:T18)<MATCH(9.99E+307,I18:T18)-MATCH(TRUE,INDEX(ISNUMBER(I18:T18),0),0)+1,"MISSING MONTH(S)",IF(AND(COUNT(E18:F18)=2,N(G18)>3*MAX(E18:F18)),"VERIFY AVG-2025 (>3× prior yrs)",IF(AND(N(H18)>=500,MIN(I18:T18)<0.1*N(H18)),"CHECK OUTLIER MONTH",IF(AND(N(H18)>=50,LOOKUP(9.99E+307,I18:T18)=0),"LATEST = 0 · CHECK METER","OK"))))) -> VERIFY AVG-2025 (>3× prior yrs)
B19: 9 | C19: Junior School-1&2 | D19: Academic | E19: 177.75 | F19: 204.33333 | G19: 2368.75 | H19: =IF(COUNT(E19:G19)=0,"",MEDIAN(E19:G19)) -> 204.33333 | I19: 0 | J19: 0 | K19: 1 | L19: 0 | M19: 0 | N19: 1 | O19: 0 | P19: 0 | U19: =IF(COUNT(I19:T19)=0,"",AVERAGE(I19:T19)) -> 0.25 | V19: =IF(COUNT(I19:T19)=0,"",SUM(I19:T19)) -> 2 | W19: =IF(OR(U19="",N(G19)=0),"",U19/G19-1) -> -0.99989446 | X19: =IF(OR(U19="",N(H19)=0),"",U19/H19-1) -> -0.99877651 | Y19: =COUNT(I19:T19) -> 8 | Z19: =IF(COUNT(I19:T19)=0,"NO 2026 DATA",IF(COUNT(I19:T19)<MATCH(9.99E+307,I19:T19)-MATCH(TRUE,INDEX(ISNUMBER(I19:T19),0),0)+1,"MISSING MONTH(S)",IF(AND(COUNT(E19:F19)=2,N(G19)>3*MAX(E19:F19)),"VERIFY AVG-2025 (>3× prior yrs)",IF(AND(N(H19)>=500,MIN(I19:T19)<0.1*N(H19)),"CHECK OUTLIER MONTH",IF(AND(N(H19)>=50,LOOKUP(9.99E+307,I19:T19)=0),"LATEST = 0 · CHECK METER","OK"))))) -> VERIFY AVG-2025 (>3× prior yrs)
B20: 10 | C20: Junior School-3 | D20: Academic | E20: 265.33333 | F20: 308.66667 | G20: 6906.1667 | H20: =IF(COUNT(E20:G20)=0,"",MEDIAN(E20:G20)) -> 308.66667 | I20: 27 | J20: 22 | K20: 40 | L20: 25 | M20: 28 | N20: 7 | O20: 87 | P20: 120 | U20: =IF(COUNT(I20:T20)=0,"",AVERAGE(I20:T20)) -> 44.5 | V20: =IF(COUNT(I20:T20)=0,"",SUM(I20:T20)) -> 356 | W20: =IF(OR(U20="",N(G20)=0),"",U20/G20-1) -> -0.99355648 | X20: =IF(OR(U20="",N(H20)=0),"",U20/H20-1) -> -0.85583153 | Y20: =COUNT(I20:T20) -> 8 | Z20: =IF(COUNT(I20:T20)=0,"NO 2026 DATA",IF(COUNT(I20:T20)<MATCH(9.99E+307,I20:T20)-MATCH(TRUE,INDEX(ISNUMBER(I20:T20),0),0)+1,"MISSING MONTH(S)",IF(AND(COUNT(E20:F20)=2,N(G20)>3*MAX(E20:F20)),"VERIFY AVG-2025 (>3× prior yrs)",IF(AND(N(H20)>=500,MIN(I20:T20)<0.1*N(H20)),"CHECK OUTLIER MONTH",IF(AND(N(H20)>=50,LOOKUP(9.99E+307,I20:T20)=0),"LATEST = 0 · CHECK METER","OK"))))) -> VERIFY AVG-2025 (>3× prior yrs)
B21: 11 | C21: Senior School-1 | D21: Academic | E21: 367.5 | F21: 328.41667 | G21: 2929.3333 | H21: =IF(COUNT(E21:G21)=0,"",MEDIAN(E21:G21)) -> 367.5 | I21: 101 | J21: 50 | K21: 61 | L21: 90 | M21: 7 | N21: 0 | O21: 78 | P21: 82 | U21: =IF(COUNT(I21:T21)=0,"",AVERAGE(I21:T21)) -> 58.625 | V21: =IF(COUNT(I21:T21)=0,"",SUM(I21:T21)) -> 469 | W21: =IF(OR(U21="",N(G21)=0),"",U21/G21-1) -> -0.97998691 | X21: =IF(OR(U21="",N(H21)=0),"",U21/H21-1) -> -0.84047619 | Y21: =COUNT(I21:T21) -> 8 | Z21: =IF(COUNT(I21:T21)=0,"NO 2026 DATA",IF(COUNT(I21:T21)<MATCH(9.99E+307,I21:T21)-MATCH(TRUE,INDEX(ISNUMBER(I21:T21),0),0)+1,"MISSING MONTH(S)",IF(AND(COUNT(E21:F21)=2,N(G21)>3*MAX(E21:F21)),"VERIFY AVG-2025 (>3× prior yrs)",IF(AND(N(H21)>=500,MIN(I21:T21)<0.1*N(H21)),"CHECK OUTLIER MONTH",IF(AND(N(H21)>=50,LOOKUP(9.99E+307,I21:T21)=0),"LATEST = 0 · CHECK METER","OK"))))) -> VERIFY AVG-2025 (>3× prior yrs)
B22: 12 | C22: Senior School-2 | D22: Academic | E22: 51.7075 | F22: 19.708333 | G22: 33.833333 | H22: =IF(COUNT(E22:G22)=0,"",MEDIAN(E22:G22)) -> 33.833333 | I22: 33 | J22: 41 | K22: 15 | L22: 121 | M22: 272 | N22: 5 | O22: 26 | P22: 45 | U22: =IF(COUNT(I22:T22)=0,"",AVERAGE(I22:T22)) -> 69.75 | V22: =IF(COUNT(I22:T22)=0,"",SUM(I22:T22)) -> 558 | W22: =IF(OR(U22="",N(G22)=0),"",U22/G22-1) -> 1.0615764 | X22: =IF(OR(U22="",N(H22)=0),"",U22/H22-1) -> 1.0615764 | Y22: =COUNT(I22:T22) -> 8 | Z22: =IF(COUNT(I22:T22)=0,"NO 2026 DATA",IF(COUNT(I22:T22)<MATCH(9.99E+307,I22:T22)-MATCH(TRUE,INDEX(ISNUMBER(I22:T22),0),0)+1,"MISSING MONTH(S)",IF(AND(COUNT(E22:F22)=2,N(G22)>3*MAX(E22:F22)),"VERIFY AVG-2025 (>3× prior yrs)",IF(AND(N(H22)>=500,MIN(I22:T22)<0.1*N(H22)),"CHECK OUTLIER MONTH",IF(AND(N(H22)>=50,LOOKUP(9.99E+307,I22:T22)=0),"LATEST = 0 · CHECK METER","OK"))))) -> OK
... B28: 18 | C28: PCM | D28: Support | E28: 1081.6667 | F28: 1140.6667 | G28: 1193 | H28: =IF(COUNT(E28:G28)=0,"",MEDIAN(E28:G28)) -> 1140.6667 | I28: 468 | J28: 497 | K28: 520 | L28: 468 | M28: 445 | N28: 589 | O28: 598 | P28: 570 | U28: =IF(COUNT(I28:T28)=0,"",AVERAGE(I28:T28)) -> 519.375 | V28: =IF(COUNT(I28:T28)=0,"",SUM(I28:T28)) -> 4155 | W28: =IF(OR(U28="",N(G28)=0),"",U28/G28-1) -> -0.56464795 | X28: =IF(OR(U28="",N(H28)=0),"",U28/H28-1) -> -0.54467417 | Y28: =COUNT(I28:T28) -> 8 | Z28: =IF(COUNT(I28:T28)=0,"NO 2026 DATA",IF(COUNT(I28:T28)<MATCH(9.99E+307,I28:T28)-MATCH(TRUE,INDEX(ISNUMBER(I28:T28),0),0)+1,"MISSING MONTH(S)",IF(AND(COUNT(E28:F28)=2,N(G28)>3*MAX(E28:F28)),"VERIFY AVG-2025 (>3× prior yrs)",IF(AND(N(H28)>=500,MIN(I28:T28)<0.1*N(H28)),"CHECK OUTLIER MONTH",IF(AND(N(H28)>=50,LOOKUP(9.99E+307,I28:T28)=0),"LATEST = 0 · CHECK METER","OK"))))) -> OK
B29: 19 | C29: Nursery | D29: Support | H29: =IF(COUNT(E29:G29)=0,"",MEDIAN(E29:G29)) | I29: 48 | J29: 33 | K29: 43 | L29: 78 | M29: 204 | N29: 96 | O29: 176 | P29: 209 | U29: =IF(COUNT(I29:T29)=0,"",AVERAGE(I29:T29)) -> 110.875 | V29: =IF(COUNT(I29:T29)=0,"",SUM(I29:T29)) -> 887 | W29: =IF(OR(U29="",N(G29)=0),"",U29/G29-1) | X29: =IF(OR(U29="",N(H29)=0),"",U29/H29-1) | Y29: =COUNT(I29:T29) -> 8 | Z29: =IF(COUNT(I29:T29)=0,"NO 2026 DATA",IF(COUNT(I29:T29)<MATCH(9.99E+307,I29:T29)-MATCH(TRUE,INDEX(ISNUMBER(I29:T29),0),0)+1,"MISSING MONTH(S)",IF(AND(COUNT(E29:F29)=2,N(G29)>3*MAX(E29:F29)),"VERIFY AVG-2025 (>3× prior yrs)",IF(AND(N(H29)>=500,MIN(I29:T29)<0.1*N(H29)),"CHECK OUTLIER MONTH",IF(AND(N(H29)>=50,LOOKUP(9.99E+307,I29:T29)=0),"LATEST = 0 · CHECK METER","OK"))))) -> OK
B30: 20 | C30: Laundry | D30: Support | H30: =IF(COUNT(E30:G30)=0,"",MEDIAN(E30:G30)) | I30: 94 | J30: 98 | K30: 104 | L30: 15 | M30: 87 | N30: 68 | O30: 89 | P30: 135 | U30: =IF(COUNT(I30:T30)=0,"",AVERAGE(I30:T30)) -> 86.25 | V30: =IF(COUNT(I30:T30)=0,"",SUM(I30:T30)) -> 690 | W30: =IF(OR(U30="",N(G30)=0),"",U30/G30-1) | X30: =IF(OR(U30="",N(H30)=0),"",U30/H30-1) | Y30: =COUNT(I30:T30) -> 8 | Z30: =IF(COUNT(I30:T30)=0,"NO 2026 DATA",IF(COUNT(I30:T30)<MATCH(9.99E+307,I30:T30)-MATCH(TRUE,INDEX(ISNUMBER(I30:T30),0),0)+1,"MISSING MONTH(S)",IF(AND(COUNT(E30:F30)=2,N(G30)>3*MAX(E30:F30)),"VERIFY AVG-2025 (>3× prior yrs)",IF(AND(N(H30)>=500,MIN(I30:T30)<0.1*N(H30)),"CHECK OUTLIER MONTH",IF(AND(N(H30)>=50,LOOKUP(9.99E+307,I30:T30)=0),"LATEST = 0 · CHECK METER","OK"))))) -> OK
C31: Σ BUILDING SUB-METERS | E31: =IF(COUNT(E11:E30)=0,"",SUM(E11:E30)) -> 5466.7075 | F31: =IF(COUNT(F11:F30)=0,"",SUM(F11:F30)) -> 5670.125 | G31: =IF(COUNT(G11:G30)=0,"",SUM(G11:G30)) -> 35968.833 | H31: =IF(COUNT(H11:H30)=0,"",SUM(H11:H30)) -> 5904.5833 | I31: =IF(COUNT(I11:I30)=0,"",SUM(I11:I30)) -> 3511 | J31: =IF(COUNT(J11:J30)=0,"",SUM(J11:J30)) -> 3737 | K31: =IF(COUNT(K11:K30)=0,"",SUM(K11:K30)) -> 4736 | L31: =IF(COUNT(L11:L30)=0,"",SUM(L11:L30)) -> 4529 | ... T31: =IF(COUNT(T11:T30)=0,"",SUM(T11:T30)) | U31: =IF(COUNT(I31:T31)=0,"",AVERAGE(I31:T31)) -> 4585.875 | V31: =IF(COUNT(I31:T31)=0,"",SUM(I31:T31)) -> 36687 | W31: =IF(OR(U31="",N(G31)=0),"",U31/G31-1) -> -0.87250421 | X31: =IF(OR(U31="",N(H31)=0),"",U31/H31-1) -> -0.22333639
B32: B · PRIMARY USES (fed from borewells + STP outlet)
B33: 21 | C33: WTP (treated output) | D33: Primary use | E33: 5010.4167 | F33: 12262.25 | G33: 10719 | H33: =IF(COUNT(E33:G33)=0,"",MEDIAN(E33:G33)) -> 10719 | I33: 8770 | J33: 14597 | K33: 12927 | L33: 12096 | M33: 11615 | N33: 7361 | O33: 8310 | P33: 10986 | U33: =IF(COUNT(I33:T33)=0,"",AVERAGE(I33:T33)) -> 10832.75 | V33: =IF(COUNT(I33:T33)=0,"",SUM(I33:T33)) -> 86662 | W33: =IF(OR(U33="",N(G33)=0),"",U33/G33-1) -> 0.010611997 | X33: =IF(OR(U33="",N(H33)=0),"",U33/H33-1) -> 0.010611997 | Y33: =COUNT(I33:T33) -> 8 | Z33: =IF(COUNT(I33:T33)=0,"NO 2026 DATA",IF(COUNT(I33:T33)<MATCH(9.99E+307,I33:T33)-MATCH(TRUE,INDEX(ISNUMBER(I33:T33),0),0)+1,"MISSING MONTH(S)",IF(AND(COUNT(E33:F33)=2,N(G33)>3*MAX(E33:F33)),"VERIFY AVG-2025 (>3× prior yrs)",IF(AND(N(H33)>=500,MIN(I33:T33)<0.1*N(H33)),"CHECK OUTLIER MONTH",IF(AND(N(H33)>=50,LOOKUP(9.99E+307,I33:T33)=0),"LATEST = 0 · CHECK METER","OK"))))) -> OK
B34: 22 | C34: Drip irrigation | D34: Primary use | E34: 7038 | F34: 4009.4167 | G34: 6035.1667 | H34: =IF(COUNT(E34:G34)=0,"",MEDIAN(E34:G34)) -> 6035.1667 | I34: 5643 | J34: 6541 | K34: 6091 | L34: 7080 | M34: 7193 | N34: 3865 | O34: 1136 | P34: 2501 | U34: =IF(COUNT(I34:T34)=0,"",AVERAGE(I34:T34)) -> 5006.25 | V34: =IF(COUNT(I34:T34)=0,"",SUM(I34:T34)) -> 40050 | W34: =IF(OR(U34="",N(G34)=0),"",U34/G34-1) -> -0.17048687 | X34: =IF(OR(U34="",N(H34)=0),"",U34/H34-1) -> -0.17048687 | Y34: =COUNT(I34:T34) -> 8 | Z34: =IF(COUNT(I34:T34)=0,"NO 2026 DATA",IF(COUNT(I34:T34)<MATCH(9.99E+307,I34:T34)-MATCH(TRUE,INDEX(ISNUMBER(I34:T34),0),0)+1,"MISSING MONTH(S)",IF(AND(COUNT(E34:F34)=2,N(G34)>3*MAX(E34:F34)),"VERIFY AVG-2025 (>3× prior yrs)",IF(AND(N(H34)>=500,MIN(I34:T34)<0.1*N(H34)),"CHECK OUTLIER MONTH",IF(AND(N(H34)>=50,LOOKUP(9.99E+307,I34:T34)=0),"LATEST = 0 · CHECK METER","OK"))))) -> OK
B35: 23 | C35: Sports field | D35: Primary use | E35: 3818.8333 | F35: 4664.1667 | G35: 12882.75 | H35: =IF(COUNT(E35:G35)=0,"",MEDIAN(E35:G35)) -> 4664.1667 | I35: 3596 | J35: 0 | K35: 0 | L35: 0 | M35: 0 | O35: 0 | U35: =IF(COUNT(I35:T35)=0,"",AVERAGE(I35:T35)) -> 599.33333 | V35: =IF(COUNT(I35:T35)=0,"",SUM(I35:T35)) -> 3596 | W35: =IF(OR(U35="",N(G35)=0),"",U35/G35-1) -> -0.95347784 | X35: =IF(OR(U35="",N(H35)=0),"",U35/H35-1) -> -0.87150259 | Y35: =COUNT(I35:T35) -> 6 | Z35: =IF(COUNT(I35:T35)=0,"NO 2026 DATA",IF(COUNT(I35:T35)<MATCH(9.99E+307,I35:T35)-MATCH(TRUE,INDEX(ISNUMBER(I35:T35),0),0)+1,"MISSING MONTH(S)",IF(AND(COUNT(E35:F35)=2,N(G35)>3*MAX(E35:F35)),"VERIFY AVG-2025 (>3× prior yrs)",IF(AND(N(H35)>=500,MIN(I35:T35)<0.1*N(H35)),"CHECK OUTLIER MONTH",IF(AND(N(H35)>=50,LOOKUP(9.99E+307,I35:T35)=0),"LATEST = 0 · CHECK METER","OK"))))) -> MISSING MONTH(S)
C36: Σ PRIMARY USES | E36: =IF(COUNT(E33:E35)=0,"",SUM(E33:E35)) -> 15867.25 | F36: =IF(COUNT(F33:F35)=0,"",SUM(F33:F35)) -> 20935.833 | G36: =IF(COUNT(G33:G35)=0,"",SUM(G33:G35)) -> 29636.917 | H36: =IF(COUNT(H33:H35)=0,"",SUM(H33:H35)) -> 21418.333 | I36: =IF(COUNT(I33:I35)=0,"",SUM(I33:I35)) -> 18009 | J36: =IF(COUNT(J33:J35)=0,"",SUM(J33:J35)) -> 21138 | K36: =IF(COUNT(K33:K35)=0,"",SUM(K33:K35)) -> 19018 | L36: =IF(COUNT(L33:L35)=0,"",SUM(L33:L35)) -> 19176 | ... T36: =IF(COUNT(T33:T35)=0,"",SUM(T33:T35)) | U36: =IF(COUNT(I36:T36)=0,"",AVERAGE(I36:T36)) -> 16288.5 | V36: =IF(COUNT(I36:T36)=0,"",SUM(I36:T36)) -> 130308 | W36: =IF(OR(U36="",N(G36)=0),"",U36/G36-1) -> -0.45039829 | X36: =IF(OR(U36="",N(H36)=0),"",U36/H36-1) -> -0.23950665
B37: C · SOURCES (campus inlet)
B38: 24 | C38: Borewells | D38: Source | E38: 11410.118 | F38: 17298.033 | G38: 29581.061 | H38: =IF(COUNT(E38:G38)=0,"",MEDIAN(E38:G38)) -> 17298.033 | I38: 15002 | J38: 19302.67 | K38: 17647.45 | L38: 18490.49 | M38: 21759.4 | N38: 11528.59 | O38: 15618.59 | P38: 11995 | U38: =IF(COUNT(I38:T38)=0,"",AVERAGE(I38:T38)) -> 16418.024 | V38: =IF(COUNT(I38:T38)=0,"",SUM(I38:T38)) -> 131344.19 | W38: =IF(OR(U38="",N(G38)=0),"",U38/G38-1) -> -0.44498191 | X38: =IF(OR(U38="",N(H38)=0),"",U38/H38-1) -> -0.050873389 | Y38: =COUNT(I38:T38) -> 8 | Z38: =IF(COUNT(I38:T38)=0,"NO 2026 DATA",IF(COUNT(I38:T38)<MATCH(9.99E+307,I38:T38)-MATCH(TRUE,INDEX(ISNUMBER(I38:T38),0),0)+1,"MISSING MONTH(S)",IF(AND(COUNT(E38:F38)=2,N(G38)>3*MAX(E38:F38)),"VERIFY AVG-2025 (>3× prior yrs)",IF(AND(N(H38)>=500,MIN(I38:T38)<0.1*N(H38)),"CHECK OUTLIER MONTH",IF(AND(N(H38)>=50,LOOKUP(9.99E+307,I38:T38)=0),"LATEST = 0 · CHECK METER","OK"))))) -> OK
B39: 25 | C39: STP outlet (recycled) | D39: Source | E39: 7230.2692 | F39: 3584 | G39: 4534.8333 | H39: =IF(COUNT(E39:G39)=0,"",MEDIAN(E39:G39)) -> 4534.8333 | I39: 3596 | J39: 5654 | K39: 4885 | L39: 3764 | M39: 1496 | N39: 1929 | O39: 2303 | P39: 2683 | U39: =IF(COUNT(I39:T39)=0,"",AVERAGE(I39:T39)) -> 3288.75 | V39: =IF(COUNT(I39:T39)=0,"",SUM(I39:T39)) -> 26310 | W39: =IF(OR(U39="",N(G39)=0),"",U39/G39-1) -> -0.2747804 | X39: =IF(OR(U39="",N(H39)=0),"",U39/H39-1) -> -0.2747804 | Y39: =COUNT(I39:T39) -> 8 | Z39: =IF(COUNT(I39:T39)=0,"NO 2026 DATA",IF(COUNT(I39:T39)<MATCH(9.99E+307,I39:T39)-MATCH(TRUE,INDEX(ISNUMBER(I39:T39),0),0)+1,"MISSING MONTH(S)",IF(AND(COUNT(E39:F39)=2,N(G39)>3*MAX(E39:F39)),"VERIFY AVG-2025 (>3× prior yrs)",IF(AND(N(H39)>=500,MIN(I39:T39)<0.1*N(H39)),"CHECK OUTLIER MONTH",IF(AND(N(H39)>=50,LOOKUP(9.99E+307,I39:T39)=0),"LATEST = 0 · CHECK METER","OK"))))) -> OK
C40: Σ INLET (borewells + STP outlet) | E40: =IF(COUNT(E38:E39)=0,"",SUM(E38:E39)) -> 18640.387 | F40: =IF(COUNT(F38:F39)=0,"",SUM(F38:F39)) -> 20882.033 | G40: =IF(COUNT(G38:G39)=0,"",SUM(G38:G39)) -> 34115.894 | H40: =IF(COUNT(H38:H39)=0,"",SUM(H38:H39)) -> 21832.867 | I40: =IF(COUNT(I38:I39)=0,"",SUM(I38:I39)) -> 18598 | J40: =IF(COUNT(J38:J39)=0,"",SUM(J38:J39)) -> 24956.67 | K40: =IF(COUNT(K38:K39)=0,"",SUM(K38:K39)) -> 22532.45 | L40: =IF(COUNT(L38:L39)=0,"",SUM(L38:L39)) -> 22254.49 | ... T40: =IF(COUNT(T38:T39)=0,"",SUM(T38:T39)) | U40: =IF(COUNT(I40:T40)=0,"",AVERAGE(I40:T40)) -> 19706.774 | V40: =IF(COUNT(I40:T40)=0,"",SUM(I40:T40)) -> 157654.19 | W40: =IF(OR(U40="",N(G40)=0),"",U40/G40-1) -> -0.42235799 | X40: =IF(OR(U40="",N(H40)=0),"",U40/H40-1) -> -0.097380383
B41: D · WATER BALANCE & METER COVERAGE
C42: Inlet − primary uses (kL) | E42: =IF(OR(E40="",E36=""),"",E40-E36) -> 2773.1375 | F42: =IF(OR(F40="",F36=""),"",F40-F36) -> -53.8 | G42: =IF(OR(G40="",G36=""),"",G40-G36) -> 4478.9775 | I42: =IF(OR(I40="",I36=""),"",I40-I36) -> 589 | J42: =IF(OR(J40="",J36=""),"",J40-J36) -> 3818.67 | K42: =IF(OR(K40="",K36=""),"",K40-K36) -> 3514.45 | L42: =IF(OR(L40="",L36=""),"",L40-L36) -> 3078.49 | M42: =IF(OR(M40="",M36=""),"",M40-M36) -> 4447.4 | N42: =IF(OR(N40="",N36=""),"",N40-N36) -> 2231.59 | O42: =IF(OR(O40="",O36=""),"",O40-O36) -> 8475.59 | P42: =IF(OR(P40="",P36=""),"",P40-P36) -> 1191 | ... T42: =IF(OR(T40="",T36=""),"",T40-T36) | U42: =IF(COUNT(I42:T42)=0,"",AVERAGE(I42:T42)) -> 3418.2738 | Z42: Tank storage change, sprinklers & losses. Negative = more used than metered inlet.
C43: WTP output − building meters (kL) | E43: =IF(OR(E33="",E31=""),"",E33-E31) -> -456.29083 | F43: =IF(OR(F33="",F31=""),"",F33-F31) -> 6592.125 | G43: =IF(OR(G33="",G31=""),"",G33-G31) -> -25249.833 | I43: =IF(OR(I33="",I31=""),"",I33-I31) -> 5259 | J43: =IF(OR(J33="",J31=""),"",J33-J31) -> 10860 | K43: =IF(OR(K33="",K31=""),"",K33-K31) -> 8191 | L43: =IF(OR(L33="",L31=""),"",L33-L31) -> 7567 | M43: =IF(OR(M33="",M31=""),"",M33-M31) -> 7594 | N43: =IF(OR(N33="",N31=""),"",N33-N31) -> 4787 | O43: =IF(OR(O33="",O31=""),"",O33-O31) -> 1759 | P43: =IF(OR(P33="",P31=""),"",P33-P31) -> 3958 | ... T43: =IF(OR(T33="",T31=""),"",T33-T31) | U43: =IF(COUNT(I43:T43)=0,"",AVERAGE(I43:T43)) -> 6246.875 | Z43: Un-metered use + softener backwash/regeneration + distribution loss.
C44: Building sub-meter coverage of WTP | E44: =IF(OR(E33="",E31="",N(E33)=0),"",E31/E33) -> 1.0910684 | F44: =IF(OR(F33="",F31="",N(F33)=0),"",F31/F33) -> 0.46240494 | G44: =IF(OR(G33="",G31="",N(G33)=0),"",G31/G33) -> 3.3556146 | I44: =IF(OR(I33="",I31="",N(I33)=0),"",I31/I33) -> 0.40034208 | J44: =IF(OR(J33="",J31="",N(J33)=0),"",J31/J33) -> 0.25601151 | K44: =IF(OR(K33="",K31="",N(K33)=0),"",K31/K33) -> 0.36636497 | L44: =IF(OR(L33="",L31="",N(L33)=0),"",L31/L33) -> 0.3744213 | M44: =IF(OR(M33="",M31="",N(M33)=0),"",M31/M33) -> 0.34619027 | N44: =IF(OR(N33="",N31="",N(N33)=0),"",N31/N33) -> 0.34968075 | O44: =IF(OR(O33="",O31="",N(O33)=0),"",O31/O33) -> 0.78832732 | P44: =IF(OR(P33="",P31="",N(P33)=0),"",P31/P33) -> 0.63972328 | ... T44: =IF(OR(T33="",T31="",N(T33)=0),"",T31/T33) | U44: =IFERROR(SUMPRODUCT(--ISNUMBER(I33:T33),--ISNUMBER(I31:T31),I31:T31)/SUMPRODUCT(--ISNUMBER(I33:T33),--ISNUMBER(I31:T31),I33:T33),"") -> 0.42333433 | Z44: Share of WTP output that building meters account for (YTD = months where both exist).
C45: Meters reporting (of 25) | I45: =COUNT(I11:I30,I33:I35,I38:I39) -> 25 | J45: =COUNT(J11:J30,J33:J35,J38:J39) -> 25 | K45: =COUNT(K11:K30,K33:K35,K38:K39) -> 25 | L45: =COUNT(L11:L30,L33:L35,L38:L39) -> 25 | M45: =COUNT(M11:M30,M33:M35,M38:M39) -> 25 | N45: =COUNT(N11:N30,N33:N35,N38:N39) -> 24 | O45: =COUNT(O11:O30,O33:O35,O38:O39) -> 25 | P45: =COUNT(P11:P30,P33:P35,P38:P39) -> 24 | ... T45: =COUNT(T11:T30,T33:T35,T38:T39) -> 0 | Z45: Months with fewer meters are incomplete – totals understate use.
B53: SAME-MONTH YEAR-ON-YEAR · Jan-25 vs Jan-26 (kL)
B54: # | C54: Location | D54: Jan-25 | E54: Jan-26 | F54: Δ kL | G54: Δ % | H54: Note
B55: 1 | C55: SR-1 | D55: 192 | E55: =IF(I11="","",I11) -> 264 | F55: =IF(OR(D55="",E55=""),"",E55-D55) -> 72 | G55: =IF(OR(D55="",E55="",N(D55)=0),"",E55/D55-1) -> 0.375
B56: 2 | C56: SR-2 | D56: 133 | E56: =IF(I12="","",I12) -> 267 | F56: =IF(OR(D56="",E56=""),"",E56-D56) -> 134 | G56: =IF(OR(D56="",E56="",N(D56)=0),"",E56/D56-1) -> 1.0075188
B57: 3 | C57: SR-3 | D57: 202 | E57: =IF(I13="","",I13) -> 205 | F57: =IF(OR(D57="",E57=""),"",E57-D57) -> 3 | G57: =IF(OR(D57="",E57="",N(D57)=0),"",E57/D57-1) -> 0.014851485
B58: 4 | C58: SR-4 | D58: 84 | E58: =IF(I14="","",I14) -> 136 | F58: =IF(OR(D58="",E58=""),"",E58-D58) -> 52 | G58: =IF(OR(D58="",E58="",N(D58)=0),"",E58/D58-1) -> 0.61904762
B59: 5 | C59: SR-9-10B1A | D59: 826 | E59: =IF(I15="","",I15) -> 568 | F59: =IF(OR(D59="",E59=""),"",E59-D59) -> -258 | G59: =IF(OR(D59="",E59="",N(D59)=0),"",E59/D59-1) -> -0.31234867
B60: 6 | C60: SR-9-10B1B | D60: 402 | E60: =IF(I16="","",I16) -> 209 | F60: =IF(OR(D60="",E60=""),"",E60-D60) -> -193 | G60: =IF(OR(D60="",E60="",N(D60)=0),"",E60/D60-1) -> -0.4800995
B61: 7 | C61: SR-11-12CA | D61: 282 | E61: =IF(I17="","",I17) -> 233 | F61: =IF(OR(D61="",E61=""),"",E61-D61) -> -49 | G61: =IF(OR(D61="",E61="",N(D61)=0),"",E61/D61-1) -> -0.17375887
B62: 8 | C62: SR-11-12CB | D62: 402 | E62: =IF(I18="","",I18) -> 0 | F62: =IF(OR(D62="",E62=""),"",E62-D62) -> -402 | G62: =IF(OR(D62="",E62="",N(D62)=0),"",E62/D62-1) -> -1
B63: 9 | C63: Junior School-1&2 | D63: 340 | E63: =IF(I19="","",I19) -> 0 | F63: =IF(OR(D63="",E63=""),"",E63-D63) -> -340 | G63: =IF(OR(D63="",E63="",N(D63)=0),"",E63/D63-1) -> -1
B64: 10 | C64: Junior School-3 | D64: 9 | E64: =IF(I20="","",I20) -> 27 | F64: =IF(OR(D64="",E64=""),"",E64-D64) -> 18 | G64: =IF(OR(D64="",E64="",N(D64)=0),"",E64/D64-1) -> 2
B65: 11 | C65: Senior School-1 | D65: 144 | E65: =IF(I21="","",I21) -> 101 | F65: =IF(OR(D65="",E65=""),"",E65-D65) -> -43 | G65: =IF(OR(D65="",E65="",N(D65)=0),"",E65/D65-1) -> -0.29861111
B66: 12 | C66: Senior School-2 | D66: 21 | E66: =IF(I22="","",I22) -> 33 | F66: =IF(OR(D66="",E66=""),"",E66-D66) -> 12 | G66: =IF(OR(D66="",E66="",N(D66)=0),"",E66/D66-1) -> 0.57142857
... B68: 14 | C68: Academy Building | D68: 318 | E68: =IF(I24="","",I24) -> 1 | F68: =IF(OR(D68="",E68=""),"",E68-D68) -> -317 | G68: =IF(OR(D68="",E68="",N(D68)=0),"",E68/D68-1) -> -0.99685535
B69: 15 | C69: Commons | D69: 604 | E69: =IF(I25="","",I25) -> 180 | F69: =IF(OR(D69="",E69=""),"",E69-D69) -> -424 | G69: =IF(OR(D69="",E69="",N(D69)=0),"",E69/D69-1) -> -0.70198675 | H69: Old table had 31 typed; meter table says 180 – verify
B70: 16 | C70: Swimming Pool | D70: 345 | E70: =IF(I26="","",I26) -> 526 | F70: =IF(OR(D70="",E70=""),"",E70-D70) -> 181 | G70: =IF(OR(D70="",E70="",N(D70)=0),"",E70/D70-1) -> 0.52463768
B71: 17 | C71: Athletic Centre | D71: 137 | E71: =IF(I27="","",I27) -> 151 | F71: =IF(OR(D71="",E71=""),"",E71-D71) -> 14 | G71: =IF(OR(D71="",E71="",N(D71)=0),"",E71/D71-1) -> 0.10218978
B72: 18 | C72: PCM | D72: 578 | E72: =IF(I28="","",I28) -> 468 | F72: =IF(OR(D72="",E72=""),"",E72-D72) -> -110 | G72: =IF(OR(D72="",E72="",N(D72)=0),"",E72/D72-1) -> -0.19031142
B73: 19 | C73: Nursery | E73: =IF(I29="","",I29) -> 48 | F73: =IF(OR(D73="",E73=""),"",E73-D73) | G73: =IF(OR(D73="",E73="",N(D73)=0),"",E73/D73-1) | H73: No Jan-25 history
B74: 20 | C74: Laundry | E74: =IF(I30="","",I30) -> 94 | F74: =IF(OR(D74="",E74=""),"",E74-D74) | G74: =IF(OR(D74="",E74="",N(D74)=0),"",E74/D74-1) | H74: Meter starts Mar-26
B75: 21 | C75: WTP (treated output) | D75: 14183 | E75: =IF(I33="","",I33) -> 8770 | F75: =IF(OR(D75="",E75=""),"",E75-D75) -> -5413 | G75: =IF(OR(D75="",E75="",N(D75)=0),"",E75/D75-1) -> -0.38165409
B76: 22 | C76: Drip irrigation | D76: 4690 | E76: =IF(I34="","",I34) -> 5643 | F76: =IF(OR(D76="",E76=""),"",E76-D76) -> 953 | G76: =IF(OR(D76="",E76="",N(D76)=0),"",E76/D76-1) -> 0.20319829
B77: 23 | C77: Sports field | D77: 16890 | E77: =IF(I35="","",I35) -> 3596 | F77: =IF(OR(D77="",E77=""),"",E77-D77) -> -13294 | G77: =IF(OR(D77="",E77="",N(D77)=0),"",E77/D77-1) -> -0.78709295 | H77: Jan-26 equals STP outlet (3,596) – suspected copy
B78: 24 | C78: Borewells | D78: 19290.87 | E78: =IF(I38="","",I38) -> 15002 | F78: =IF(OR(D78="",E78=""),"",E78-D78) -> -4288.87 | G78: =IF(OR(D78="",E78="",N(D78)=0),"",E78/D78-1) -> -0.22232642
B79: 25 | C79: STP outlet (recycled) | D79: 4704 | E79: =IF(I39="","",I39) -> 3596 | F79: =IF(OR(D79="",E79=""),"",E79-D79) -> -1108 | G79: =IF(OR(D79="",E79="",N(D79)=0),"",E79/D79-1) -> -0.23554422
B82: Unlabelled legacy values (were at M63:M67, no location or month) – owner to identify or delete:
C83: values | D83: 61 | E83: 140 | F83: 122 | G83: 373 | H83: 489

Sheet LPCD
A1: LPCD · LITRES PER CAPITA PER DAY
A3: LPCD = monthly litres ÷ occupants ÷ days in month (averages ÷ 365/12). Benchmark 135 LPCD is domestic.
B4: Month | C4: Water Consumption in Ltrs | D4: No. of occupants | E4: Benchmark | F4: LPCD
B5: Avg 2023 | C5: 39998606 | D5: 1354 | E5: 135 | F5: =IFERROR(C5/D5/(365/12),"") -> 971.21319
B6: Avg 2024 | C6: 47504705 | D6: 1354 | E6: 135 | F6: =IFERROR(C6/D6/(365/12),"") -> 1153.4701
B7: Avg 2025 | C7: 1.0016867e+08 | D7: 1354 | E7: 135 | F7: =IFERROR(C7/D7/(365/12),"") -> 2432.213
B8: 46023 | C8: 40704000 | D8: 1354 | E8: 135 | F8: =IF(OR(C8="",D8=""),"",IFERROR(C8/D8/DAY(EOMONTH(B8,0)),"")) -> 969.74317
B9: 46054 | C9: 66046000 | D9: 1354 | E9: 135 | F9: =IF(OR(C9="",D9=""),"",IFERROR(C9/D9/DAY(EOMONTH(B9,0)),"")) -> 1742.0869
B10: 46082 | C10: 19919000 | D10: 1354 | E10: 135 | F10: =IF(OR(C10="",D10=""),"",IFERROR(C10/D10/DAY(EOMONTH(B10,0)),"")) -> 474.55568
B11: 46113 | C11: 21828000 | D11: 1354 | E11: 135 | F11: =IF(OR(C11="",D11=""),"",IFERROR(C11/D11/DAY(EOMONTH(B11,0)),"")) -> 537.37075
B12: 46143 | C12: 26607000 | D12: 1354 | E12: 135 | F12: =IF(OR(C12="",D12=""),"",IFERROR(C12/D12/DAY(EOMONTH(B12,0)),"")) -> 633.89241
B13: 46174 | C13: 12988000 | D13: 1354 | E13: 135 | F13: =IF(OR(C13="",D13=""),"",IFERROR(C13/D13/DAY(EOMONTH(B13,0)),"")) -> 319.74397
B14: 46204 | C14: 9633000 | D14: 1354 | E14: 135 | F14: =IF(OR(C14="",D14=""),"",IFERROR(C14/D14/DAY(EOMONTH(B14,0)),"")) -> 229.49921
B15: 46235 | C15: 14026000 | D15: 1354 | E15: 135 | F15: =IF(OR(C15="",D15=""),"",IFERROR(C15/D15/DAY(EOMONTH(B15,0)),"")) -> 334.15924
B16: 46266 | D16: 1354 | E16: 135 | F16: =IF(OR(C16="",D16=""),"",IFERROR(C16/D16/DAY(EOMONTH(B16,0)),""))
B17: 46296 | D17: 1354 | E17: 135 | F17: =IF(OR(C17="",D17=""),"",IFERROR(C17/D17/DAY(EOMONTH(B17,0)),""))
B18: 46327 | D18: 1354 | E18: 135 | F18: =IF(OR(C18="",D18=""),"",IFERROR(C18/D18/DAY(EOMONTH(B18,0)),""))
B19: 46357 | D19: 1354 | E19: 135 | F19: =IF(OR(C19="",D19=""),"",IFERROR(C19/D19/DAY(EOMONTH(B19,0)),""))
B20: Avg 2026 | C20: =IFERROR(AVERAGE(C8:C19),"") -> 26468875 | D20: =IFERROR(AVERAGE(D8:D19),"") -> 1354 | E20: =SUBTOTAL(101,LPCDTable[Benchmark]) -> 135 | F20: =IFERROR(AVERAGE(F8:F19),"") -> 655.13142
B23: Comparison | C23: 45839 | D23: 46054
B24: Water Con in Lt | C24: 82376000 | D24: =C9 -> 66046000
B25: No of Occupants | C25: 1354 | D25: =D9 -> 1354
B26: LPCD | C26: =IFERROR(C24/C25/DAY(EOMONTH(C23,0)),"") -> 1962.5482 | D26: =IFERROR(D24/D25/DAY(EOMONTH(D23,0)),"") -> 1742.0869
B27: Benchmark (LPCD) | C27: 135 | D27: =E9 -> 135

Sheet EPI
A1: EPI · ENERGY PERFORMANCE INDEX (kWh / m² / month)
B3: Electricity consumption / Sq.m/month
B4: Month | C4: Benchmark | D4: kWh/Sq.m/month
B5: Avg-2024 | C5: 8 | D5: ='Power data'!C5/$D$19 -> 3.5124319
B6: Avg-2025 | C6: 8 | D6: ='Power data'!C6/$D$19 -> 2.5218193
B7: 46023 | C7: 8 | D7: =IF('Power data'!C7="","",IFERROR('Power data'!C7/$D$19,"")) -> 1.2649028
B8: 46054 | C8: 8 | D8: =IF('Power data'!C8="","",IFERROR('Power data'!C8/$D$19,"")) -> 1.8182693
B9: 46082 | C9: 8 | D9: =IF('Power data'!C9="","",IFERROR('Power data'!C9/$D$19,"")) -> 2.3769917
B10: 46113 | C10: 8 | D10: =IF('Power data'!C10="","",IFERROR('Power data'!C10/$D$19,"")) -> 3.7617754
B11: 46143 | C11: 8 | D11: =IF('Power data'!C11="","",IFERROR('Power data'!C11/$D$19,"")) -> 4.2190776
B12: 46174 | C12: 8 | D12: =IF('Power data'!C12="","",IFERROR('Power data'!C12/$D$19,"")) -> 1.3847837
B13: 46204 | C13: 8 | D13: =IF('Power data'!C13="","",IFERROR('Power data'!C13/$D$19,"")) -> 2.3295863
B14: 46235 | C14: 8 | D14: =IF('Power data'!C14="","",IFERROR('Power data'!C14/$D$19,"")) -> 2.7801652
B15: 46266 | C15: 8 | D15: =IF('Power data'!C15="","",IFERROR('Power data'!C15/$D$19,""))
B16: 46296 | C16: 8 | D16: =IF('Power data'!C16="","",IFERROR('Power data'!C16/$D$19,""))
B17: 46327 | C17: 8 | D17: =IF('Power data'!C17="","",IFERROR('Power data'!C17/$D$19,""))
B18: 46357 | C18: 8 | D18: =IF('Power data'!C18="","",IFERROR('Power data'!C18/$D$19,""))
B19: Built-up Area (sq.mtr) | D19: 52652.267
B24: Power consumption / Sq.m/month
B25: 45689 | C25: 46023 | D25: Benchmark
B26: 2.49 | C26: =D7 -> 1.2649028 | D26: 8

Sheet Power data
A1: HT POWER CONSUMPTION & COST
B3: Month | C3: HT Units in kWh | D3: HT Units in kVAH | E3: PF | F3: Amount | G3: Unit Rate | H3: MD-Recorded | I3: Sanctioned MD
B4: Avg 2023 | D4: 214546.21 | E4: =IF(OR(C4="",D4=""),"",IFERROR(C4/D4,"")) | F4: 2534576.9 | G4: =IF(OR(F4="",D4=""),"",IFERROR(F4/D4,"")) -> 11.813664 | H4: 562 | I4: 1276
B5: Avg 2024 | C5: 184937.5 | D5: 187911.83 | E5: =IF(OR(C5="",D5=""),"",IFERROR(C5/D5,"")) -> 0.98417165 | F5: 2309764.7 | G5: =IF(OR(F5="",D5=""),"",IFERROR(F5/D5,"")) -> 12.291747 | H5: 1117 | I5: 1276
B6: Avg 2025 | C6: 132779.5 | D6: 137678 | E6: =IF(OR(C6="",D6=""),"",IFERROR(C6/D6,"")) -> 0.9644206 | F6: 1741299.4 | G6: =IF(OR(F6="",D6=""),"",IFERROR(F6/D6,"")) -> 12.647623 | H6: 511.03333 | I6: 1276
B7: 46023 | C7: 66600 | D7: 78804 | E7: =IF(OR(C7="",D7=""),"",IFERROR(C7/D7,"")) -> 0.84513476 | F7: 929887.2 | G7: =IF(OR(F7="",D7=""),"",IFERROR(F7/D7,"")) -> 11.8 | H7: 306 | I7: 1276
B8: 46054 | C8: 95736 | D8: 100326 | E8: =IF(OR(C8="",D8=""),"",IFERROR(C8/D8,"")) -> 0.95424915 | F8: 1099602 | G8: =IF(OR(F8="",D8=""),"",IFERROR(F8/D8,"")) -> 10.960289 | H8: 386 | I8: 1276
B9: 46082 | C9: 125154 | D9: 129780 | E9: =IF(OR(C9="",D9=""),"",IFERROR(C9/D9,"")) -> 0.96435506 | F9: 1406695 | G9: =IF(OR(F9="",D9=""),"",IFERROR(F9/D9,"")) -> 10.839074 | H9: 440 | I9: 1276
B10: 46113 | C10: 198066 | D10: 204438 | E10: =IF(OR(C10="",D10=""),"",IFERROR(C10/D10,"")) -> 0.96883163 | F10: 2109953 | G10: =IF(OR(F10="",D10=""),"",IFERROR(F10/D10,"")) -> 10.320748 | H10: 744 | I10: 1276
B11: 46143 | C11: 222144 | D11: 226842 | E11: =IF(OR(C11="",D11=""),"",IFERROR(C11/D11,"")) -> 0.97928955 | F11: 2496490 | G11: =IF(OR(F11="",D11=""),"",IFERROR(F11/D11,"")) -> 11.005413 | H11: 706 | I11: 1276
B12: 46174 | C12: 72912 | D12: 75684 | E12: =IF(OR(C12="",D12=""),"",IFERROR(C12/D12,"")) -> 0.96337403 | F12: 777429 | G12: =IF(OR(F12="",D12=""),"",IFERROR(F12/D12,"")) -> 10.272039 | H12: 321 | I12: 1276
B13: 46204 | C13: 122658 | D13: 126318 | E13: =IF(OR(C13="",D13=""),"",IFERROR(C13/D13,"")) -> 0.97102551 | F13: 1501851 | G13: =IF(OR(F13="",D13=""),"",IFERROR(F13/D13,"")) -> 11.889446 | H13: 451.44 | I13: 1276
B14: 46235 | C14: 146382 | D14: 156360 | E14: =IF(OR(C14="",D14=""),"",IFERROR(C14/D14,"")) -> 0.93618573 | F14: 1829571 | G14: =IF(OR(F14="",D14=""),"",IFERROR(F14/D14,"")) -> 11.701017 | H14: 475 | I14: 1276
B15: 46266 | E15: =IF(OR(C15="",D15=""),"",IFERROR(C15/D15,"")) | G15: =IF(OR(F15="",D15=""),"",IFERROR(F15/D15,""))
B16: 46296 | E16: =IF(OR(C16="",D16=""),"",IFERROR(C16/D16,"")) | G16: =IF(OR(F16="",D16=""),"",IFERROR(F16/D16,""))
B17: 46327 | E17: =IF(OR(C17="",D17=""),"",IFERROR(C17/D17,"")) | G17: =IF(OR(F17="",D17=""),"",IFERROR(F17/D17,""))
B18: 46357 | E18: =IF(OR(C18="",D18=""),"",IFERROR(C18/D18,"")) | G18: =IF(OR(F18="",D18=""),"",IFERROR(F18/D18,""))
B19: TOTAL 2026 YTD | C19: =SUM(C7:C18) -> 1049652 | D19: =SUM(D7:D18) -> 1098552 | E19: =IFERROR(C19/D19,"") -> 0.95548686 | F19: =SUM(F7:F18) -> 12151478 | G19: =IFERROR(F19/D19,"") -> 11.061359
B20: Avg 2026 | C20: =IFERROR(AVERAGE(C7:C18),"") -> 131206.5 | D20: =IFERROR(AVERAGE(D7:D18),"") -> 137319 | E20: =IFERROR(AVERAGE(E7:E18),"") -> 0.94780568 | F20: =IFERROR(AVERAGE(F7:F18),"") -> 1518934.8 | G20: =IFERROR(F20/D20,"") -> 11.061359 | H20: =IFERROR(AVERAGE(H7:H18),"") -> 478.68 | I20: =IFERROR(AVERAGE(I7:I18),"") -> 1276
B21: Avg 2026 ('000) | C21: =IFERROR(C20/1000,"") -> 131.2065 | D21: =IFERROR(D20/1000,"") -> 137.319 | F21: =IFERROR(F20/1000,"") -> 1518.9348
B23: Parameter | C23: 45689 | D23: 46054
B24: KWH | C24: 131316 | D24: =C8 -> 95736
B25: KVAH | C25: 134268 | D25: =D8 -> 100326
B26: Amount | C26: 1584362 | D26: =F8 -> 1099602
B27: Unit Rate | C27: =IFERROR(C26/C25,"") -> 11.799997 | D27: =IFERROR(D26/D25,"") -> 10.960289
B28: MD Recorded | C28: 528 | D28: =H8 -> 386
B29: Sanctiond MD | C29: 1276 | D29: =I8 -> 1276

Sheet Power Building wise
A1: BUILDING-WISE POWER CONSUMPTION (kWh) · 2026
A2: S No | B2: Buildings | C2: Avg 2024 | D2: Avg 2025 | E2: Jan-26 | F2: Feb-26 | G2: Mar-26 | H2: Apr-26 | I2: May-26 | J2: Jun-26 | K2: Jul-26 | L2: Aug-26 | M2: Sep-26 | N2: Oct-26 | O2: Nov-26 | P2: Dec-26 | Q2: Avg 2026 YTD | R2: Building | S2: Feb-25 | T2: Feb-26
A3: 1 | B3: SR1,2,3&4 Emergency | C3: 563.83333 | D3: 537.83333 | E3: 480 | F3: 525 | G3: 675 | H3: 653 | I3: 647 | J3: 573 | K3: 631 | L3: 815 | Q3: =IFERROR(AVERAGE(E3:P3),"") -> 624.875 | R3: SR1,2,3&4 Emgy. | S3: 538 | T3: =F3 -> 525
A4: 2 | B4: SR 9&10A,B 11-12A,B Emergency | C4: 2122.5 | D4: 1150.25 | E4: 1154 | F4: 1119 | G4: 1257 | H4: 1253 | I4: 1203 | J4: 1054 | K4: 1234 | L4: 1331 | Q4: =IFERROR(AVERAGE(E4:P4),"") -> 1200.625 | R4: SR9/10AB,SR11/12A,B Emgy. | S4: 1850 | T4: =F4 -> 1119
A5: 3 | B5: Laundry | C5: 2708.75 | D5: 2706.5 | E5: 2447 | F5: 2920 | G5: 3006 | H5: 3383 | I5: 2839 | J5: 2202 | K5: 2875 | L5: 3382 | Q5: =IFERROR(AVERAGE(E5:P5),"") -> 2881.75 | R5: Laundry | S5: 2964 | T5: =F5 -> 2920
A6: 4 | B6: Substation | C6: 212.821 | D6: 667.50833 | E6: 436 | F6: 602 | G6: 993.3 | H6: 961.7 | I6: 1173 | J6: 1030 | K6: 836 | L6: 933 | Q6: =IFERROR(AVERAGE(E6:P6),"") -> 870.625 | R6: Substation | S6: 667 | T6: =F6 -> 602
A7: 5 | B7: SR-1 | C7: 3459.9167 | D7: 2632 | E7: 2273 | F7: 3173 | G7: 4616 | H7: 6151 | I7: 5274 | J7: 2391 | K7: 4289 | L7: 4790 | Q7: =IFERROR(AVERAGE(E7:P7),"") -> 4119.625 | R7: SR-1 | S7: 3171 | T7: =F7 -> 3173
A8: 6 | B8: SR-2 | C8: 4117.75 | D8: 3026.4167 | E8: 2426 | F8: 2719 | G8: 4525 | H8: 6080 | I8: 7229 | J8: 2576 | K8: 3615 | L8: 4692 | Q8: =IFERROR(AVERAGE(E8:P8),"") -> 4232.75 | R8: SR-2 | S8: 3893 | T8: =F8 -> 2719
A9: 7 | B9: SR-3 | C9: 3465.4167 | D9: 3216.8333 | E9: 1858 | F9: 3608 | G9: 3486 | H9: 4748 | I9: 4922 | J9: 2227 | K9: 4090 | L9: 5092 | Q9: =IFERROR(AVERAGE(E9:P9),"") -> 3753.875 | R9: SR-3 | S9: 4717 | T9: =F9 -> 3608
A10: 8 | B10: SR-4 | C10: 4755.3333 | D10: 3604.75 | E10: 3035 | F10: 5027 | G10: 7021 | H10: 9892 | I10: 10722 | J10: 2915 | K10: 6848 | L10: 6408 | Q10: =IFERROR(AVERAGE(E10:P10),"") -> 6483.5 | R10: SR-4 | S10: 3563 | T10: =F10 -> 5027
A11: 9 | B11: SR-9-10A | C11: 8637 | D11: 5664.7667 | E11: 2936 | F11: 4122 | G11: 8610 | H11: 13623 | I11: 4475 | J11: 2951 | K11: 3693 | L11: 3576 | Q11: =IFERROR(AVERAGE(E11:P11),"") -> 5498.25 | R11: SR-9-10A | S11: 2756.2 | T11: =F11 -> 4122
A12: 10 | B12: SR-9-10B | C12: 5749.0833 | D12: 5468.95 | E12: 4053 | F12: 6416 | G12: 9833 | H12: 14587 | I12: 12517 | J12: 1965 | K12: 5778 | L12: 12306 | Q12: =IFERROR(AVERAGE(E12:P12),"") -> 8431.875 | R12: SR-9-10B | S12: 1991.4 | T12: =F12 -> 6416
A13: 11 | B13: SR-11-12CA | C13: 6480.25 | D13: 4599.4 | E13: 3981 | F13: 5304 | G13: 7352 | H13: 9602 | I13: 9997 | J13: 4369 | K13: 4443 | L13: 5498 | Q13: =IFERROR(AVERAGE(E13:P13),"") -> 6318.25 | R13: SR-11-12CA | S13: 1930.8 | T13: =F13 -> 5304
A14: 12 | B14: SR-11-12CB | C14: 6609 | D14: 5202.85 | E14: 4068 | F14: 7064 | G14: 10129 | H14: 13778 | I14: 14594 | J14: 3887 | K14: 6393 | L14: 8718 | Q14: =IFERROR(AVERAGE(E14:P14),"") -> 8578.875 | R14: SR-11-12CB | S14: 1966.2 | T14: =F14 -> 7064
... A27: 25 | B27: Nursary | C27: 303.2475 | D27: 2515.2083 | E27: 780 | F27: 1440 | G27: 3957 | H27: 8560.3 | I27: 7497.7 | J27: 2035.8 | K27: 2497.9 | L27: 4852 | Q27: =IFERROR(AVERAGE(E27:P27),"") -> 3952.5875 | R27: Nursary | S27: 3364 | T27: =F27 -> 1440
B29: Total ('000 kWh) | C29: =IF(COUNT(C3:C27)=0,"",SUM(C3:C27)/1000) -> 157.69462 | D29: =IF(COUNT(D3:D27)=0,"",SUM(D3:D27)/1000) -> 146.81559 | E29: =IF(COUNT(E3:E27)=0,"",SUM(E3:E27)/1000) -> 105.7465 | F29: =IF(COUNT(F3:F27)=0,"",SUM(F3:F27)/1000) -> 128.2405 | G29: =IF(COUNT(G3:G27)=0,"",SUM(G3:G27)/1000) -> 171.6873 | H29: =IF(COUNT(H3:H27)=0,"",SUM(H3:H27)/1000) -> 224.988 | I29: =IF(COUNT(I3:I27)=0,"",SUM(I3:I27)/1000) -> 230.0305 | J29: =IF(COUNT(J3:J27)=0,"",SUM(J3:J27)/1000) -> 119.6658 | ... P29: =IF(COUNT(P3:P27)=0,"",SUM(P3:P27)/1000) | Q29: =IFERROR(AVERAGE(E29:P29),"") -> 162.69165

Sheet Solar Power
B1: SOLAR POWER · GENERATION & EXPORT TO TSSPDCL
B3: SOLAR POWER EXPORTED TO TSSPDCL
B4: Month | C4: KWh | D4: Savings Amount in INR | F4: Export tariff (₹/kWh) | G4: 11.8
B5: 46023 | C5: 89214 | D5: =IF(C5="","",C5*$G$4) -> 1052725.2
B6: 46054 | C6: 112176 | D6: =IF(C6="","",C6*$G$4) -> 1323676.8
B7: 46082 | C7: 144102 | D7: =IF(C7="","",C7*$G$4) -> 1700403.6
B8: 46113 | C8: 227564 | D8: =IF(C8="","",C8*$G$4) -> 2685255.2
B9: 46143 | C9: 131666 | D9: =IF(C9="","",C9*$G$4) -> 1553658.8
B10: 46174 | C10: 128018 | D10: =IF(C10="","",C10*$G$4) -> 1510612.4
B11: 46204 | C11: 100380 | D11: =IF(C11="","",C11*$G$4) -> 1184484
B12: 46235 | C12: 115911 | D12: =IF(C12="","",C12*$G$4) -> 1367749.8
B13: 46266 | D13: =IF(C13="","",C13*$G$4)
B14: 46296 | D14: =IF(C14="","",C14*$G$4)
B15: 46327 | D15: =IF(C15="","",C15*$G$4)
B16: 46357 | D16: =IF(C16="","",C16*$G$4)
B17: TOTAL | C17: =SUM(C5:C16) -> 1049031 | D17: =SUM(D5:D16) -> 12378566
B20: Month | C20: 46023 | D20: 46054 | E20: 46082 | F20: 46113 | G20: 46143 | H20: 46174 | I20: 46204 | J20: 46235 | K20: 46266 | L20: 46296 | M20: 46327 | N20: 46357
B21: Plant Name | C21: Generation (KWh) | D21: Generation (KWh) | E21: Generation (KWh) | F21: Generation (KWh) | G21: Generation (KWh) | H21: Generation (KWh) | I21: Generation (KWh) | J21: Generation (KWh) | K21: Generation (KWh) | L21: Generation (KWh) | M21: Generation (KWh) | N21: Generation (KWh)
B22: AB_BUILDING | C22: 12661 | D22: 21829 | E22: 23491 | F22: 22775 | G22: 24623 | H22: 21433 | I22: 12655 | J22: 19530
B23: ART_AND_MUSIC | C23: 4548 | D23: 4382.9 | E23: 5865 | F23: 5550 | G23: 6223 | H23: 5423 | I23: 4453 | J23: 4783
B24: ATHLETIC_CENTRE | C24: 3745 | D24: 4540.7 | E24: 4727.3 | F24: 4596.4 | G24: 4933.4 | H24: 4353 | I24: 3606 | J24: 3955
B25: COMMONS_BUILDING | C25: 7601 | D25: 17016 | E25: 20874 | F25: 20938 | G25: 22443 | H25: 18821 | I25: 16903 | J25: 17451
B26: FACILITY_BLOCK | C26: 4676 | D26: 4260 | E26: 6824 | F26: 7130 | G26: 7937 | H26: 6907 | I26: 5651 | J26: 6770
B27: Ground_Mount_And_Substation | C27: 42443 | D27: 46210 | E27: 67509 | F27: 52060 | G27: 55073.8 | H27: 50128 | I27: 39351 | J27: 44867
B28: JS_LIBRARY | C28: 6117.6 | D28: 5871 | E28: 4996.4 | F28: 4764.5 | G28: 5081.5 | H28: 4463 | I28: 3711 | J28: 4045
B29: SENIOR_SCHOOL_1 | C29: 3927 | D29: 4386.2 | E29: 4868.7 | F29: 4656.6 | G29: 5111.7 | H29: 3862 | I29: 3737 | J29: 3820
B30: SQUASH_COURT | C30: 3495.1 | D30: 3680 | E30: 4946.3 | F30: 4825.6 | G30: 5312.2 | H30: 4705 | I30: 3820 | J30: 4047
B31: SS_LABORATORY | C31: 6592 | D31: 7325 | E31: 8503 | F31: 8722 | G31: 9067 | H31: 7923 | I31: 6493 | J31: 6643
B32: Total | C32: =IF(COUNT(C22:C31)=0,"",SUM(C22:C31)) -> 95805.7 | D32: =IF(COUNT(D22:D31)=0,"",SUM(D22:D31)) -> 119500.8 | E32: =IF(COUNT(E22:E31)=0,"",SUM(E22:E31)) -> 152604.7 | F32: =IF(COUNT(F22:F31)=0,"",SUM(F22:F31)) -> 136018.1 | G32: =IF(COUNT(G22:G31)=0,"",SUM(G22:G31)) -> 145805.6 | H32: =IF(COUNT(H22:H31)=0,"",SUM(H22:H31)) -> 128018 | I32: =IF(COUNT(I22:I31)=0,"",SUM(I22:I31)) -> 100380 | J32: =IF(COUNT(J22:J31)=0,"",SUM(J22:J31)) -> 115911 | ... N32: =IF(COUNT(N22:N31)=0,"",SUM(N22:N31))
B38: Solar Power
B39: Avg 2025 | C39: 46023 | D39: 46054 | E39: 46082 | F39: 46113 | G39: 46143 | H39: 46174 | I39: 46204 | J39: 46235 | K39: 46266 | L39: 46296 | M39: 46327 | N39: 46357
B40: 85838.867 | C40: =C32 -> 95805.7 | D40: =D32 -> 119500.8 | E40: =E32 -> 152604.7 | F40: =F32 -> 136018.1 | G40: =G32 -> 145805.6 | H40: =H32 -> 128018 | I40: =I32 -> 100380 | J40: =J32 -> 115911 | ... N40: =N32

Sheet HVAC consumption
A1: HVAC ELECTRICITY CONSUMPTION (kWh)
B4: HVAC BY BUILDING
B5: Month | C5: JS | D5: SS | E5: SR1 | F5: SR2 | G5: SR3 | H5: SR4 | I5: SR9/10A | J5: SR9/10B | K5: SR11/12CA | L5: SR11/12CB | M5: Nursery | N5: Total (kWh)
B6: 2024 (Avg) | C6: 12301.067 | D6: 8812.0931 | E6: 2204.9231 | F6: 2221.0385 | G6: 2547.6923 | H6: 3862.6538 | I6: 5883.2538 | J6: 3588.1308 | K6: 4764.0692 | L6: 4377.9846 | M6: 20637.73 | N6: =IF(COUNT(C6:M6)=0,"",SUM(C6:M6)) -> 71200.636 | S6: 45689 | T6: 46054
B7: 2025 (Avg) | C7: 2851.9091 | D7: 2971.5455 | E7: 997.41667 | F7: 1380.1333 | G7: 822.91667 | H7: 777.76667 | I7: 2576.1167 | J7: 2139.2083 | K7: 1793.975 | L7: 1903.7583 | M7: 2724.3333 | N7: =IF(COUNT(C7:M7)=0,"",SUM(C7:M7)) -> 20939.08 | R7: JS | S7: 942 | T7: =C9 -> 1730
B8: 46023 | C8: 550 | D8: 830 | E8: 257 | F8: 358.3 | G8: 87 | H8: 95 | I8: 647 | J8: 376 | K8: 262.5 | L8: 733 | M8: 460 | N8: =IF(COUNT(C8:M8)=0,"",SUM(C8:M8)) -> 4655.8 | R8: SS | S8: 1952 | T8: =D9 -> 2740
B9: 46054 | C9: 1730 | D9: 2740 | E9: 694 | F9: 732 | G9: 273 | H9: 478 | I9: 1267 | J9: 1505 | K9: 917 | L9: 1556 | M9: 930 | N9: =IF(COUNT(C9:M9)=0,"",SUM(C9:M9)) -> 12822 | R9: SR1 | S9: 1081 | T9: =E9 -> 694
B10: 46082 | C10: 5630 | D10: 7080 | E10: 1918 | F10: 2624 | G10: 1078 | H10: 1879 | I10: 4920 | J10: 5267 | K10: 2639 | L10: 4099 | M10: 1016 | N10: =IF(COUNT(C10:M10)=0,"",SUM(C10:M10)) -> 38150 | R10: SR2 | S10: 1757 | T10: =F9 -> 732
B11: 46113 | C11: 9640 | D11: 11590 | E11: 2771 | F11: 4027 | G11: 1640 | H11: 3058 | I11: 7895 | J11: 6713 | K11: 4819 | L11: 6261 | M11: 3960 | N11: =IF(COUNT(C11:M11)=0,"",SUM(C11:M11)) -> 62374 | R11: SR3 | S11: 983 | T11: =G9 -> 273
B12: 46143 | C12: 4250 | D12: 2890 | E12: 1351.4 | F12: 4427 | G12: 287 | H12: 1307 | I12: 3153 | J12: 1399 | K12: 1495 | L12: 2327 | M12: 1090 | N12: =IF(COUNT(C12:M12)=0,"",SUM(C12:M12)) -> 23976.4 | R12: SR4 | S12: 582 | T12: =H9 -> 478
B13: 46174 | C13: 1280 | D13: 2160 | E13: 1300 | F13: 1552 | G13: 1506 | H13: 1300 | I13: 794 | J13: 243.4 | K13: 735.5 | L13: 1099.5 | M13: 0 | N13: =IF(COUNT(C13:M13)=0,"",SUM(C13:M13)) -> 11970.4 | R13: SR9/10A | S13: 2756 | T13: =I9 -> 1267
B14: 46204 | C14: 3850 | D14: 4590 | E14: 1536 | F14: 1701.9 | G14: 1321 | H14: 1090.2 | I14: 3572 | J14: 3524.1 | K14: 1453.3 | L14: 3374.8 | M14: 2820 | N14: =IF(COUNT(C14:M14)=0,"",SUM(C14:M14)) -> 28833.3 | R14: SR9/10B | S14: 1991 | T14: =J9 -> 1505
B15: 46235 | C15: 2457 | D15: 4596 | E15: 1137 | F15: 1271 | G15: 485 | H15: 420.28 | I15: 2376 | J15: 2647 | K15: 1331.6 | L15: 2387 | M15: 2850 | N15: =IF(COUNT(C15:M15)=0,"",SUM(C15:M15)) -> 21957.88 | R15: SR11/12CA | S15: 1930 | T15: =K9 -> 917
B16: 46266 | N16: =IF(COUNT(C16:M16)=0,"",SUM(C16:M16)) | R16: SR11/12CB | S16: 1966 | T16: =L9 -> 1556
B17: 46296 | N17: =IF(COUNT(C17:M17)=0,"",SUM(C17:M17)) | R17: Nursery | S17: 2450 | T17: =M9 -> 930
B18: 46327 | N18: =IF(COUNT(C18:M18)=0,"",SUM(C18:M18))
B19: 46357 | N19: =IF(COUNT(C19:M19)=0,"",SUM(C19:M19))
B20: Avg 2026 | C20: =IFERROR(AVERAGE(C8:C19),"") -> 3673.375 | D20: =IFERROR(AVERAGE(D8:D19),"") -> 4559.5 | E20: =IFERROR(AVERAGE(E8:E19),"") -> 1370.55 | F20: =IFERROR(AVERAGE(F8:F19),"") -> 2086.65 | G20: =IFERROR(AVERAGE(G8:G19),"") -> 834.625 | H20: =IFERROR(AVERAGE(H8:H19),"") -> 1203.435 | I20: =IFERROR(AVERAGE(I8:I19),"") -> 3078 | J20: =IFERROR(AVERAGE(J8:J19),"") -> 2709.3125 | ... N20: =IFERROR(AVERAGE(N8:N19),"") -> 25592.472

Sheet Technical manpower cost
B4: Sodexo-Technical- Manpower Services Invoice Amounts | H4: Sodexo-Commons - Manpower Services Invoice Amounts | O4: Sodexo-HK- Manpower Services Invoice Amounts
B5: S No | C5: Description | D5: Month | E5: Amount(TINR,000) | F5: Budget | H5: S No | I5: Description | J5: Month | K5: Amount | L5: Amount(TINR,000) | M5: Budget | O5: S No | P5: Description | Q5: Month | R5: Amount | S5: Amount(TINR,000) | T5: Budget | W5: Year | X5: Values in TINR
B6: 1 | C6: Technical Manpower Services | D6: 44501 | F6: =1505470/1000 -> 1505.47 | H6: 1 | I6: Commons | J6: 44501 | M6: =1505470/1000 -> 1505.47 | O6: 1 | P6: House Keeping | Q6: 44501 | T6: =1505470/1000 -> 1505.47 | W6: Avg.2018
B7: 2 | C7: Technical Arc -Flash suit rent & Technical staff PPE Kit | D7: 44501 | F7: =1505470/1000 -> 1505.47 | H7: 2 | I7: Commons | J7: 44501 | M7: =1505470/1000 -> 1505.47 | O7: 2 | P7: House Keeping | Q7: 44501 | T7: =1505470/1000 -> 1505.47 | W7: Avg.2019
B8: 2 | C8: Technical Manpower Services | D8: 44531 | F8: =1505470/1000 -> 1505.47 | H8: 2 | I8: Commons | J8: 44531 | M8: =1505470/1000 -> 1505.47 | O8: 2 | P8: House Keeping | Q8: 44531 | T8: =1505470/1000 -> 1505.47 | W8: Avg.2020
B9: 3 | C9: Technical Manpower Services | D9: 44562 | F9: =1505470/1000 -> 1505.47 | H9: 3 | I9: Commons | J9: 44562 | M9: =1505470/1000 -> 1505.47 | O9: 3 | P9: House Keeping | Q9: 44562 | T9: =1505470/1000 -> 1505.47 | W9: Avg.2021
B10: 4 | C10: Technical Manpower Services | D10: 44593 | F10: =1505470/1000 -> 1505.47 | H10: 4 | I10: Commons | J10: 44593 | M10: =1505470/1000 -> 1505.47 | O10: 4 | P10: House Keeping | Q10: 44593 | T10: =1505470/1000 -> 1505.47 | W10: Avg.2022
B11: 5 | C11: Technical Manpower Services | D11: 44621 | F11: =1505470/1000 -> 1505.47 | H11: 5 | I11: Commons | J11: 44621 | M11: =1505470/1000 -> 1505.47 | O11: 5 | P11: House Keeping | Q11: 44621 | T11: =1505470/1000 -> 1505.47
B12: 6 | C12: Technical Manpower Services | D12: 44652 | F12: =1505470/1000 -> 1505.47 | H12: 6 | I12: Commons | J12: 44652 | M12: =1505470/1000 -> 1505.47 | O12: 6 | P12: House Keeping | Q12: 44652 | T12: =1505470/1000 -> 1505.47
B13: 7 | C13: Technical Manpower Services | D13: 44682 | F13: =1505470/1000 -> 1505.47 | H13: 7 | I13: Commons | J13: 44682 | M13: =1505470/1000 -> 1505.47 | O13: 7 | P13: House Keeping | Q13: 44682 | T13: =1505470/1000 -> 1505.47
B14: 8 | C14: Technical Manpower Services | D14: 44713 | F14: =1505470/1000 -> 1505.47 | H14: 8 | I14: Commons | J14: 44713 | M14: =1505470/1000 -> 1505.47 | O14: 8 | P14: House Keeping | Q14: 44713 | T14: =1505470/1000 -> 1505.47
B15: 9 | C15: Technical Manpower Services | D15: 44743 | F15: =1505470/1000 -> 1505.47 | H15: 9 | I15: Commons | J15: 44743 | M15: =1505470/1000 -> 1505.47 | O15: 9 | P15: House Keeping | Q15: 44743 | T15: =1505470/1000 -> 1505.47
B16: 10 | C16: Technical Manpower Services | D16: 44774 | E16: 569.093 | F16: =1505470/1000 -> 1505.47 | H16: 10 | I16: Commons | J16: 44774 | M16: =1505470/1000 -> 1505.47 | O16: 10 | P16: House Keeping | Q16: 44774 | T16: =1505470/1000 -> 1505.47
B17: 11 | C17: Technical Manpower Services | D17: 44805 | E17: 551.683 | F17: =1505470/1000 -> 1505.47 | H17: 11 | I17: Commons | J17: 44805 | M17: =1505470/1000 -> 1505.47 | O17: 11 | P17: House Keeping | Q17: 44805 | T17: =1505470/1000 -> 1505.47
B18: 12 | C18: Technical Manpower Services | D18: 44835 | E18: 672.941 | F18: =1505470/1000 -> 1505.47 | G18: FM included | H18: 12 | I18: Commons | J18: 44835 | M18: =1505470/1000 -> 1505.47 | O18: 12 | P18: House Keeping | Q18: 44835 | T18: =1505470/1000 -> 1505.47
B19: 13 | C19: Technical Manpower Services | D19: 44866 | E19: 631.901 | F19: =1505470/1000 -> 1505.47 | G19: FM yet to join | H19: 13 | I19: Commons | J19: 44866 | M19: =1505470/1000 -> 1505.47 | O19: 13 | P19: House Keeping | Q19: 44866 | T19: =1505470/1000 -> 1505.47
B20: 14 | C20: Technical Manpower Services | D20: 44896 | E20: 705 | F20: =1505470/1000 -> 1505.47 | G20: FM Joined | H20: 14 | I20: Commons | J20: 44896 | M20: =1505470/1000 -> 1505.47 | O20: 14 | P20: House Keeping | Q20: 44896 | T20: =1505470/1000 -> 1505.47
D21: Average | E21: =AVERAGE(E9:E20) -> 626.1236 | J21: Average | L21: =IFERROR(AVERAGE(L6:L20),"") | Q21: Average | S21: =IFERROR(AVERAGE(S6:S20),"")
B46: TECHNICAL MANPOWER COST · Sodexo & Trident invoices (₹'000)
B47: Sodexo-Technical- Manpower Services Invoice Amounts | U47: Particular | V47: 45689 | W47: 46054
B48: S No | C48: Description | D48: Month | E48: Amount(TINR,000) | F48: Budget (,000) | G48: Budget Utilisation % | U48: Amount | V48: 797.927 | W48: =E53 -> 747.92
B49: 1 | C49: Technical Manpower Services | D49: Avg.23 | E49: 691.52 | F49: 850 | G49: =IF(OR(E49="",F49="",F49=0),"",E49/F49) -> 0.81355294 | U49: Budget | V49: 1084.72 | W49: =F53 -> 1079.5317
B50: 2 | C50: Technical Manpower Services | D50: Avg.24 | E50: 784.24 | F50: 1022.46 | G50: =IF(OR(E50="",F50="",F50=0),"",E50/F50) -> 0.76701289
B51: 3 | C51: Technical Manpower Services | D51: Avg.25 | E51: 750.08925 | F51: 1079.5317 | G51: =IF(OR(E51="",F51="",F51=0),"",E51/F51) -> 0.69482839
B52: 4 | C52: Technical Manpower Services | D52: 46023 | E52: 728.279 | F52: 1079.5317 | G52: =IF(OR(E52="",F52="",F52=0),"",E52/F52) -> 0.67462495
B53: 5 | C53: Technical Manpower Services | D53: 46054 | E53: 747.92 | F53: 1079.5317 | G53: =IF(OR(E53="",F53="",F53=0),"",E53/F53) -> 0.69281895
B54: 6 | C54: Technical Manpower Services | D54: 46082 | G54: =IF(OR(E54="",F54="",F54=0),"",E54/F54)
B55: 7 | C55: Technical Manpower Services | D55: 46113 | G55: =IF(OR(E55="",F55="",F55=0),"",E55/F55)
B56: 8 | C56: Technical Manpower Services | D56: 46143 | G56: =IF(OR(E56="",F56="",F56=0),"",E56/F56)
B57: 9 | C57: Technical Manpower Services | D57: 46174 | G57: =IF(OR(E57="",F57="",F57=0),"",E57/F57)
B58: 10 | C58: Technical Manpower Services | D58: 46204 | G58: =IF(OR(E58="",F58="",F58=0),"",E58/F58)
B59: 11 | C59: Technical Manpower Services | D59: 46235 | G59: =IF(OR(E59="",F59="",F59=0),"",E59/F59)
B60: 12 | C60: Technical Manpower Services | D60: 46266 | G60: =IF(OR(E60="",F60="",F60=0),"",E60/F60)
B61: 13 | C61: Technical Manpower Services | D61: 46296 | G61: =IF(OR(E61="",F61="",F61=0),"",E61/F61)
B62: 14 | C62: Technical Manpower Services | D62: 46327 | G62: =IF(OR(E62="",F62="",F62=0),"",E62/F62)
B63: 15 | C63: Technical Manpower Services | D63: 46357 | G63: =IF(OR(E63="",F63="",F63=0),"",E63/F63)
C64: Technical Manpower Services | D64: Avg-26 | E64: =IFERROR(AVERAGE(E52:E63),"") -> 738.0995 | F64: =IFERROR(AVERAGE(F52:F63),"") -> 1079.5317 | G64: =IFERROR(E64/F64,"") -> 0.68372195
C65: Total YTD | E65: =SUM(E52:E63) -> 1476.199 | F65: =SUMPRODUCT((E52:E63<>"")*F52:F63) -> 2159.0633 | G65: =IFERROR(E65/F65,"") -> 0.68372195
D66: Average
B91: Trident Manpower Services Invoice Amounts
B93: S No | C93: Description | D93: Month | E93: Amount(TINR,000)
B94: 1 | C94: Trident Manpower Services | D94: Avg.22 | E94: =E49 -> 691.52
B95: 2 | C95: Trident Manpower Services | D95: 44927 | E95: 251.34
B96: 3 | C96: Trident Manpower Services | D96: 44958 | E96: 255.4
B97: 4 | C97: Trident Manpower Services | D97: 44986 | E97: 237.03
B98: 5 | C98: Trident Manpower Services | D98: 45017
B99: 6 | C99: Trident Manpower Services | D99: 45047
B100: 7 | C100: Trident Manpower Services | D100: 45078
B101: 8 | C101: Trident Manpower Services | D101: 45108
B102: 9 | C102: Trident Manpower Services | D102: 45139
B103: 10 | C103: Trident Manpower Services | D103: 45170
B104: 11 | C104: Trident Manpower Services | D104: 45200 | E104: 574.962
B105: 12 | C105: Trident Manpower Services | D105: 45231
B106: 13 | C106: Trident Manpower Services | D106: 45261
B107: 14 | C107: Total | E107: =SUM(E94:E106) -> 2010.252
D108: Average | E108: =IFERROR(AVERAGE(E95:E106),"") -> 329.683

Sheet Attendance
A1: TECHNICAL TEAM ATTENDANCE & DEPLOYMENT
B3: Technical Team Deployment – 2026 | N3: 45658 | O3: 46054
B4: Month | C4: Total Present | D4: Total Deployed | E4: % Deployment | F4: OT(in Hrs) | G4: OT Value(INR) | H4: Remarks | I4: Headcount | J4: Weekly Offs | M4: % Deployment | N4: 0.8966 | O4: =E9 -> 0.82015504
B5: Avg 2023 | C5: 529 | D5: =(31-7)*24 -> 576 | E5: =C5/D5 -> 0.91840278 | F5: 120 | G5: 23760.23
B6: Avg 2024 | C6: 629 | D6: =(31-4)*27 -> 729 | E6: =C6/D6 -> 0.86282579 | F6: 220 | G6: 48902 | H6: OT for 15th & 26th Jan
B7: Avg 2025 | C7: 583.58333 | D7: 702.16667 | E7: =IFERROR(C7/D7,"") -> 0.83111797 | F7: 129.45455 | G7: 25749.545 | H7: OT for 14,26 Jan-25
B8: 46023 | C8: 551 | D8: 633 | E8: =IF(OR(C8="",D8=""),"",IFERROR(C8/D8,"")) -> 0.87045814 | F8: 120 | G8: 48043 | H8: OT for 27 Feb-25 | I8: 27 | J8: 4
B9: 46054 | C9: 529 | D9: 645 | E9: =IF(OR(C9="",D9=""),"",IFERROR(C9/D9,"")) -> 0.82015504 | F9: 200 | G9: 48043 | H9: OT For 31 Mar-25 | I9: 27 | J9: 4
B10: 46082 | C10: 545 | D10: 653 | E10: =IF(OR(C10="",D10=""),"",IFERROR(C10/D10,"")) -> 0.83460949 | F10: 120 | I10: 27 | J10: 4
B11: 46113 | C11: 530 | D11: =IF(OR(I11="",J11=""),"",(DAY(EOMONTH(B11,0))-J11)*I11) -> 676 | E11: =IF(OR(C11="",D11=""),"",IFERROR(C11/D11,"")) -> 0.78402367 | H11: OT For 01,24-May-25 | I11: 26 | J11: 4
B12: 46143 | C12: 550 | D12: 655 | E12: =IF(OR(C12="",D12=""),"",IFERROR(C12/D12,"")) -> 0.83969466 | H12: OT 02-Jun-2025 | I12: 26 | J12: 4
B13: 46174 | C13: 580 | D13: 663 | E13: =IF(OR(C13="",D13=""),"",IFERROR(C13/D13,"")) -> 0.87481146 | I13: 27 | J13: 4
B14: 46204 | C14: 595 | D14: 634 | E14: =IF(OR(C14="",D14=""),"",IFERROR(C14/D14,"")) -> 0.9384858 | H14: OT 15 AUG-2025 | I14: 27 | J14: 4
B15: 46235 | C15: 543 | D15: 640 | E15: =IF(OR(C15="",D15=""),"",IFERROR(C15/D15,"")) -> 0.8484375 | I15: 27 | J15: 4
B16: 46266 | D16: =IF(OR(I16="",J16=""),"",(DAY(EOMONTH(B16,0))-J16)*I16) -> 702 | E16: =IF(OR(C16="",D16=""),"",IFERROR(C16/D16,"")) | H16: OT 02-OCT-2025 | I16: 27 | J16: 4
B17: 46296 | D17: =IF(OR(I17="",J17=""),"",(DAY(EOMONTH(B17,0))-J17)*I17) -> 702 | E17: =IF(OR(C17="",D17=""),"",IFERROR(C17/D17,"")) | I17: 26 | J17: 4
B18: 46327 | D18: =IF(OR(I18="",J18=""),"",(DAY(EOMONTH(B18,0))-J18)*I18) | E18: =IF(OR(C18="",D18=""),"",IFERROR(C18/D18,""))
B19: 46357 | D19: =IF(OR(I19="",J19=""),"",(DAY(EOMONTH(B19,0))-J19)*I19) -> 729 | E19: =IF(OR(C19="",D19=""),"",IFERROR(C19/D19,"")) | I19: 27 | J19: 4
B20: Avg 2026 | C20: =IFERROR(AVERAGE(C8:C19),"") -> 552.875 | D20: =IFERROR(AVERAGE(D8:D19),"") -> 666.54545 | E20: =IFERROR(AVERAGE(E8:E19),"") -> 0.85133447 | F20: =IFERROR(AVERAGE(F8:F19),"") -> 146.66667 | G20: =IFERROR(AVERAGE(G8:G19),"") -> 48043

Sheet DG Units Generated
A1: DG GENERATION & POWER FAILURE MONITORING
B3: Month | C3: Units Generated | F3: Diesel Consumed (in ltrs)Avg./ Month | G3: No. of power failures/Month (Avg) | H3: Total Failure Time ( in Hrs)
B4: Month | C4: 500KVA | D4: 750KVA | E4: Total Units Generated/Month | F4: Diesel Consumed (L) | G4: Power Failures / Month | H4: Failure Time (Hrs)
B5: Avg 2023 | C5: 469 | D5: 515 | E5: =C5+D5 -> 984 | F5: 322 | G5: =50/12 -> 4.1666667 | H5: =66/12 -> 5.5
B6: Avg 2024 | C6: 678.818 | D6: 309.818 | E6: =C6+D6 -> 988.636 | F6: 333 | G6: 42 | H6: 37
B7: Avg 2025 | C7: 352.27273 | D7: 142 | E7: =C7+D7 -> 494.27273 | F7: 178 | G7: 21 | H7: 27.25
B8: 46023 | C8: 4325 | D8: 0 | E8: =IF(COUNT(C8:D8)=0,"",SUM(C8:D8)) -> 4325 | F8: 1523 | G8: 10 | H8: 1.0729167
B9: 46054 | C9: 770 | D9: 0 | E9: =IF(COUNT(C9:D9)=0,"",SUM(C9:D9)) -> 770 | F9: 266 | G9: 7 | H9: 0.22222222
B10: 46082 | C10: 44 | D10: 0 | E10: 17 | F10: 8735 | G10: 11 | H10: 8.3
B11: 46113 | C11: 86 | D11: 45 | E11: 22 | F11: 17490 | G11: 4 | H11: 0.55
B12: 46143 | C12: 88 | D12: 0 | E12: 44 | F12: 17820 | G12: 2 | H12: 6.25
B13: 46174 | C13: 60 | D13: 0 | E13: 26 | F13: 12010 | G13: 5 | H13: 1.45
B14: 46204 | C14: 78 | D14: 0 | E14: 56 | F14: 16390 | G14: 1 | H14: 0.15
B15: 46235 | C15: 50 | D15: 100 | E15: 11 | F15: 11435 | G15: 1 | H15: 0.15
B16: 46266 | E16: =IF(COUNT(C16:D16)=0,"",SUM(C16:D16))
B17: 46296 | E17: =IF(COUNT(C17:D17)=0,"",SUM(C17:D17))
B18: 46327 | E18: =IF(COUNT(C18:D18)=0,"",SUM(C18:D18))
B19: 46357 | E19: =IF(COUNT(C19:D19)=0,"",SUM(C19:D19))
B20: Avg 2026 | C20: =IFERROR(AVERAGE(C8:C19),"") -> 687.625 | D20: =IFERROR(AVERAGE(D8:D19),"") -> 18.125 | E20: =IFERROR(AVERAGE(E8:E19),"") -> 658.875 | F20: =IFERROR(AVERAGE(F8:F19),"") -> 10708.625 | G20: =IFERROR(AVERAGE(G8:G19),"") -> 5.125 | H20: =IFERROR(AVERAGE(H8:H19),"") -> 2.2681424
B21: TOTAL 2026 YTD | C21: =SUM(C8:C19) -> 5501 | D21: =SUM(D8:D19) -> 145 | E21: =SUM(E8:E19) -> 5271 | F21: =SUM(F8:F19) -> 85669 | G21: =SUM(G8:G19) -> 41 | H21: =SUM(H8:H19) -> 18.145139
C43: 45689 | D43: 46054
B44: 500KVA | C44: 34 | D44: =C9 -> 770
B45: 750KVA | C45: 0 | D45: =D9 -> 0
B46: Total units Generated/Month | C46: =C44+C45 -> 34 | D46: =D45+D44 -> 770
B47: Diesel Consumed (in ltrs)Avg./ Month | C47: 25 | D47: =F9 -> 266

Sheet WQ
A1: PARAMETERS Bore Well | B1: UNITS | C1: DESIRABLE LIMITS | D1: Bore 01 | E1: Bore 02 | F1: Bore 03 | G1: Bore 04 | H1: Bore 05 | I1: Bore 06 | J1: Bore 07 | K1: Bore 08 | L1: Bore 09 | M1: Bore 10
D2: 46235 | E2: 46235 | F2: 46235 | G2: 46235 | H2: 46235 | I2: 46235 | J2: 46235 | K2: 46235 | L2: 46235 | M2: 46235
A3: PHYSICAL
A4: Colour | B4: Hazen | C4: 5 | D4: Colorless | E4: Colorless | F4: Colorless | G4: Colorless | H4: Colorless | I4: Colorless | J4: Colorless | K4: Colorless | L4: Colorless | M4: Colorless
A5: Turbidity | B5: NTU | C5: 1 | K5: 912 | M5: 840
A6: pH | C6: 6.5 - 8.5 | K6: 360 | M6: 150
A7: Electrical Conductivity | B7: Us/cm | C7: NS | K7: 380 | M7: 180
A8: CHEMICAL PARAMETERS
A9: HmmTotal Dissolved Solids | B9: mg/l | C9: 500 | K9: 86.4 | M9: 36
A10: Total Hardness as Caco3 | B10: mg/l | C10: 200 | K10: 34.6 | M10: 14.4
A11: Alkalilnity to Phenolphthalein | B11: mg/l | C11: NS | K11: 62.3 | M11: 56.8
A12: Methyl Orange Alkalinity | B12: mg/l | C12: 200 | K12: 20.3 | M12: 19.2
A13: Calcium as Ca, | B13: mg/l | C13: 75 | K13: 190 | M13: 140
A14: Magnesium as Mg | B14: mg/l | C14: 30 | K14: 52.7 | M14: 42.3
A15: Soldium as Na, | B15: mg/l | C15: NS | K15: 29.8 | M15: 26.8
A16: Potassium as K, | B16: mg/l | C16: NS | K16: 0.6 | M16: o.5
A17: Chloride as Cl, | B17: mg/l | C17: 250 | K17: 0.07 | M17: 0.04
A18: Sulphates as S04, | B18: mg/l | C18: 200 | K18: 1 | M18: 1
A19: Nitrates as No3, | B19: mg/l | C19: 45 | K19: 2.44 | M19: 3.11
A20: Fluoride as F | B20: mg/l | C20: 1 | K20: 1.38 | M20: 1.35
A21: Iron | B21: mg/l | C21: 0.3 | K21: 0.02 | M21: 0.02
A22: Silica | B22: mg/l | C22: NS | K22: 21.55 | M22: 18.14
A23: MICROBIOLOGICAL PARAMETERS
A24: Total Bacterial Count | B24: Cfu/ml | C24: NS | D24: 75 x 10 1 | E24: 68 x 10 1 | F24: 81 x 10 1 | G24: 75 x 10 1 | H24: 37 x 10 2 | I24: 47 x 10 1 | J24: 71 x 10 1 | K24: 43 x 10 1 | L24: 55 x 10 1 | M24: 49 x 10 1
A25: Coli form | B25: MPN/100ml | C25: Nil | D25: 3 | E25: 2 | F25: 2 | G25: 2 | H25: 6 | I25: 2 | J25: 2 | K25: Nil | L25: 2 | M25: 2
A26: E coli | C26: Absent/100ml | D26: Absent | E26: Absent | F26: 2 | G26: Absent | H26: Absent | I26: Absent | J26: Absent | K26: Absent | L26: Absent | M26: Absent
A28: SWIMMING POOL | C28: 46023 | D28: 46054 | E28: 46082 | F28: 46113 | G28: 46143 | H28: 46174 | I28: 46204 | J28: 46235 | K28: 46266 | L28: 46296 | M28: 46327
A29: pH | B29: NS | C29: 7.76 | E29: 7.8 | G29: 7.49 | H29: 7.78 | I29: 8.6 | J29: 8
A30: Total Alkalinity as (Cac03) | B30: mg/l | C30: 124.32 | E30: 247.52 | G30: 155.4 | H30: 152.89 | I30: 276 | J30: 260
A31: Aluminium as AI | B31: mg/l | C31: <0.01 | E31: < 0.01 | G31: < 0.01 | H31: < 0.01 | I31: < 0.01
A32: Total Residue Chlorine | B32: mg/l | C32: 0.3 | E32: 0.2 | G32: 0.4 | H32: 0.5 | I32: 0.5
A33: Oxygen Observed in 4 hours at 27 C | B33: mg/l | C33: 0.8 | E33: 0.7 | G33: 0.2 | H33: 0.5 | I33: 0.5
A34: Total Dissolved Solids | B34: mg/l | C34: 1689 | E34: 1779 | G34: 1839 | H34: 1176 | I34: 771 | J34: 980
A35: Chloride as CI | B35: mg/l | C35: 919.7 | E35: 885.45 | G35: 958.83 | H35: 543 | I35: 320 | J35: 260
A36: Iron as Fe | B36: HAZEN | C36: 0.02 | E36: 0.02 | G36: 0.02 | H36: 0.02 | I36: 0.02 | J36: 0.06
A37: Heavy metals (as Pb) | B37: NTU | C37: <0.001 | E37: < 0.001 | G37: < 0.001 | H37: < 0.001 | I37: < 0.001
A38: Color Odour Taste | B38: NS | C38: Colorless | E38: Colorless | G38: Colorless | H38: Colorless | I38: Colorless
A39: Turbidity | B39: NS | C39: 1.37 | E39: 1.41 | G39: 1.09 | H39: 1.39 | I39: 1 | J39: 0.5
A40: Odour | C40: Odourless | E40: Odourless | G40: Odourless | H40: Odourless | I40: Odourless | J40: Odourless
A41: Taste | C41: Un agreeable | E41: Un agreeable | G41: Un agreeable | H41: Un agreeable | I41: Un agreeable | J41: Un agreeable
A43: SEWARE WATER - DISCHARGE | E43: 45413 | F43: 46054 | G43: 46174
A45: pH | C45: 5.5 - 9.0 | E45: 7.29 | F45: 7.42 | G45: 7.5
A46: Electrical conductivity
A47: Total Solids | B47: mg/l | C47: 2200
A48: Total dissolved solids (TDS) | B48: mg/l | C48: 2100 | E48: 4071 | F48: 3079 | G48: 724
A49: Total suspended solids (TSS) | B49: mg/l | C49: 30-100 | E49: 18 | F49: 18 | G49: 20
A50: Chemical Oxygen demand (COD) | B50: mg/l | C50: 100-250 | E50: 110.4 | F50: 214 | G50: 50
A51: Biochemical Oxygen demand (BOD) | B51: mg/l | C51: 20 -30 | E51: 19 | F51: 26 | G51: 10
A52: Fecal Coliforms | B52: CFU/ml | C52: <1000/100
A53: Colour | B53: mg/l | C53: colourless
A54: Oil and Grease | B54: mg/l | C54: 10-20 | E54: < 1.00 | F54: 1044 | G54: <5
A55: Sulphide content | B55: mg/l | C55: 2 | E55: 786.4 | F55: 855 | G55: 42.6
A56: Chromium content | B56: mg/l | C56: 2
A57: Chloride content | B57: mg/l | C57: 1000 | E57: 2289.5 | F57: <1.00 | G57: 150
A60: Parameters above desirable limit | C60: count | D60: =SUMPRODUCT(ISNUMBER(D4:D22)*ISNUMBER($C$4:$C$22)*(D4:D22>$C$4:$C$22)) -> 0 | E60: =SUMPRODUCT(ISNUMBER(E4:E22)*ISNUMBER($C$4:$C$22)*(E4:E22>$C$4:$C$22)) -> 0 | F60: =SUMPRODUCT(ISNUMBER(F4:F22)*ISNUMBER($C$4:$C$22)*(F4:F22>$C$4:$C$22)) -> 0 | G60: =SUMPRODUCT(ISNUMBER(G4:G22)*ISNUMBER($C$4:$C$22)*(G4:G22>$C$4:$C$22)) -> 0 | H60: =SUMPRODUCT(ISNUMBER(H4:H22)*ISNUMBER($C$4:$C$22)*(H4:H22>$C$4:$C$22)) -> 0 | I60: =SUMPRODUCT(ISNUMBER(I4:I22)*ISNUMBER($C$4:$C$22)*(I4:I22>$C$4:$C$22)) -> 0 | J60: =SUMPRODUCT(ISNUMBER(J4:J22)*ISNUMBER($C$4:$C$22)*(J4:J22>$C$4:$C$22)) -> 0 | K60: =SUMPRODUCT(ISNUMBER(K4:K22)*ISNUMBER($C$4:$C$22)*(K4:K22>$C$4:$C$22)) -> 4 | ... M60: =SUMPRODUCT(ISNUMBER(M4:M22)*ISNUMBER($C$4:$C$22)*(M4:M22>$C$4:$C$22)) -> 4

Sheet Monthly KPI Report
A1: MONTHLY KPI REPORT · FACILITY MANAGEMENT 2026 (monthly roll-up of all source sheets · 16 KPIs)
A2: Month | B2: Complaints Received | C2: Closure % | D2: Pending Complaints | E2: LPCD | F2: Water Consumption (KL) | G2: Borewell (KL) | H2: HT Units (kWh) | I2: PF | J2: EPI (kWh/m²) | K2: Solar Export (kWh) | L2: Solar Savings (₹) | M2: DG Generation (kWh) | N2: DG Failures | O2: Deployment % | P2: HVAC (kWh) | Q2: Tech Manpower (₹000) | R2: Data Completeness % | S2: Data Status
A3: 46023 | B3: =IF('Complaints summary'!C8="","",'Complaints summary'!C8) -> 144 | C3: =IF(OR('Complaints summary'!C8="",'Complaints summary'!C8=0),"",'Complaints summary'!F8/'Complaints summary'!C8) -> 0.96527778 | D3: =IF('Complaints summary'!I8="","",'Complaints summary'!I8) -> 1 | E3: =IF(LPCD!F8="","",LPCD!F8) -> 969.74317 | F3: =IF(LPCD!C8="","",LPCD!C8/1000) -> 40704 | G3: =IF('Building wise water'!I38="","",'Building wise water'!I38) -> 15002 | H3: =IF('Power data'!C7="","",'Power data'!C7) -> 66600 | I3: =IF('Power data'!E7="","",'Power data'!E7) -> 0.84513476 | J3: =IF(EPI!D7="","",EPI!D7) -> 1.2649028 | K3: =IF('Solar Power'!C5="","",'Solar Power'!C5) -> 89214 | L3: =IF('Solar Power'!D5="","",'Solar Power'!D5) -> 1052725.2 | M3: =IF('DG Units Generated'!E8="","",'DG Units Generated'!E8) -> 4325 | N3: =IF('DG Units Generated'!G8="","",'DG Units Generated'!G8) -> 10 | O3: =IF(Attendance!E8="","",Attendance!E8) -> 0.87045814 | P3: =IF('HVAC consumption'!N8="","",'HVAC consumption'!N8) -> 4655.8 | Q3: =IF('Technical manpower cost'!E52="","",'Technical manpower cost'!E52) -> 728.279 | R3: =SUMPRODUCT(--(B3:Q3<>""))/COLUMNS(B3:Q3) -> 1 | S3: =IF(R3>=0.8,"READY",IF(R3>=0.4,"PARTIAL","MISSING")) -> READY
A4: 46054 | B4: =IF('Complaints summary'!C9="","",'Complaints summary'!C9) -> 122 | C4: =IF(OR('Complaints summary'!C9="",'Complaints summary'!C9=0),"",'Complaints summary'!F9/'Complaints summary'!C9) -> 0.97540984 | D4: =IF('Complaints summary'!I9="","",'Complaints summary'!I9) -> 3 | E4: =IF(LPCD!F9="","",LPCD!F9) -> 1742.0869 | F4: =IF(LPCD!C9="","",LPCD!C9/1000) -> 66046 | G4: =IF('Building wise water'!J38="","",'Building wise water'!J38) -> 19302.67 | H4: =IF('Power data'!C8="","",'Power data'!C8) -> 95736 | I4: =IF('Power data'!E8="","",'Power data'!E8) -> 0.95424915 | J4: =IF(EPI!D8="","",EPI!D8) -> 1.8182693 | K4: =IF('Solar Power'!C6="","",'Solar Power'!C6) -> 112176 | L4: =IF('Solar Power'!D6="","",'Solar Power'!D6) -> 1323676.8 | M4: =IF('DG Units Generated'!E9="","",'DG Units Generated'!E9) -> 770 | N4: =IF('DG Units Generated'!G9="","",'DG Units Generated'!G9) -> 7 | O4: =IF(Attendance!E9="","",Attendance!E9) -> 0.82015504 | P4: =IF('HVAC consumption'!N9="","",'HVAC consumption'!N9) -> 12822 | Q4: =IF('Technical manpower cost'!E53="","",'Technical manpower cost'!E53) -> 747.92 | R4: =SUMPRODUCT(--(B4:Q4<>""))/COLUMNS(B4:Q4) -> 1 | S4: =IF(R4>=0.8,"READY",IF(R4>=0.4,"PARTIAL","MISSING")) -> READY
A5: 46082 | B5: =IF('Complaints summary'!C10="","",'Complaints summary'!C10) | C5: =IF(OR('Complaints summary'!C10="",'Complaints summary'!C10=0),"",'Complaints summary'!F10/'Complaints summary'!C10) | D5: =IF('Complaints summary'!I10="","",'Complaints summary'!I10) | E5: =IF(LPCD!F10="","",LPCD!F10) -> 474.55568 | F5: =IF(LPCD!C10="","",LPCD!C10/1000) -> 19919 | G5: =IF('Building wise water'!K38="","",'Building wise water'!K38) -> 17647.45 | H5: =IF('Power data'!C9="","",'Power data'!C9) -> 125154 | I5: =IF('Power data'!E9="","",'Power data'!E9) -> 0.96435506 | J5: =IF(EPI!D9="","",EPI!D9) -> 2.3769917 | K5: =IF('Solar Power'!C7="","",'Solar Power'!C7) -> 144102 | L5: =IF('Solar Power'!D7="","",'Solar Power'!D7) -> 1700403.6 | M5: =IF('DG Units Generated'!E10="","",'DG Units Generated'!E10) -> 17 | N5: =IF('DG Units Generated'!G10="","",'DG Units Generated'!G10) -> 11 | O5: =IF(Attendance!E10="","",Attendance!E10) -> 0.83460949 | P5: =IF('HVAC consumption'!N10="","",'HVAC consumption'!N10) -> 38150 | Q5: =IF('Technical manpower cost'!E54="","",'Technical manpower cost'!E54) | R5: =SUMPRODUCT(--(B5:Q5<>""))/COLUMNS(B5:Q5) -> 0.75 | S5: =IF(R5>=0.8,"READY",IF(R5>=0.4,"PARTIAL","MISSING")) -> PARTIAL
A6: 46113 | B6: =IF('Complaints summary'!C11="","",'Complaints summary'!C11) | C6: =IF(OR('Complaints summary'!C11="",'Complaints summary'!C11=0),"",'Complaints summary'!F11/'Complaints summary'!C11) | D6: =IF('Complaints summary'!I11="","",'Complaints summary'!I11) | E6: =IF(LPCD!F11="","",LPCD!F11) -> 537.37075 | F6: =IF(LPCD!C11="","",LPCD!C11/1000) -> 21828 | G6: =IF('Building wise water'!L38="","",'Building wise water'!L38) -> 18490.49 | H6: =IF('Power data'!C10="","",'Power data'!C10) -> 198066 | I6: =IF('Power data'!E10="","",'Power data'!E10) -> 0.96883163 | J6: =IF(EPI!D10="","",EPI!D10) -> 3.7617754 | K6: =IF('Solar Power'!C8="","",'Solar Power'!C8) -> 227564 | L6: =IF('Solar Power'!D8="","",'Solar Power'!D8) -> 2685255.2 | M6: =IF('DG Units Generated'!E11="","",'DG Units Generated'!E11) -> 22 | N6: =IF('DG Units Generated'!G11="","",'DG Units Generated'!G11) -> 4 | O6: =IF(Attendance!E11="","",Attendance!E11) -> 0.78402367 | P6: =IF('HVAC consumption'!N11="","",'HVAC consumption'!N11) -> 62374 | Q6: =IF('Technical manpower cost'!E55="","",'Technical manpower cost'!E55) | R6: =SUMPRODUCT(--(B6:Q6<>""))/COLUMNS(B6:Q6) -> 0.75 | S6: =IF(R6>=0.8,"READY",IF(R6>=0.4,"PARTIAL","MISSING")) -> PARTIAL
A7: 46143 | B7: =IF('Complaints summary'!C12="","",'Complaints summary'!C12) | C7: =IF(OR('Complaints summary'!C12="",'Complaints summary'!C12=0),"",'Complaints summary'!F12/'Complaints summary'!C12) | D7: =IF('Complaints summary'!I12="","",'Complaints summary'!I12) | E7: =IF(LPCD!F12="","",LPCD!F12) -> 633.89241 | F7: =IF(LPCD!C12="","",LPCD!C12/1000) -> 26607 | G7: =IF('Building wise water'!M38="","",'Building wise water'!M38) -> 21759.4 | H7: =IF('Power data'!C11="","",'Power data'!C11) -> 222144 | I7: =IF('Power data'!E11="","",'Power data'!E11) -> 0.97928955 | J7: =IF(EPI!D11="","",EPI!D11) -> 4.2190776 | K7: =IF('Solar Power'!C9="","",'Solar Power'!C9) -> 131666 | L7: =IF('Solar Power'!D9="","",'Solar Power'!D9) -> 1553658.8 | M7: =IF('DG Units Generated'!E12="","",'DG Units Generated'!E12) -> 44 | N7: =IF('DG Units Generated'!G12="","",'DG Units Generated'!G12) -> 2 | O7: =IF(Attendance!E12="","",Attendance!E12) -> 0.83969466 | P7: =IF('HVAC consumption'!N12="","",'HVAC consumption'!N12) -> 23976.4 | Q7: =IF('Technical manpower cost'!E56="","",'Technical manpower cost'!E56) | R7: =SUMPRODUCT(--(B7:Q7<>""))/COLUMNS(B7:Q7) -> 0.75 | S7: =IF(R7>=0.8,"READY",IF(R7>=0.4,"PARTIAL","MISSING")) -> PARTIAL
A8: 46174 | B8: =IF('Complaints summary'!C13="","",'Complaints summary'!C13) -> 155 | C8: =IF(OR('Complaints summary'!C13="",'Complaints summary'!C13=0),"",'Complaints summary'!F13/'Complaints summary'!C13) -> 1 | D8: =IF('Complaints summary'!I13="","",'Complaints summary'!I13) | E8: =IF(LPCD!F13="","",LPCD!F13) -> 319.74397 | F8: =IF(LPCD!C13="","",LPCD!C13/1000) -> 12988 | G8: =IF('Building wise water'!N38="","",'Building wise water'!N38) -> 11528.59 | H8: =IF('Power data'!C12="","",'Power data'!C12) -> 72912 | I8: =IF('Power data'!E12="","",'Power data'!E12) -> 0.96337403 | J8: =IF(EPI!D12="","",EPI!D12) -> 1.3847837 | K8: =IF('Solar Power'!C10="","",'Solar Power'!C10) -> 128018 | L8: =IF('Solar Power'!D10="","",'Solar Power'!D10) -> 1510612.4 | M8: =IF('DG Units Generated'!E13="","",'DG Units Generated'!E13) -> 26 | N8: =IF('DG Units Generated'!G13="","",'DG Units Generated'!G13) -> 5 | O8: =IF(Attendance!E13="","",Attendance!E13) -> 0.87481146 | P8: =IF('HVAC consumption'!N13="","",'HVAC consumption'!N13) -> 11970.4 | Q8: =IF('Technical manpower cost'!E57="","",'Technical manpower cost'!E57) | R8: =SUMPRODUCT(--(B8:Q8<>""))/COLUMNS(B8:Q8) -> 0.875 | S8: =IF(R8>=0.8,"READY",IF(R8>=0.4,"PARTIAL","MISSING")) -> READY
A9: 46204 | B9: =IF('Complaints summary'!C14="","",'Complaints summary'!C14) -> 168 | C9: =IF(OR('Complaints summary'!C14="",'Complaints summary'!C14=0),"",'Complaints summary'!F14/'Complaints summary'!C14) -> 0.75595238 | D9: =IF('Complaints summary'!I14="","",'Complaints summary'!I14) | E9: =IF(LPCD!F14="","",LPCD!F14) -> 229.49921 | F9: =IF(LPCD!C14="","",LPCD!C14/1000) -> 9633 | G9: =IF('Building wise water'!O38="","",'Building wise water'!O38) -> 15618.59 | H9: =IF('Power data'!C13="","",'Power data'!C13) -> 122658 | I9: =IF('Power data'!E13="","",'Power data'!E13) -> 0.97102551 | J9: =IF(EPI!D13="","",EPI!D13) -> 2.3295863 | K9: =IF('Solar Power'!C11="","",'Solar Power'!C11) -> 100380 | L9: =IF('Solar Power'!D11="","",'Solar Power'!D11) -> 1184484 | M9: =IF('DG Units Generated'!E14="","",'DG Units Generated'!E14) -> 56 | N9: =IF('DG Units Generated'!G14="","",'DG Units Generated'!G14) -> 1 | O9: =IF(Attendance!E14="","",Attendance!E14) -> 0.9384858 | P9: =IF('HVAC consumption'!N14="","",'HVAC consumption'!N14) -> 28833.3 | Q9: =IF('Technical manpower cost'!E58="","",'Technical manpower cost'!E58) | R9: =SUMPRODUCT(--(B9:Q9<>""))/COLUMNS(B9:Q9) -> 0.875 | S9: =IF(R9>=0.8,"READY",IF(R9>=0.4,"PARTIAL","MISSING")) -> READY
A10: 46235 | B10: =IF('Complaints summary'!C15="","",'Complaints summary'!C15) -> 216 | C10: =IF(OR('Complaints summary'!C15="",'Complaints summary'!C15=0),"",'Complaints summary'!F15/'Complaints summary'!C15) -> 0.67592593 | D10: =IF('Complaints summary'!I15="","",'Complaints summary'!I15) | E10: =IF(LPCD!F15="","",LPCD!F15) -> 334.15924 | F10: =IF(LPCD!C15="","",LPCD!C15/1000) -> 14026 | G10: =IF('Building wise water'!P38="","",'Building wise water'!P38) -> 11995 | H10: =IF('Power data'!C14="","",'Power data'!C14) -> 146382 | I10: =IF('Power data'!E14="","",'Power data'!E14) -> 0.93618573 | J10: =IF(EPI!D14="","",EPI!D14) -> 2.7801652 | K10: =IF('Solar Power'!C12="","",'Solar Power'!C12) -> 115911 | L10: =IF('Solar Power'!D12="","",'Solar Power'!D12) -> 1367749.8 | M10: =IF('DG Units Generated'!E15="","",'DG Units Generated'!E15) -> 11 | N10: =IF('DG Units Generated'!G15="","",'DG Units Generated'!G15) -> 1 | O10: =IF(Attendance!E15="","",Attendance!E15) -> 0.8484375 | P10: =IF('HVAC consumption'!N15="","",'HVAC consumption'!N15) -> 21957.88 | Q10: =IF('Technical manpower cost'!E59="","",'Technical manpower cost'!E59) | R10: =SUMPRODUCT(--(B10:Q10<>""))/COLUMNS(B10:Q10) -> 0.875 | S10: =IF(R10>=0.8,"READY",IF(R10>=0.4,"PARTIAL","MISSING")) -> READY
A11: 46266 | B11: =IF('Complaints summary'!C16="","",'Complaints summary'!C16) | C11: =IF(OR('Complaints summary'!C16="",'Complaints summary'!C16=0),"",'Complaints summary'!F16/'Complaints summary'!C16) | D11: =IF('Complaints summary'!I16="","",'Complaints summary'!I16) | E11: =IF(LPCD!F16="","",LPCD!F16) | F11: =IF(LPCD!C16="","",LPCD!C16/1000) | G11: =IF('Building wise water'!Q38="","",'Building wise water'!Q38) | H11: =IF('Power data'!C15="","",'Power data'!C15) | I11: =IF('Power data'!E15="","",'Power data'!E15) | J11: =IF(EPI!D15="","",EPI!D15) | K11: =IF('Solar Power'!C13="","",'Solar Power'!C13) | L11: =IF('Solar Power'!D13="","",'Solar Power'!D13) | M11: =IF('DG Units Generated'!E16="","",'DG Units Generated'!E16) | N11: =IF('DG Units Generated'!G16="","",'DG Units Generated'!G16) | O11: =IF(Attendance!E16="","",Attendance!E16) | P11: =IF('HVAC consumption'!N16="","",'HVAC consumption'!N16) | Q11: =IF('Technical manpower cost'!E60="","",'Technical manpower cost'!E60) | R11: =SUMPRODUCT(--(B11:Q11<>""))/COLUMNS(B11:Q11) -> 0 | S11: =IF(R11>=0.8,"READY",IF(R11>=0.4,"PARTIAL","MISSING")) -> MISSING
A12: 46296 | B12: =IF('Complaints summary'!C17="","",'Complaints summary'!C17) | C12: =IF(OR('Complaints summary'!C17="",'Complaints summary'!C17=0),"",'Complaints summary'!F17/'Complaints summary'!C17) | D12: =IF('Complaints summary'!I17="","",'Complaints summary'!I17) | E12: =IF(LPCD!F17="","",LPCD!F17) | F12: =IF(LPCD!C17="","",LPCD!C17/1000) | G12: =IF('Building wise water'!R38="","",'Building wise water'!R38) | H12: =IF('Power data'!C16="","",'Power data'!C16) | I12: =IF('Power data'!E16="","",'Power data'!E16) | J12: =IF(EPI!D16="","",EPI!D16) | K12: =IF('Solar Power'!C14="","",'Solar Power'!C14) | L12: =IF('Solar Power'!D14="","",'Solar Power'!D14) | M12: =IF('DG Units Generated'!E17="","",'DG Units Generated'!E17) | N12: =IF('DG Units Generated'!G17="","",'DG Units Generated'!G17) | O12: =IF(Attendance!E17="","",Attendance!E17) | P12: =IF('HVAC consumption'!N17="","",'HVAC consumption'!N17) | Q12: =IF('Technical manpower cost'!E61="","",'Technical manpower cost'!E61) | R12: =SUMPRODUCT(--(B12:Q12<>""))/COLUMNS(B12:Q12) -> 0 | S12: =IF(R12>=0.8,"READY",IF(R12>=0.4,"PARTIAL","MISSING")) -> MISSING
A13: 46327 | B13: =IF('Complaints summary'!C18="","",'Complaints summary'!C18) | C13: =IF(OR('Complaints summary'!C18="",'Complaints summary'!C18=0),"",'Complaints summary'!F18/'Complaints summary'!C18) | D13: =IF('Complaints summary'!I18="","",'Complaints summary'!I18) | E13: =IF(LPCD!F18="","",LPCD!F18) | F13: =IF(LPCD!C18="","",LPCD!C18/1000) | G13: =IF('Building wise water'!S38="","",'Building wise water'!S38) | H13: =IF('Power data'!C17="","",'Power data'!C17) | I13: =IF('Power data'!E17="","",'Power data'!E17) | J13: =IF(EPI!D17="","",EPI!D17) | K13: =IF('Solar Power'!C15="","",'Solar Power'!C15) | L13: =IF('Solar Power'!D15="","",'Solar Power'!D15) | M13: =IF('DG Units Generated'!E18="","",'DG Units Generated'!E18) | N13: =IF('DG Units Generated'!G18="","",'DG Units Generated'!G18) | O13: =IF(Attendance!E18="","",Attendance!E18) | P13: =IF('HVAC consumption'!N18="","",'HVAC consumption'!N18) | Q13: =IF('Technical manpower cost'!E62="","",'Technical manpower cost'!E62) | R13: =SUMPRODUCT(--(B13:Q13<>""))/COLUMNS(B13:Q13) -> 0 | S13: =IF(R13>=0.8,"READY",IF(R13>=0.4,"PARTIAL","MISSING")) -> MISSING
A14: 46357 | B14: =IF('Complaints summary'!C19="","",'Complaints summary'!C19) | C14: =IF(OR('Complaints summary'!C19="",'Complaints summary'!C19=0),"",'Complaints summary'!F19/'Complaints summary'!C19) | D14: =IF('Complaints summary'!I19="","",'Complaints summary'!I19) | E14: =IF(LPCD!F19="","",LPCD!F19) | F14: =IF(LPCD!C19="","",LPCD!C19/1000) | G14: =IF('Building wise water'!T38="","",'Building wise water'!T38) | H14: =IF('Power data'!C18="","",'Power data'!C18) | I14: =IF('Power data'!E18="","",'Power data'!E18) | J14: =IF(EPI!D18="","",EPI!D18) | K14: =IF('Solar Power'!C16="","",'Solar Power'!C16) | L14: =IF('Solar Power'!D16="","",'Solar Power'!D16) | M14: =IF('DG Units Generated'!E19="","",'DG Units Generated'!E19) | N14: =IF('DG Units Generated'!G19="","",'DG Units Generated'!G19) | O14: =IF(Attendance!E19="","",Attendance!E19) | P14: =IF('HVAC consumption'!N19="","",'HVAC consumption'!N19) | Q14: =IF('Technical manpower cost'!E63="","",'Technical manpower cost'!E63) | R14: =SUMPRODUCT(--(B14:Q14<>""))/COLUMNS(B14:Q14) -> 0 | S14: =IF(R14>=0.8,"READY",IF(R14>=0.4,"PARTIAL","MISSING")) -> MISSING
A15: Avg 2026 YTD | B15: =IFERROR(AVERAGE(B3:B14),"") -> 161 | C15: =IFERROR(SUM('Complaints summary'!F8:F19)/SUM('Complaints summary'!C8:C19),"") -> 0.85217391 | D15: =IFERROR(AVERAGE(D3:D14),"") -> 2 | E15: =IFERROR(AVERAGE(E3:E14),"") -> 655.13142 | F15: =IFERROR(AVERAGE(F3:F14),"") -> 26468.875 | G15: =IFERROR(AVERAGE(G3:G14),"") -> 16418.024 | H15: =IFERROR(AVERAGE(H3:H14),"") -> 131206.5 | I15: =IFERROR(SUM('Power data'!C7:C18)/SUM('Power data'!D7:D18),"") -> 0.95548686 | J15: =IFERROR(AVERAGE(J3:J14),"") -> 2.491944 | K15: =IFERROR(AVERAGE(K3:K14),"") -> 131128.88 | L15: =IFERROR(AVERAGE(L3:L14),"") -> 1547320.7 | M15: =IFERROR(AVERAGE(M3:M14),"") -> 658.875 | N15: =IFERROR(AVERAGE(N3:N14),"") -> 5.125 | O15: =IFERROR(SUM(Attendance!C8:C19)/SUMIFS(Attendance!D8:D19,Attendance!C8:C19,">0"),"") -> 0.85074053 | P15: =IFERROR(AVERAGE(P3:P14),"") -> 25592.472 | Q15: =IFERROR(AVERAGE(Q3:Q14),"") -> 738.0995 | R15: =IFERROR(AVERAGEIF(S3:S14,"<>MISSING",R3:R14),"") -> 0.859375
A16: Total 2026 YTD | B16: =SUM(B3:B14) -> 805 | D16: =IFERROR(LOOKUP(2,1/(D3:D14<>""),D3:D14),"") -> 3 | F16: =SUM(F3:F14) -> 211751 | G16: =SUM(G3:G14) -> 131344.19 | H16: =SUM(H3:H14) -> 1049652 | K16: =SUM(K3:K14) -> 1049031 | L16: =SUM(L3:L14) -> 12378566 | M16: =SUM(M3:M14) -> 5271 | N16: =SUM(N3:N14) -> 41 | P16: =SUM(P3:P14) -> 204739.78 | Q16: =SUM(Q3:Q14) -> 1476.199
A17: SOURCE BENCHMARKS / CONTROL NOTES
A18: KPI | B18: Target / Benchmark | C18: Rule | D18: Source | E18: Control | F18: Monitoring use
A19: LPCD | B19: 135 | C19: ≤ benchmark | D19: LPCD | E19: Lower is better | F19: Monthly water-efficiency KPI
A20: EPI | B20: 8.0 | C20: ≤ benchmark | D20: EPI | E20: Lower is better | F20: Monthly energy-efficiency KPI
A21: Data Completeness | B21: 80% | C21: ≥ threshold | D21: KPI report | E21: Higher is better | F21: Minimum readiness for management review

Sheet Building_Master
A1: BUILDING MASTER — facility map used by FM_Dashboard & PerCapita_Pyramid
A2: Blue cells are inputs. Enter each facility's occupants (beds / regular users) and built-up area to unlock per-building per-capita (LPCD, kWh/person) and per-m² KPIs. Leave blank if unknown — dashboards then show '–'. Residences carry resident students from the 2026-27 roster (192); staff living in the residences are not counted. Where two buildings share one headcount, enter it on the first and name that building under 'Counted with' on the second — the per-person figures are then worked out for the pair.
A4: Facility | B4: Group | C4: Water meter(s) — 'Building wise water' | D4: Power meter — 'Power Building wise' | E4: Occupants (input) | F4: Built-up area m² (input) | G4: Mapping note | H4: Counted with (shared headcount) | I4: Residence block (2026-27 roster)
A5: SR-1 | B5: Residence | C5: ='Building wise water'!C11 -> SR-1 | D5: ='Power Building wise'!B7 -> SR-1 | E5: 29 | I5: Charminar (with SR-2)
A6: SR-2 | B6: Residence | C6: ='Building wise water'!C12 -> SR-2 | D6: ='Power Building wise'!B8 -> SR-2 | H6: SR-1 | I6: Charminar (with SR-1)
A7: SR-3 | B7: Residence | C7: ='Building wise water'!C13 -> SR-3 | D7: ='Power Building wise'!B9 -> SR-3 | E7: 33 | I7: Falaknuma (with SR-4)
A8: SR-4 | B8: Residence | C8: ='Building wise water'!C14 -> SR-4 | D8: ='Power Building wise'!B10 -> SR-4 | H8: SR-3 | I8: Falaknuma (with SR-3)
A9: SR-9/10 A | B9: Residence | C9: ='Building wise water'!C15 -> SR-9-10B1A | D9: ='Power Building wise'!B11 -> SR-9-10A | E9: 44 | G9: water meter SR-9-10B1A | I9: Chowmahalla-2
A10: SR-9/10 B | B10: Residence | C10: ='Building wise water'!C16 -> SR-9-10B1B | D10: ='Power Building wise'!B12 -> SR-9-10B | E10: 17 | G10: water meter SR-9-10B1B | I10: Chowmahalla-1
A11: SR-11/12 CA | B11: Residence | C11: ='Building wise water'!C17 -> SR-11-12CA | D11: ='Power Building wise'!B13 -> SR-11-12CA | E11: 41 | I11: Golconda-2
A12: SR-11/12 CB | B12: Residence | C12: ='Building wise water'!C18 -> SR-11-12CB | D12: ='Power Building wise'!B14 -> SR-11-12CB | E12: 28 | I12: Golconda-1
A13: Junior School | B13: Academic | C13: ='Building wise water'!C19&" + "&'Building wise water'!C20 -> Junior School-1&2 + Junior School-3 | D13: ='Power Building wise'!B15 -> Junior School-1,2&3 | G13: water JS-1&2 + JS-3; power JS-1,2&3
A14: Senior School 1 & 3 | B14: Academic | C14: ='Building wise water'!C21&" + "&'Building wise water'!C23 -> Senior School-1 + Senior School-3 | D14: ='Power Building wise'!B16 -> Senior School-1&3 | G14: power meter covers SS-1 & SS-3
A15: Senior School 2 | B15: Academic | C15: ='Building wise water'!C22 -> Senior School-2 | D15: ='Power Building wise'!B17 -> Senior School-2
A16: Academy Building | B16: Academic | C16: ='Building wise water'!C24 -> Academy Building | D16: ='Power Building wise'!B18 -> Academy Building
A17: Commons | B17: Amenity | C17: ='Building wise water'!C25 -> Commons | D17: ='Power Building wise'!B26 -> Commons
A18: Athletic Centre | B18: Amenity | C18: ='Building wise water'!C27 -> Athletic Centre | D18: ='Power Building wise'!B21 -> Athletic Centre
A19: Swimming Pool | B19: Amenity | C19: ='Building wise water'!C26 -> Swimming Pool | D19: — (not metered) | G19: no separate power meter
A20: PCM | B20: Support | C20: ='Building wise water'!C28 -> PCM | D20: ='Power Building wise'!B22 -> PCM
A21: Nursery | B21: Support | C21: ='Building wise water'!C29 -> Nursery | D21: ='Power Building wise'!B27 -> Nursary | G21: power meter 'Nursary'
A22: Laundry | B22: Support | C22: ='Building wise water'!C30 -> Laundry | D22: ='Power Building wise'!B5 -> Laundry
A24: Campus occupants (LPCD sheet) | E24: =LPCD!D8 -> 1354
A25: Campus built-up area m² (EPI sheet) | F25: =EPI!D19 -> 52652.267
A26: Sum of facility occupants entered | E26: =SUM(E5:E22) -> 192
A27: Resident students entered for SR residences (roster total 192) | E27: =SUM(E5:E12) -> 192

Sheet MIS_Calc
A1: MIS CALCULATION ENGINE — links every dashboard figure to the source MIS sheets. Do not type here.
E2: Month list | CU2: Facility list (drop-down source)
A3: FM_Dashboard month | B3: =FM_Dashboard!$D$5 -> Aug-26 | E3: 2026 YTD | CU3: All Facilities
A4: FM_Dashboard facility | B4: =FM_Dashboard!$J$5 -> All Facilities | E4: Jan-26 | CU4: =A194 -> SR-1
A5: PerCapita_Pyramid month | B5: =PerCapita_Pyramid!$D$5 -> Aug-26 | E5: Feb-26 | CU5: =A195 -> SR-2
A6: Latest month with HT power data | B6: =IFERROR(LOOKUP(2,1/($N$21:$N$32<>""),$A$21:$A$32),"–") -> Aug-26 | E6: Mar-26 | CU6: =A196 -> SR-3
A7: Campus built-up area m² | B7: =EPI!D19 -> 52652.267 | E7: Apr-26 | CU7: =A197 -> SR-4
A8: LPCD benchmark | B8: =LPCD!E8 -> 135 | E8: May-26 | CU8: =A198 -> SR-9/10 A
A9: EPI benchmark (kWh/m²/month) | B9: =EPI!C7 -> 8 | E9: Jun-26 | CU9: =A199 -> SR-9/10 B
A10: PF target | B10: 0.95 | E10: Jul-26 | CU10: =A200 -> SR-11/12 CA
A11: Deployment target | B11: 0.9 | E11: Aug-26 | CU11: =A201 -> SR-11/12 CB
A12: Closure target | B12: 0.95 | E12: Sep-26 | CU12: =A202 -> Junior School
A13: Days in FM selection | B13: =IF($B$3="2026 YTD",AVERAGE($B$21:INDEX($B$21:$B$32,MAX(1,COUNT($N$21:$N$32)))),INDEX($B$21:$B$32,MATCH($B$3,$A$21:$A$32,0))) -> 31 | E13: Oct-26 | CU13: =A203 -> Senior School 1 & 3
A14: Days in Pyramid selection | B14: =IF($B$5="2026 YTD",AVERAGE($B$21:INDEX($B$21:$B$32,MAX(1,COUNT($N$21:$N$32)))),INDEX($B$21:$B$32,MATCH($B$5,$A$21:$A$32,0))) -> 31 | E14: Nov-26 | CU14: =A204 -> Senior School 2
A15: Campus occupants | B15: =LPCD!D8 -> 1354 | E15: Dec-26 | CU15: =A205 -> Academy Building
CU16: =A206 -> Commons
CU17: =A207 -> Athletic Centre
A18: A. Monthly fact table (Jan–Dec 2026) + baselines (Avg 2023 / 2024 / 2025) — blank = not yet logged | CU18: =A208 -> Swimming Pool
CU19: =A209 -> PCM
A20: Month | B20: Days | C20: Complaints received (count) | D20: Complaints closed (count) | E20: Pending complaints (count) | F20: Emergency complaints (count) | G20: Water consumption (kL) | H20: Occupants (persons) | I20: LPCD (L/person/day) | J20: Borewell draw (kL) | K20: STP outlet (recycled) (kL) | L20: WTP treated output (kL) | M20: Drip irrigation (kL) | N20: HT grid energy (kWh) | O20: HT energy (kVAh) | P20: Power factor (ratio) | Q20: HT energy bill (₹) | R20: Energy unit rate (₹/kVAh) | S20: Max demand recorded (kVA) | T20: Sanctioned MD (kVA) | U20: EPI (kWh/m²/month) | V20: Solar generation (kWh) | W20: Solar exported to TSSPDCL (kWh) | X20: Solar savings (₹) | Y20: DG units generated (kWh) | Z20: Power failures (count) | AA20: Power failure time (hrs) | AB20: HVAC energy (kWh) | AJ20: Technical manpower cost (₹) | AK20: Technical manpower budget (₹) | AL20: Technical man-days present (man-days) | AM20: Technical man-days deployed (man-days) | AN20: Deployment % (%) | AO20: Overtime (hrs) | AP20: Technical headcount (persons) | AQ20: Data completeness (%) | AR20: Grid energy per person (kWh/person/month) | AS20: Energy bill per person (₹/person/month) | AT20: HVAC energy per person (kWh/person/month) | AV20: Max-demand utilisation (% of sanctioned) | AW20: Borewell draw per person (L/person/day) | AX20: STP recycled per person (L/person/day) | AY20: WTP treated water per person (L/person/day) | AZ20: Drip irrigation per person (L/person/day) | BA20: STP share of inlet water (%) | BB20: Solar generation per person (kWh/person/month) | BC20: Solar offset of grid energy (%) | BD20: Solar savings per person (₹/person/month) | BH20: Complaints per 100 persons (per 100 persons/month) | BI20: Closure rate (%) | BJ20: Emergency share of complaints (%) | BK20: Pending complaints per 1,000 persons (per 1,000 persons) | BL20: Technical manpower cost per person (₹/person/month) | BM20: Technical manpower budget use (%) | BN20: Overtime per 100 man-days present (hrs/100 man-days) | BO20: Persons served per technician (persons/technician) | BP20: Tracked OPEX: HT energy bill + technical manpower (₹) | BQ20: Tracked OPEX per person (₹/person/month) | BR20: DG energy per person (kWh/person/month) | BT20: chart:ht | BU20: chart:solar | BV20: chart:bore | BW20: chart:stp | BX20: chart:lpcd | BY20: chart:epi | BZ20: chart:pf | CA20: chart:bill | CB20: chart:wtp | CC20: chart:comp | CD20: chart:closed | CE20: chart:deploy | CI20: chart:pc_kwh | CJ20: chart:pc_opex | CK20: chart:hvac | CL20: chart:dg | CM20: chart:dgfail | CO20: chart:water | CP20: LPCD benchmark | CQ20: EPI benchmark | CR20: PF target | CS20: Deploy target | CU20: =A210 -> Nursery
A21: Jan-26 | B21: 31 | C21: =IF('Complaints summary'!C8="","",'Complaints summary'!C8) -> 144 | D21: =IF('Complaints summary'!F8="","",'Complaints summary'!F8) -> 139 | E21: =IF('Complaints summary'!I8="","",'Complaints summary'!I8) -> 1 | F21: =IF('Complaints summary'!D8="","",'Complaints summary'!D8) -> 8 | G21: =IF(LPCD!C8="","",LPCD!C8/1000) -> 40704 | H21: =IF(LPCD!D8="","",LPCD!D8) -> 1354 | I21: =IF(LPCD!F8="","",LPCD!F8) -> 969.74317 | J21: =IF('Building wise water'!I38="","",'Building wise water'!I38) -> 15002 | K21: =IF('Building wise water'!I39="","",'Building wise water'!I39) -> 3596 | L21: =IF('Building wise water'!I33="","",'Building wise water'!I33) -> 8770 | M21: =IF('Building wise water'!I34="","",'Building wise water'!I34) -> 5643 | N21: =IF('Power data'!C7="","",'Power data'!C7) -> 66600 | O21: =IF('Power data'!D7="","",'Power data'!D7) -> 78804 | P21: =IF('Power data'!E7="","",'Power data'!E7) -> 0.84513476 | Q21: =IF('Power data'!F7="","",'Power data'!F7) -> 929887.2 | R21: =IF('Power data'!G7="","",'Power data'!G7) -> 11.8 | S21: =IF('Power data'!H7="","",'Power data'!H7) -> 306 | T21: =IF('Power data'!I7="","",'Power data'!I7) -> 1276 | U21: =IF(EPI!D7="","",EPI!D7) -> 1.2649028 | V21: =IF('Solar Power'!C32="","",'Solar Power'!C32) -> 95805.7 | W21: =IF('Solar Power'!C5="","",'Solar Power'!C5) -> 89214 | X21: =IF('Solar Power'!D5="","",'Solar Power'!D5) -> 1052725.2 | Y21: =IF('DG Units Generated'!E8="","",'DG Units Generated'!E8) -> 4325 | Z21: =IF('DG Units Generated'!G8="","",'DG Units Generated'!G8) -> 10 | AA21: =IF('DG Units Generated'!H8="","",'DG Units Generated'!H8) -> 1.0729167 | AB21: =IF('HVAC consumption'!N8="","",'HVAC consumption'!N8) -> 4655.8 | AJ21: =IF('Technical manpower cost'!E52="","",'Technical manpower cost'!E52*1000) -> 728279 | AK21: =IF('Technical manpower cost'!F52="","",'Technical manpower cost'!F52*1000) -> 1079531.7 | AL21: =IF(Attendance!C8="","",Attendance!C8) -> 551 | AM21: =IF(Attendance!C8="","",Attendance!D8) -> 633 | AN21: =IF(Attendance!E8="","",Attendance!E8) -> 0.87045814 | AO21: =IF(Attendance!F8="","",Attendance!F8) -> 120 | AP21: =IF(Attendance!C8="","",Attendance!I8) -> 27 | AQ21: =IF('Monthly KPI Report'!S3="MISSING","",'Monthly KPI Report'!R3) -> 1 | AR21: =IFERROR(N21/H21,"") -> 49.187592 | AS21: =IFERROR(Q21/H21,"") -> 686.77046 | AT21: =IFERROR(IF(OR(AB21="",H21=""),"",AB21/H21),"") -> 3.4385524 | AV21: =IFERROR(S21/T21,"") -> 0.23981191 | AW21: =IFERROR(J21*1000/(H21*$B21),"") -> 357.41173 | AX21: =IFERROR(K21*1000/(H21*$B21),"") -> 85.672083 | AY21: =IFERROR(L21*1000/(H21*$B21),"") -> 208.93887 | AZ21: =IFERROR(M21*1000/(H21*$B21),"") -> 134.44037 | BA21: =IFERROR(K21/(J21+K21),"") -> 0.19335412 | BB21: =IFERROR(IF(OR(V21="",H21=""),"",V21/H21),"") -> 70.757533 | BC21: =IFERROR(IF(OR(V21="",N21=""),"",V21/N21),"") -> 1.438524 | BD21: =IFERROR(IF(OR(X21="",H21=""),"",X21/H21),"") -> 777.49276 | BH21: =IFERROR(C21*100/H21,"") -> 10.635155 | BI21: =IFERROR(D21/C21,"") -> 0.96527778 | BJ21: =IFERROR(F21/C21,"") -> 0.055555556 | BK21: =IFERROR(E21*1000/H21,"") -> 0.73855244 | BL21: =IFERROR(AJ21/H21,"") -> 537.87223 | BM21: =IFERROR(AJ21/AK21,"") -> 0.67462495 | BN21: =IFERROR(AO21*100/AL21,"") -> 21.778584 | BO21: =IFERROR(H21/AP21,"") -> 50.148148 | BP21: =IF(OR(Q21="",AJ21=""),"",Q21+AJ21) -> 1658166.2 | BQ21: =IFERROR(IF(OR(BP21="",H21=""),"",BP21/H21),"") -> 1224.6427 | BR21: =IFERROR(Y21/H21,"") -> 3.1942393 | BT21: =IF(N21="",0,N21) -> 66600 | BU21: =IF(V21="",0,V21) -> 95805.7 | BV21: =IF(J21="",0,J21) -> 15002 | BW21: =IF(K21="",0,K21) -> 3596 | BX21: =IF(I21="",0,I21) -> 969.74317 | BY21: =IF(U21="",0,U21) -> 1.2649028 | BZ21: =IF(P21="",0,P21) -> 0.84513476 | CA21: =IF(Q21="",0,Q21) -> 929887.2 | CB21: =IF(L21="",0,L21) -> 8770 | CC21: =IF(C21="",0,C21) -> 144 | CD21: =IF(D21="",0,D21) -> 139 | CE21: =IF(AN21="",0,AN21) -> 0.87045814 | CI21: =IF(AR21="",0,AR21) -> 49.187592 | CJ21: =IF(BQ21="",0,BQ21) -> 1224.6427 | CK21: =IF(AB21="",0,AB21) -> 4655.8 | CL21: =IF(Y21="",0,Y21) -> 4325 | CM21: =IF(Z21="",0,Z21) -> 10 | CO21: =IF(G21="",0,G21) -> 40704 | CP21: =MIS_Calc!$B$8 -> 135 | CQ21: =MIS_Calc!$B$9 -> 8 | CR21: =MIS_Calc!$B$10 -> 0.95 | CS21: =MIS_Calc!$B$11 -> 0.9 | CU21: =A211 -> Laundry
A22: Feb-26 | B22: 28 | C22: =IF('Complaints summary'!C9="","",'Complaints summary'!C9) -> 122 | D22: =IF('Complaints summary'!F9="","",'Complaints summary'!F9) -> 119 | E22: =IF('Complaints summary'!I9="","",'Complaints summary'!I9) -> 3 | F22: =IF('Complaints summary'!D9="","",'Complaints summary'!D9) -> 0 | G22: =IF(LPCD!C9="","",LPCD!C9/1000) -> 66046 | H22: =IF(LPCD!D9="","",LPCD!D9) -> 1354 | I22: =IF(LPCD!F9="","",LPCD!F9) -> 1742.0869 | J22: =IF('Building wise water'!J38="","",'Building wise water'!J38) -> 19302.67 | K22: =IF('Building wise water'!J39="","",'Building wise water'!J39) -> 5654 | L22: =IF('Building wise water'!J33="","",'Building wise water'!J33) -> 14597 | M22: =IF('Building wise water'!J34="","",'Building wise water'!J34) -> 6541 | N22: =IF('Power data'!C8="","",'Power data'!C8) -> 95736 | O22: =IF('Power data'!D8="","",'Power data'!D8) -> 100326 | P22: =IF('Power data'!E8="","",'Power data'!E8) -> 0.95424915 | Q22: =IF('Power data'!F8="","",'Power data'!F8) -> 1099602 | R22: =IF('Power data'!G8="","",'Power data'!G8) -> 10.960289 | S22: =IF('Power data'!H8="","",'Power data'!H8) -> 386 | T22: =IF('Power data'!I8="","",'Power data'!I8) -> 1276 | U22: =IF(EPI!D8="","",EPI!D8) -> 1.8182693 | V22: =IF('Solar Power'!D32="","",'Solar Power'!D32) -> 119500.8 | W22: =IF('Solar Power'!C6="","",'Solar Power'!C6) -> 112176 | X22: =IF('Solar Power'!D6="","",'Solar Power'!D6) -> 1323676.8 | Y22: =IF('DG Units Generated'!E9="","",'DG Units Generated'!E9) -> 770 | Z22: =IF('DG Units Generated'!G9="","",'DG Units Generated'!G9) -> 7 | AA22: =IF('DG Units Generated'!H9="","",'DG Units Generated'!H9) -> 0.22222222 | AB22: =IF('HVAC consumption'!N9="","",'HVAC consumption'!N9) -> 12822 | AJ22: =IF('Technical manpower cost'!E53="","",'Technical manpower cost'!E53*1000) -> 747920 | AK22: =IF('Technical manpower cost'!F53="","",'Technical manpower cost'!F53*1000) -> 1079531.7 | AL22: =IF(Attendance!C9="","",Attendance!C9) -> 529 | AM22: =IF(Attendance!C9="","",Attendance!D9) -> 645 | AN22: =IF(Attendance!E9="","",Attendance!E9) -> 0.82015504 | AO22: =IF(Attendance!F9="","",Attendance!F9) -> 200 | AP22: =IF(Attendance!C9="","",Attendance!I9) -> 27 | AQ22: =IF('Monthly KPI Report'!S4="MISSING","",'Monthly KPI Report'!R4) -> 1 | AR22: =IFERROR(N22/H22,"") -> 70.706056 | AS22: =IFERROR(Q22/H22,"") -> 812.11374 | AT22: =IFERROR(IF(OR(AB22="",H22=""),"",AB22/H22),"") -> 9.4697194 | AV22: =IFERROR(S22/T22,"") -> 0.30250784 | AW22: =IFERROR(J22*1000/(H22*$B22),"") -> 509.14407 | AX22: =IFERROR(K22*1000/(H22*$B22),"") -> 149.13484 | AY22: =IFERROR(L22*1000/(H22*$B22),"") -> 385.02321 | AZ22: =IFERROR(M22*1000/(H22*$B22),"") -> 172.53112 | BA22: =IFERROR(K22/(J22+K22),"") -> 0.22655266 | BB22: =IFERROR(IF(OR(V22="",H22=""),"",V22/H22),"") -> 88.257607 | BC22: =IFERROR(IF(OR(V22="",N22=""),"",V22/N22),"") -> 1.2482326 | BD22: =IFERROR(IF(OR(X22="",H22=""),"",X22/H22),"") -> 977.60473 | BH22: =IFERROR(C22*100/H22,"") -> 9.0103397 | BI22: =IFERROR(D22/C22,"") -> 0.97540984 | BJ22: =IFERROR(F22/C22,"") -> 0 | BK22: =IFERROR(E22*1000/H22,"") -> 2.2156573 | BL22: =IFERROR(AJ22/H22,"") -> 552.37814 | BM22: =IFERROR(AJ22/AK22,"") -> 0.69281895 | BN22: =IFERROR(AO22*100/AL22,"") -> 37.807183 | BO22: =IFERROR(H22/AP22,"") -> 50.148148 | BP22: =IF(OR(Q22="",AJ22=""),"",Q22+AJ22) -> 1847522 | BQ22: =IFERROR(IF(OR(BP22="",H22=""),"",BP22/H22),"") -> 1364.4919 | BR22: =IFERROR(Y22/H22,"") -> 0.56868538 | BT22: =IF(N22="",0,N22) -> 95736 | BU22: =IF(V22="",0,V22) -> 119500.8 | BV22: =IF(J22="",0,J22) -> 19302.67 | BW22: =IF(K22="",0,K22) -> 5654 | BX22: =IF(I22="",0,I22) -> 1742.0869 | BY22: =IF(U22="",0,U22) -> 1.8182693 | BZ22: =IF(P22="",0,P22) -> 0.95424915 | CA22: =IF(Q22="",0,Q22) -> 1099602 | CB22: =IF(L22="",0,L22) -> 14597 | CC22: =IF(C22="",0,C22) -> 122 | CD22: =IF(D22="",0,D22) -> 119 | CE22: =IF(AN22="",0,AN22) -> 0.82015504 | CI22: =IF(AR22="",0,AR22) -> 70.706056 | CJ22: =IF(BQ22="",0,BQ22) -> 1364.4919 | CK22: =IF(AB22="",0,AB22) -> 12822 | CL22: =IF(Y22="",0,Y22) -> 770 | CM22: =IF(Z22="",0,Z22) -> 7 | CO22: =IF(G22="",0,G22) -> 66046 | CP22: =MIS_Calc!$B$8 -> 135 | CQ22: =MIS_Calc!$B$9 -> 8 | CR22: =MIS_Calc!$B$10 -> 0.95 | CS22: =MIS_Calc!$B$11 -> 0.9
A23: Mar-26 | B23: 31 | C23: =IF('Complaints summary'!C10="","",'Complaints summary'!C10) | D23: =IF('Complaints summary'!F10="","",'Complaints summary'!F10) | E23: =IF('Complaints summary'!I10="","",'Complaints summary'!I10) | F23: =IF('Complaints summary'!D10="","",'Complaints summary'!D10) | G23: =IF(LPCD!C10="","",LPCD!C10/1000) -> 19919 | H23: =IF(LPCD!D10="","",LPCD!D10) -> 1354 | I23: =IF(LPCD!F10="","",LPCD!F10) -> 474.55568 | J23: =IF('Building wise water'!K38="","",'Building wise water'!K38) -> 17647.45 | K23: =IF('Building wise water'!K39="","",'Building wise water'!K39) -> 4885 | L23: =IF('Building wise water'!K33="","",'Building wise water'!K33) -> 12927 | M23: =IF('Building wise water'!K34="","",'Building wise water'!K34) -> 6091 | N23: =IF('Power data'!C9="","",'Power data'!C9) -> 125154 | O23: =IF('Power data'!D9="","",'Power data'!D9) -> 129780 | P23: =IF('Power data'!E9="","",'Power data'!E9) -> 0.96435506 | Q23: =IF('Power data'!F9="","",'Power data'!F9) -> 1406695 | R23: =IF('Power data'!G9="","",'Power data'!G9) -> 10.839074 | S23: =IF('Power data'!H9="","",'Power data'!H9) -> 440 | T23: =IF('Power data'!I9="","",'Power data'!I9) -> 1276 | U23: =IF(EPI!D9="","",EPI!D9) -> 2.3769917 | V23: =IF('Solar Power'!E32="","",'Solar Power'!E32) -> 152604.7 | W23: =IF('Solar Power'!C7="","",'Solar Power'!C7) -> 144102 | X23: =IF('Solar Power'!D7="","",'Solar Power'!D7) -> 1700403.6 | Y23: =IF('DG Units Generated'!E10="","",'DG Units Generated'!E10) -> 17 | Z23: =IF('DG Units Generated'!G10="","",'DG Units Generated'!G10) -> 11 | AA23: =IF('DG Units Generated'!H10="","",'DG Units Generated'!H10) -> 8.3 | AB23: =IF('HVAC consumption'!N10="","",'HVAC consumption'!N10) -> 38150 | AJ23: =IF('Technical manpower cost'!E54="","",'Technical manpower cost'!E54*1000) | AK23: =IF('Technical manpower cost'!F54="","",'Technical manpower cost'!F54*1000) | AL23: =IF(Attendance!C10="","",Attendance!C10) -> 545 | AM23: =IF(Attendance!C10="","",Attendance!D10) -> 653 | AN23: =IF(Attendance!E10="","",Attendance!E10) -> 0.83460949 | AO23: =IF(Attendance!F10="","",Attendance!F10) -> 120 | AP23: =IF(Attendance!C10="","",Attendance!I10) -> 27 | AQ23: =IF('Monthly KPI Report'!S5="MISSING","",'Monthly KPI Report'!R5) -> 0.75 | AR23: =IFERROR(N23/H23,"") -> 92.432792 | AS23: =IFERROR(Q23/H23,"") -> 1038.918 | AT23: =IFERROR(IF(OR(AB23="",H23=""),"",AB23/H23),"") -> 28.175775 | AV23: =IFERROR(S23/T23,"") -> 0.34482759 | AW23: =IFERROR(J23*1000/(H23*$B23),"") -> 420.43765 | AX23: =IFERROR(K23*1000/(H23*$B23),"") -> 116.38157 | AY23: =IFERROR(L23*1000/(H23*$B23),"") -> 307.97637 | AZ23: =IFERROR(M23*1000/(H23*$B23),"") -> 145.11364 | BA23: =IFERROR(K23/(J23+K23),"") -> 0.21679844 | BB23: =IFERROR(IF(OR(V23="",H23=""),"",V23/H23),"") -> 112.70657 | BC23: =IFERROR(IF(OR(V23="",N23=""),"",V23/N23),"") -> 1.2193354 | BD23: =IFERROR(IF(OR(X23="",H23=""),"",X23/H23),"") -> 1255.8372 | BH23: =IFERROR(C23*100/H23,"") | BI23: =IFERROR(D23/C23,"") | BJ23: =IFERROR(F23/C23,"") | BK23: =IFERROR(E23*1000/H23,"") | BL23: =IFERROR(AJ23/H23,"") | BM23: =IFERROR(AJ23/AK23,"") | BN23: =IFERROR(AO23*100/AL23,"") -> 22.018349 | BO23: =IFERROR(H23/AP23,"") -> 50.148148 | BP23: =IF(OR(Q23="",AJ23=""),"",Q23+AJ23) | BQ23: =IFERROR(IF(OR(BP23="",H23=""),"",BP23/H23),"") | BR23: =IFERROR(Y23/H23,"") -> 0.012555391 | BT23: =IF(N23="",0,N23) -> 125154 | BU23: =IF(V23="",0,V23) -> 152604.7 | BV23: =IF(J23="",0,J23) -> 17647.45 | BW23: =IF(K23="",0,K23) -> 4885 | BX23: =IF(I23="",0,I23) -> 474.55568 | BY23: =IF(U23="",0,U23) -> 2.3769917 | BZ23: =IF(P23="",0,P23) -> 0.96435506 | CA23: =IF(Q23="",0,Q23) -> 1406695 | CB23: =IF(L23="",0,L23) -> 12927 | CC23: =IF(C23="",0,C23) -> 0 | CD23: =IF(D23="",0,D23) -> 0 | CE23: =IF(AN23="",0,AN23) -> 0.83460949 | CI23: =IF(AR23="",0,AR23) -> 92.432792 | CJ23: =IF(BQ23="",0,BQ23) -> 0 | CK23: =IF(AB23="",0,AB23) -> 38150 | CL23: =IF(Y23="",0,Y23) -> 17 | CM23: =IF(Z23="",0,Z23) -> 11 | CO23: =IF(G23="",0,G23) -> 19919 | CP23: =MIS_Calc!$B$8 -> 135 | CQ23: =MIS_Calc!$B$9 -> 8 | CR23: =MIS_Calc!$B$10 -> 0.95 | CS23: =MIS_Calc!$B$11 -> 0.9
A24: Apr-26 | B24: 30 | C24: =IF('Complaints summary'!C11="","",'Complaints summary'!C11) | D24: =IF('Complaints summary'!F11="","",'Complaints summary'!F11) | E24: =IF('Complaints summary'!I11="","",'Complaints summary'!I11) | F24: =IF('Complaints summary'!D11="","",'Complaints summary'!D11) | G24: =IF(LPCD!C11="","",LPCD!C11/1000) -> 21828 | H24: =IF(LPCD!D11="","",LPCD!D11) -> 1354 | I24: =IF(LPCD!F11="","",LPCD!F11) -> 537.37075 | J24: =IF('Building wise water'!L38="","",'Building wise water'!L38) -> 18490.49 | K24: =IF('Building wise water'!L39="","",'Building wise water'!L39) -> 3764 | L24: =IF('Building wise water'!L33="","",'Building wise water'!L33) -> 12096 | M24: =IF('Building wise water'!L34="","",'Building wise water'!L34) -> 7080 | N24: =IF('Power data'!C10="","",'Power data'!C10) -> 198066 | O24: =IF('Power data'!D10="","",'Power data'!D10) -> 204438 | P24: =IF('Power data'!E10="","",'Power data'!E10) -> 0.96883163 | Q24: =IF('Power data'!F10="","",'Power data'!F10) -> 2109953 | R24: =IF('Power data'!G10="","",'Power data'!G10) -> 10.320748 | S24: =IF('Power data'!H10="","",'Power data'!H10) -> 744 | T24: =IF('Power data'!I10="","",'Power data'!I10) -> 1276 | U24: =IF(EPI!D10="","",EPI!D10) -> 3.7617754 | V24: =IF('Solar Power'!F32="","",'Solar Power'!F32) -> 136018.1 | W24: =IF('Solar Power'!C8="","",'Solar Power'!C8) -> 227564 | X24: =IF('Solar Power'!D8="","",'Solar Power'!D8) -> 2685255.2 | Y24: =IF('DG Units Generated'!E11="","",'DG Units Generated'!E11) -> 22 | Z24: =IF('DG Units Generated'!G11="","",'DG Units Generated'!G11) -> 4 | AA24: =IF('DG Units Generated'!H11="","",'DG Units Generated'!H11) -> 0.55 | AB24: =IF('HVAC consumption'!N11="","",'HVAC consumption'!N11) -> 62374 | AJ24: =IF('Technical manpower cost'!E55="","",'Technical manpower cost'!E55*1000) | AK24: =IF('Technical manpower cost'!F55="","",'Technical manpower cost'!F55*1000) | AL24: =IF(Attendance!C11="","",Attendance!C11) -> 530 | AM24: =IF(Attendance!C11="","",Attendance!D11) -> 676 | AN24: =IF(Attendance!E11="","",Attendance!E11) -> 0.78402367 | AO24: =IF(Attendance!F11="","",Attendance!F11) | AP24: =IF(Attendance!C11="","",Attendance!I11) -> 26 | AQ24: =IF('Monthly KPI Report'!S6="MISSING","",'Monthly KPI Report'!R6) -> 0.75 | AR24: =IFERROR(N24/H24,"") -> 146.28213 | AS24: =IFERROR(Q24/H24,"") -> 1558.3109 | AT24: =IFERROR(IF(OR(AB24="",H24=""),"",AB24/H24),"") -> 46.06647 | AV24: =IFERROR(S24/T24,"") -> 0.5830721 | AW24: =IFERROR(J24*1000/(H24*$B24),"") -> 455.20655 | AX24: =IFERROR(K24*1000/(H24*$B24),"") -> 92.663712 | AY24: =IFERROR(L24*1000/(H24*$B24),"") -> 297.78434 | AZ24: =IFERROR(M24*1000/(H24*$B24),"") -> 174.29838 | BA24: =IFERROR(K24/(J24+K24),"") -> 0.16913441 | BB24: =IFERROR(IF(OR(V24="",H24=""),"",V24/H24),"") -> 100.4565 | BC24: =IFERROR(IF(OR(V24="",N24=""),"",V24/N24),"") -> 0.68673119 | BD24: =IFERROR(IF(OR(X24="",H24=""),"",X24/H24),"") -> 1983.2018 | BH24: =IFERROR(C24*100/H24,"") | BI24: =IFERROR(D24/C24,"") | BJ24: =IFERROR(F24/C24,"") | BK24: =IFERROR(E24*1000/H24,"") | BL24: =IFERROR(AJ24/H24,"") | BM24: =IFERROR(AJ24/AK24,"") | BN24: =IFERROR(AO24*100/AL24,"") | BO24: =IFERROR(H24/AP24,"") -> 52.076923 | BP24: =IF(OR(Q24="",AJ24=""),"",Q24+AJ24) | BQ24: =IFERROR(IF(OR(BP24="",H24=""),"",BP24/H24),"") | BR24: =IFERROR(Y24/H24,"") -> 0.016248154 | BT24: =IF(N24="",0,N24) -> 198066 | BU24: =IF(V24="",0,V24) -> 136018.1 | BV24: =IF(J24="",0,J24) -> 18490.49 | BW24: =IF(K24="",0,K24) -> 3764 | BX24: =IF(I24="",0,I24) -> 537.37075 | BY24: =IF(U24="",0,U24) -> 3.7617754 | BZ24: =IF(P24="",0,P24) -> 0.96883163 | CA24: =IF(Q24="",0,Q24) -> 2109953 | CB24: =IF(L24="",0,L24) -> 12096 | CC24: =IF(C24="",0,C24) -> 0 | CD24: =IF(D24="",0,D24) -> 0 | CE24: =IF(AN24="",0,AN24) -> 0.78402367 | CI24: =IF(AR24="",0,AR24) -> 146.28213 | CJ24: =IF(BQ24="",0,BQ24) -> 0 | CK24: =IF(AB24="",0,AB24) -> 62374 | CL24: =IF(Y24="",0,Y24) -> 22 | CM24: =IF(Z24="",0,Z24) -> 4 | CO24: =IF(G24="",0,G24) -> 21828 | CP24: =MIS_Calc!$B$8 -> 135 | CQ24: =MIS_Calc!$B$9 -> 8 | CR24: =MIS_Calc!$B$10 -> 0.95 | CS24: =MIS_Calc!$B$11 -> 0.9
A25: May-26 | B25: 31 | C25: =IF('Complaints summary'!C12="","",'Complaints summary'!C12) | D25: =IF('Complaints summary'!F12="","",'Complaints summary'!F12) | E25: =IF('Complaints summary'!I12="","",'Complaints summary'!I12) | F25: =IF('Complaints summary'!D12="","",'Complaints summary'!D12) | G25: =IF(LPCD!C12="","",LPCD!C12/1000) -> 26607 | H25: =IF(LPCD!D12="","",LPCD!D12) -> 1354 | I25: =IF(LPCD!F12="","",LPCD!F12) -> 633.89241 | J25: =IF('Building wise water'!M38="","",'Building wise water'!M38) -> 21759.4 | K25: =IF('Building wise water'!M39="","",'Building wise water'!M39) -> 1496 | L25: =IF('Building wise water'!M33="","",'Building wise water'!M33) -> 11615 | M25: =IF('Building wise water'!M34="","",'Building wise water'!M34) -> 7193 | N25: =IF('Power data'!C11="","",'Power data'!C11) -> 222144 | O25: =IF('Power data'!D11="","",'Power data'!D11) -> 226842 | P25: =IF('Power data'!E11="","",'Power data'!E11) -> 0.97928955 | Q25: =IF('Power data'!F11="","",'Power data'!F11) -> 2496490 | R25: =IF('Power data'!G11="","",'Power data'!G11) -> 11.005413 | S25: =IF('Power data'!H11="","",'Power data'!H11) -> 706 | T25: =IF('Power data'!I11="","",'Power data'!I11) -> 1276 | U25: =IF(EPI!D11="","",EPI!D11) -> 4.2190776 | V25: =IF('Solar Power'!G32="","",'Solar Power'!G32) -> 145805.6 | W25: =IF('Solar Power'!C9="","",'Solar Power'!C9) -> 131666 | X25: =IF('Solar Power'!D9="","",'Solar Power'!D9) -> 1553658.8 | Y25: =IF('DG Units Generated'!E12="","",'DG Units Generated'!E12) -> 44 | Z25: =IF('DG Units Generated'!G12="","",'DG Units Generated'!G12) -> 2 | AA25: =IF('DG Units Generated'!H12="","",'DG Units Generated'!H12) -> 6.25 | AB25: =IF('HVAC consumption'!N12="","",'HVAC consumption'!N12) -> 23976.4 | AJ25: =IF('Technical manpower cost'!E56="","",'Technical manpower cost'!E56*1000) | AK25: =IF('Technical manpower cost'!F56="","",'Technical manpower cost'!F56*1000) | AL25: =IF(Attendance!C12="","",Attendance!C12) -> 550 | AM25: =IF(Attendance!C12="","",Attendance!D12) -> 655 | AN25: =IF(Attendance!E12="","",Attendance!E12) -> 0.83969466 | AO25: =IF(Attendance!F12="","",Attendance!F12) | AP25: =IF(Attendance!C12="","",Attendance!I12) -> 26 | AQ25: =IF('Monthly KPI Report'!S7="MISSING","",'Monthly KPI Report'!R7) -> 0.75 | AR25: =IFERROR(N25/H25,"") -> 164.06499 | AS25: =IFERROR(Q25/H25,"") -> 1843.7888 | AT25: =IFERROR(IF(OR(AB25="",H25=""),"",AB25/H25),"") -> 17.707829 | AV25: =IFERROR(S25/T25,"") -> 0.55329154 | AW25: =IFERROR(J25*1000/(H25*$B25),"") -> 518.40187 | AX25: =IFERROR(K25*1000/(H25*$B25),"") -> 35.641111 | AY25: =IFERROR(L25*1000/(H25*$B25),"") -> 276.71892 | AZ25: =IFERROR(M25*1000/(H25*$B25),"") -> 171.36799 | BA25: =IFERROR(K25/(J25+K25),"") -> 0.064329145 | BB25: =IFERROR(IF(OR(V25="",H25=""),"",V25/H25),"") -> 107.68508 | BC25: =IFERROR(IF(OR(V25="",N25=""),"",V25/N25),"") -> 0.65635624 | BD25: =IFERROR(IF(OR(X25="",H25=""),"",X25/H25),"") -> 1147.4585 | BH25: =IFERROR(C25*100/H25,"") | BI25: =IFERROR(D25/C25,"") | BJ25: =IFERROR(F25/C25,"") | BK25: =IFERROR(E25*1000/H25,"") | BL25: =IFERROR(AJ25/H25,"") | BM25: =IFERROR(AJ25/AK25,"") | BN25: =IFERROR(AO25*100/AL25,"") | BO25: =IFERROR(H25/AP25,"") -> 52.076923 | BP25: =IF(OR(Q25="",AJ25=""),"",Q25+AJ25) | BQ25: =IFERROR(IF(OR(BP25="",H25=""),"",BP25/H25),"") | BR25: =IFERROR(Y25/H25,"") -> 0.032496307 | BT25: =IF(N25="",0,N25) -> 222144 | BU25: =IF(V25="",0,V25) -> 145805.6 | BV25: =IF(J25="",0,J25) -> 21759.4 | BW25: =IF(K25="",0,K25) -> 1496 | BX25: =IF(I25="",0,I25) -> 633.89241 | BY25: =IF(U25="",0,U25) -> 4.2190776 | BZ25: =IF(P25="",0,P25) -> 0.97928955 | CA25: =IF(Q25="",0,Q25) -> 2496490 | CB25: =IF(L25="",0,L25) -> 11615 | CC25: =IF(C25="",0,C25) -> 0 | CD25: =IF(D25="",0,D25) -> 0 | CE25: =IF(AN25="",0,AN25) -> 0.83969466 | CI25: =IF(AR25="",0,AR25) -> 164.06499 | CJ25: =IF(BQ25="",0,BQ25) -> 0 | CK25: =IF(AB25="",0,AB25) -> 23976.4 | CL25: =IF(Y25="",0,Y25) -> 44 | CM25: =IF(Z25="",0,Z25) -> 2 | CO25: =IF(G25="",0,G25) -> 26607 | CP25: =MIS_Calc!$B$8 -> 135 | CQ25: =MIS_Calc!$B$9 -> 8 | CR25: =MIS_Calc!$B$10 -> 0.95 | CS25: =MIS_Calc!$B$11 -> 0.9
A26: Jun-26 | B26: 30 | C26: =IF('Complaints summary'!C13="","",'Complaints summary'!C13) -> 155 | D26: =IF('Complaints summary'!F13="","",'Complaints summary'!F13) -> 155 | E26: =IF('Complaints summary'!I13="","",'Complaints summary'!I13) | F26: =IF('Complaints summary'!D13="","",'Complaints summary'!D13) -> 5 | G26: =IF(LPCD!C13="","",LPCD!C13/1000) -> 12988 | H26: =IF(LPCD!D13="","",LPCD!D13) -> 1354 | I26: =IF(LPCD!F13="","",LPCD!F13) -> 319.74397 | J26: =IF('Building wise water'!N38="","",'Building wise water'!N38) -> 11528.59 | K26: =IF('Building wise water'!N39="","",'Building wise water'!N39) -> 1929 | L26: =IF('Building wise water'!N33="","",'Building wise water'!N33) -> 7361 | M26: =IF('Building wise water'!N34="","",'Building wise water'!N34) -> 3865 | N26: =IF('Power data'!C12="","",'Power data'!C12) -> 72912 | O26: =IF('Power data'!D12="","",'Power data'!D12) -> 75684 | P26: =IF('Power data'!E12="","",'Power data'!E12) -> 0.96337403 | Q26: =IF('Power data'!F12="","",'Power data'!F12) -> 777429 | R26: =IF('Power data'!G12="","",'Power data'!G12) -> 10.272039 | S26: =IF('Power data'!H12="","",'Power data'!H12) -> 321 | T26: =IF('Power data'!I12="","",'Power data'!I12) -> 1276 | U26: =IF(EPI!D12="","",EPI!D12) -> 1.3847837 | V26: =IF('Solar Power'!H32="","",'Solar Power'!H32) -> 128018 | W26: =IF('Solar Power'!C10="","",'Solar Power'!C10) -> 128018 | X26: =IF('Solar Power'!D10="","",'Solar Power'!D10) -> 1510612.4 | Y26: =IF('DG Units Generated'!E13="","",'DG Units Generated'!E13) -> 26 | Z26: =IF('DG Units Generated'!G13="","",'DG Units Generated'!G13) -> 5 | AA26: =IF('DG Units Generated'!H13="","",'DG Units Generated'!H13) -> 1.45 | AB26: =IF('HVAC consumption'!N13="","",'HVAC consumption'!N13) -> 11970.4 | AJ26: =IF('Technical manpower cost'!E57="","",'Technical manpower cost'!E57*1000) | AK26: =IF('Technical manpower cost'!F57="","",'Technical manpower cost'!F57*1000) | AL26: =IF(Attendance!C13="","",Attendance!C13) -> 580 | AM26: =IF(Attendance!C13="","",Attendance!D13) -> 663 | AN26: =IF(Attendance!E13="","",Attendance!E13) -> 0.87481146 | AO26: =IF(Attendance!F13="","",Attendance!F13) | AP26: =IF(Attendance!C13="","",Attendance!I13) -> 27 | AQ26: =IF('Monthly KPI Report'!S8="MISSING","",'Monthly KPI Report'!R8) -> 0.875 | AR26: =IFERROR(N26/H26,"") -> 53.849335 | AS26: =IFERROR(Q26/H26,"") -> 574.17208 | AT26: =IFERROR(IF(OR(AB26="",H26=""),"",AB26/H26),"") -> 8.8407681 | AV26: =IFERROR(S26/T26,"") -> 0.2515674 | AW26: =IFERROR(J26*1000/(H26*$B26),"") -> 283.81561 | AX26: =IFERROR(K26*1000/(H26*$B26),"") -> 47.488922 | AY26: =IFERROR(L26*1000/(H26*$B26),"") -> 181.21615 | AZ26: =IFERROR(M26*1000/(H26*$B26),"") -> 95.150172 | BA26: =IFERROR(K26/(J26+K26),"") -> 0.14333919 | BB26: =IFERROR(IF(OR(V26="",H26=""),"",V26/H26),"") -> 94.548006 | BC26: =IFERROR(IF(OR(V26="",N26=""),"",V26/N26),"") -> 1.7557878 | BD26: =IFERROR(IF(OR(X26="",H26=""),"",X26/H26),"") -> 1115.6665 | BH26: =IFERROR(C26*100/H26,"") -> 11.447563 | BI26: =IFERROR(D26/C26,"") -> 1 | BJ26: =IFERROR(F26/C26,"") -> 0.032258065 | BK26: =IFERROR(E26*1000/H26,"") | BL26: =IFERROR(AJ26/H26,"") | BM26: =IFERROR(AJ26/AK26,"") | BN26: =IFERROR(AO26*100/AL26,"") | BO26: =IFERROR(H26/AP26,"") -> 50.148148 | BP26: =IF(OR(Q26="",AJ26=""),"",Q26+AJ26) | BQ26: =IFERROR(IF(OR(BP26="",H26=""),"",BP26/H26),"") | BR26: =IFERROR(Y26/H26,"") -> 0.019202363 | BT26: =IF(N26="",0,N26) -> 72912 | BU26: =IF(V26="",0,V26) -> 128018 | BV26: =IF(J26="",0,J26) -> 11528.59 | BW26: =IF(K26="",0,K26) -> 1929 | BX26: =IF(I26="",0,I26) -> 319.74397 | BY26: =IF(U26="",0,U26) -> 1.3847837 | BZ26: =IF(P26="",0,P26) -> 0.96337403 | CA26: =IF(Q26="",0,Q26) -> 777429 | CB26: =IF(L26="",0,L26) -> 7361 | CC26: =IF(C26="",0,C26) -> 155 | CD26: =IF(D26="",0,D26) -> 155 | CE26: =IF(AN26="",0,AN26) -> 0.87481146 | CI26: =IF(AR26="",0,AR26) -> 53.849335 | CJ26: =IF(BQ26="",0,BQ26) -> 0 | CK26: =IF(AB26="",0,AB26) -> 11970.4 | CL26: =IF(Y26="",0,Y26) -> 26 | CM26: =IF(Z26="",0,Z26) -> 5 | CO26: =IF(G26="",0,G26) -> 12988 | CP26: =MIS_Calc!$B$8 -> 135 | CQ26: =MIS_Calc!$B$9 -> 8 | CR26: =MIS_Calc!$B$10 -> 0.95 | CS26: =MIS_Calc!$B$11 -> 0.9
A27: Jul-26 | B27: 31 | C27: =IF('Complaints summary'!C14="","",'Complaints summary'!C14) -> 168 | D27: =IF('Complaints summary'!F14="","",'Complaints summary'!F14) -> 127 | E27: =IF('Complaints summary'!I14="","",'Complaints summary'!I14) | F27: =IF('Complaints summary'!D14="","",'Complaints summary'!D14) -> 6 | G27: =IF(LPCD!C14="","",LPCD!C14/1000) -> 9633 | H27: =IF(LPCD!D14="","",LPCD!D14) -> 1354 | I27: =IF(LPCD!F14="","",LPCD!F14) -> 229.49921 | J27: =IF('Building wise water'!O38="","",'Building wise water'!O38) -> 15618.59 | K27: =IF('Building wise water'!O39="","",'Building wise water'!O39) -> 2303 | L27: =IF('Building wise water'!O33="","",'Building wise water'!O33) -> 8310 | M27: =IF('Building wise water'!O34="","",'Building wise water'!O34) -> 1136 | N27: =IF('Power data'!C13="","",'Power data'!C13) -> 122658 | O27: =IF('Power data'!D13="","",'Power data'!D13) -> 126318 | P27: =IF('Power data'!E13="","",'Power data'!E13) -> 0.97102551 | Q27: =IF('Power data'!F13="","",'Power data'!F13) -> 1501851 | R27: =IF('Power data'!G13="","",'Power data'!G13) -> 11.889446 | S27: =IF('Power data'!H13="","",'Power data'!H13) -> 451.44 | T27: =IF('Power data'!I13="","",'Power data'!I13) -> 1276 | U27: =IF(EPI!D13="","",EPI!D13) -> 2.3295863 | V27: =IF('Solar Power'!I32="","",'Solar Power'!I32) -> 100380 | W27: =IF('Solar Power'!C11="","",'Solar Power'!C11) -> 100380 | X27: =IF('Solar Power'!D11="","",'Solar Power'!D11) -> 1184484 | Y27: =IF('DG Units Generated'!E14="","",'DG Units Generated'!E14) -> 56 | Z27: =IF('DG Units Generated'!G14="","",'DG Units Generated'!G14) -> 1 | AA27: =IF('DG Units Generated'!H14="","",'DG Units Generated'!H14) -> 0.15 | AB27: =IF('HVAC consumption'!N14="","",'HVAC consumption'!N14) -> 28833.3 | AJ27: =IF('Technical manpower cost'!E58="","",'Technical manpower cost'!E58*1000) | AK27: =IF('Technical manpower cost'!F58="","",'Technical manpower cost'!F58*1000) | AL27: =IF(Attendance!C14="","",Attendance!C14) -> 595 | AM27: =IF(Attendance!C14="","",Attendance!D14) -> 634 | AN27: =IF(Attendance!E14="","",Attendance!E14) -> 0.9384858 | AO27: =IF(Attendance!F14="","",Attendance!F14) | AP27: =IF(Attendance!C14="","",Attendance!I14) -> 27 | AQ27: =IF('Monthly KPI Report'!S9="MISSING","",'Monthly KPI Report'!R9) -> 0.875 | AR27: =IFERROR(N27/H27,"") -> 90.589365 | AS27: =IFERROR(Q27/H27,"") -> 1109.1957 | AT27: =IFERROR(IF(OR(AB27="",H27=""),"",AB27/H27),"") -> 21.294904 | AV27: =IFERROR(S27/T27,"") -> 0.3537931 | AW27: =IFERROR(J27*1000/(H27*$B27),"") -> 372.10154 | AX27: =IFERROR(K27*1000/(H27*$B27),"") -> 54.867299 | AY27: =IFERROR(L27*1000/(H27*$B27),"") -> 197.9797 | AZ27: =IFERROR(M27*1000/(H27*$B27),"") -> 27.064373 | BA27: =IFERROR(K27/(J27+K27),"") -> 0.12850422 | BB27: =IFERROR(IF(OR(V27="",H27=""),"",V27/H27),"") -> 74.135894 | BC27: =IFERROR(IF(OR(V27="",N27=""),"",V27/N27),"") -> 0.81837304 | BD27: =IFERROR(IF(OR(X27="",H27=""),"",X27/H27),"") -> 874.80355 | BH27: =IFERROR(C27*100/H27,"") -> 12.407681 | BI27: =IFERROR(D27/C27,"") -> 0.75595238 | BJ27: =IFERROR(F27/C27,"") -> 0.035714286 | BK27: =IFERROR(E27*1000/H27,"") | BL27: =IFERROR(AJ27/H27,"") | BM27: =IFERROR(AJ27/AK27,"") | BN27: =IFERROR(AO27*100/AL27,"") | BO27: =IFERROR(H27/AP27,"") -> 50.148148 | BP27: =IF(OR(Q27="",AJ27=""),"",Q27+AJ27) | BQ27: =IFERROR(IF(OR(BP27="",H27=""),"",BP27/H27),"") | BR27: =IFERROR(Y27/H27,"") -> 0.041358936 | BT27: =IF(N27="",0,N27) -> 122658 | BU27: =IF(V27="",0,V27) -> 100380 | BV27: =IF(J27="",0,J27) -> 15618.59 | BW27: =IF(K27="",0,K27) -> 2303 | BX27: =IF(I27="",0,I27) -> 229.49921 | BY27: =IF(U27="",0,U27) -> 2.3295863 | BZ27: =IF(P27="",0,P27) -> 0.97102551 | CA27: =IF(Q27="",0,Q27) -> 1501851 | CB27: =IF(L27="",0,L27) -> 8310 | CC27: =IF(C27="",0,C27) -> 168 | CD27: =IF(D27="",0,D27) -> 127 | CE27: =IF(AN27="",0,AN27) -> 0.9384858 | CI27: =IF(AR27="",0,AR27) -> 90.589365 | CJ27: =IF(BQ27="",0,BQ27) -> 0 | CK27: =IF(AB27="",0,AB27) -> 28833.3 | CL27: =IF(Y27="",0,Y27) -> 56 | CM27: =IF(Z27="",0,Z27) -> 1 | CO27: =IF(G27="",0,G27) -> 9633 | CP27: =MIS_Calc!$B$8 -> 135 | CQ27: =MIS_Calc!$B$9 -> 8 | CR27: =MIS_Calc!$B$10 -> 0.95 | CS27: =MIS_Calc!$B$11 -> 0.9
A28: Aug-26 | B28: 31 | C28: =IF('Complaints summary'!C15="","",'Complaints summary'!C15) -> 216 | D28: =IF('Complaints summary'!F15="","",'Complaints summary'!F15) -> 146 | E28: =IF('Complaints summary'!I15="","",'Complaints summary'!I15) | F28: =IF('Complaints summary'!D15="","",'Complaints summary'!D15) -> 7 | G28: =IF(LPCD!C15="","",LPCD!C15/1000) -> 14026 | H28: =IF(LPCD!D15="","",LPCD!D15) -> 1354 | I28: =IF(LPCD!F15="","",LPCD!F15) -> 334.15924 | J28: =IF('Building wise water'!P38="","",'Building wise water'!P38) -> 11995 | K28: =IF('Building wise water'!P39="","",'Building wise water'!P39) -> 2683 | L28: =IF('Building wise water'!P33="","",'Building wise water'!P33) -> 10986 | M28: =IF('Building wise water'!P34="","",'Building wise water'!P34) -> 2501 | N28: =IF('Power data'!C14="","",'Power data'!C14) -> 146382 | O28: =IF('Power data'!D14="","",'Power data'!D14) -> 156360 | P28: =IF('Power data'!E14="","",'Power data'!E14) -> 0.93618573 | Q28: =IF('Power data'!F14="","",'Power data'!F14) -> 1829571 | R28: =IF('Power data'!G14="","",'Power data'!G14) -> 11.701017 | S28: =IF('Power data'!H14="","",'Power data'!H14) -> 475 | T28: =IF('Power data'!I14="","",'Power data'!I14) -> 1276 | U28: =IF(EPI!D14="","",EPI!D14) -> 2.7801652 | V28: =IF('Solar Power'!J32="","",'Solar Power'!J32) -> 115911 | W28: =IF('Solar Power'!C12="","",'Solar Power'!C12) -> 115911 | X28: =IF('Solar Power'!D12="","",'Solar Power'!D12) -> 1367749.8 | Y28: =IF('DG Units Generated'!E15="","",'DG Units Generated'!E15) -> 11 | Z28: =IF('DG Units Generated'!G15="","",'DG Units Generated'!G15) -> 1 | AA28: =IF('DG Units Generated'!H15="","",'DG Units Generated'!H15) -> 0.15 | AB28: =IF('HVAC consumption'!N15="","",'HVAC consumption'!N15) -> 21957.88 | AJ28: =IF('Technical manpower cost'!E59="","",'Technical manpower cost'!E59*1000) | AK28: =IF('Technical manpower cost'!F59="","",'Technical manpower cost'!F59*1000) | AL28: =IF(Attendance!C15="","",Attendance!C15) -> 543 | AM28: =IF(Attendance!C15="","",Attendance!D15) -> 640 | AN28: =IF(Attendance!E15="","",Attendance!E15) -> 0.8484375 | AO28: =IF(Attendance!F15="","",Attendance!F15) | AP28: =IF(Attendance!C15="","",Attendance!I15) -> 27 | AQ28: =IF('Monthly KPI Report'!S10="MISSING","",'Monthly KPI Report'!R10) -> 0.875 | AR28: =IFERROR(N28/H28,"") -> 108.11078 | AS28: =IFERROR(Q28/H28,"") -> 1351.2341 | AT28: =IFERROR(IF(OR(AB28="",H28=""),"",AB28/H28),"") -> 16.217046 | AV28: =IFERROR(S28/T28,"") -> 0.37225705 | AW28: =IFERROR(J28*1000/(H28*$B28),"") -> 285.77214 | AX28: =IFERROR(K28*1000/(H28*$B28),"") -> 63.920522 | AY28: =IFERROR(L28*1000/(H28*$B28),"") -> 261.73345 | AZ28: =IFERROR(M28*1000/(H28*$B28),"") -> 59.584505 | BA28: =IFERROR(K28/(J28+K28),"") -> 0.18279057 | BB28: =IFERROR(IF(OR(V28="",H28=""),"",V28/H28),"") -> 85.606352 | BC28: =IFERROR(IF(OR(V28="",N28=""),"",V28/N28),"") -> 0.79183916 | BD28: =IFERROR(IF(OR(X28="",H28=""),"",X28/H28),"") -> 1010.1549 | BH28: =IFERROR(C28*100/H28,"") -> 15.952733 | BI28: =IFERROR(D28/C28,"") -> 0.67592593 | BJ28: =IFERROR(F28/C28,"") -> 0.032407407 | BK28: =IFERROR(E28*1000/H28,"") | BL28: =IFERROR(AJ28/H28,"") | BM28: =IFERROR(AJ28/AK28,"") | BN28: =IFERROR(AO28*100/AL28,"") | BO28: =IFERROR(H28/AP28,"") -> 50.148148 | BP28: =IF(OR(Q28="",AJ28=""),"",Q28+AJ28) | BQ28: =IFERROR(IF(OR(BP28="",H28=""),"",BP28/H28),"") | BR28: =IFERROR(Y28/H28,"") -> 0.0081240768 | BT28: =IF(N28="",0,N28) -> 146382 | BU28: =IF(V28="",0,V28) -> 115911 | BV28: =IF(J28="",0,J28) -> 11995 | BW28: =IF(K28="",0,K28) -> 2683 | BX28: =IF(I28="",0,I28) -> 334.15924 | BY28: =IF(U28="",0,U28) -> 2.7801652 | BZ28: =IF(P28="",0,P28) -> 0.93618573 | CA28: =IF(Q28="",0,Q28) -> 1829571 | CB28: =IF(L28="",0,L28) -> 10986 | CC28: =IF(C28="",0,C28) -> 216 | CD28: =IF(D28="",0,D28) -> 146 | CE28: =IF(AN28="",0,AN28) -> 0.8484375 | CI28: =IF(AR28="",0,AR28) -> 108.11078 | CJ28: =IF(BQ28="",0,BQ28) -> 0 | CK28: =IF(AB28="",0,AB28) -> 21957.88 | CL28: =IF(Y28="",0,Y28) -> 11 | CM28: =IF(Z28="",0,Z28) -> 1 | CO28: =IF(G28="",0,G28) -> 14026 | CP28: =MIS_Calc!$B$8 -> 135 | CQ28: =MIS_Calc!$B$9 -> 8 | CR28: =MIS_Calc!$B$10 -> 0.95 | CS28: =MIS_Calc!$B$11 -> 0.9
A29: Sep-26 | B29: 30 | C29: =IF('Complaints summary'!C16="","",'Complaints summary'!C16) | D29: =IF('Complaints summary'!F16="","",'Complaints summary'!F16) | E29: =IF('Complaints summary'!I16="","",'Complaints summary'!I16) | F29: =IF('Complaints summary'!D16="","",'Complaints summary'!D16) | G29: =IF(LPCD!C16="","",LPCD!C16/1000) | H29: =IF(LPCD!D16="","",LPCD!D16) -> 1354 | I29: =IF(LPCD!F16="","",LPCD!F16) | J29: =IF('Building wise water'!Q38="","",'Building wise water'!Q38) | K29: =IF('Building wise water'!Q39="","",'Building wise water'!Q39) | L29: =IF('Building wise water'!Q33="","",'Building wise water'!Q33) | M29: =IF('Building wise water'!Q34="","",'Building wise water'!Q34) | N29: =IF('Power data'!C15="","",'Power data'!C15) | O29: =IF('Power data'!D15="","",'Power data'!D15) | P29: =IF('Power data'!E15="","",'Power data'!E15) | Q29: =IF('Power data'!F15="","",'Power data'!F15) | R29: =IF('Power data'!G15="","",'Power data'!G15) | S29: =IF('Power data'!H15="","",'Power data'!H15) | T29: =IF('Power data'!I15="","",'Power data'!I15) | U29: =IF(EPI!D15="","",EPI!D15) | V29: =IF('Solar Power'!K32="","",'Solar Power'!K32) | W29: =IF('Solar Power'!C13="","",'Solar Power'!C13) | X29: =IF('Solar Power'!D13="","",'Solar Power'!D13) | Y29: =IF('DG Units Generated'!E16="","",'DG Units Generated'!E16) | Z29: =IF('DG Units Generated'!G16="","",'DG Units Generated'!G16) | AA29: =IF('DG Units Generated'!H16="","",'DG Units Generated'!H16) | AB29: =IF('HVAC consumption'!N16="","",'HVAC consumption'!N16) | AJ29: =IF('Technical manpower cost'!E60="","",'Technical manpower cost'!E60*1000) | AK29: =IF('Technical manpower cost'!F60="","",'Technical manpower cost'!F60*1000) | AL29: =IF(Attendance!C16="","",Attendance!C16) | AM29: =IF(Attendance!C16="","",Attendance!D16) | AN29: =IF(Attendance!E16="","",Attendance!E16) | AO29: =IF(Attendance!F16="","",Attendance!F16) | AP29: =IF(Attendance!C16="","",Attendance!I16) | AQ29: =IF('Monthly KPI Report'!S11="MISSING","",'Monthly KPI Report'!R11) | AR29: =IFERROR(N29/H29,"") | AS29: =IFERROR(Q29/H29,"") | AT29: =IFERROR(IF(OR(AB29="",H29=""),"",AB29/H29),"") | AV29: =IFERROR(S29/T29,"") | AW29: =IFERROR(J29*1000/(H29*$B29),"") | AX29: =IFERROR(K29*1000/(H29*$B29),"") | AY29: =IFERROR(L29*1000/(H29*$B29),"") | AZ29: =IFERROR(M29*1000/(H29*$B29),"") | BA29: =IFERROR(K29/(J29+K29),"") | BB29: =IFERROR(IF(OR(V29="",H29=""),"",V29/H29),"") | BC29: =IFERROR(IF(OR(V29="",N29=""),"",V29/N29),"") | BD29: =IFERROR(IF(OR(X29="",H29=""),"",X29/H29),"") | BH29: =IFERROR(C29*100/H29,"") | BI29: =IFERROR(D29/C29,"") | BJ29: =IFERROR(F29/C29,"") | BK29: =IFERROR(E29*1000/H29,"") | BL29: =IFERROR(AJ29/H29,"") | BM29: =IFERROR(AJ29/AK29,"") | BN29: =IFERROR(AO29*100/AL29,"") | BO29: =IFERROR(H29/AP29,"") | BP29: =IF(OR(Q29="",AJ29=""),"",Q29+AJ29) | BQ29: =IFERROR(IF(OR(BP29="",H29=""),"",BP29/H29),"") | BR29: =IFERROR(Y29/H29,"") | BT29: =IF(N29="",0,N29) -> 0 | BU29: =IF(V29="",0,V29) -> 0 | BV29: =IF(J29="",0,J29) -> 0 | BW29: =IF(K29="",0,K29) -> 0 | BX29: =IF(I29="",0,I29) -> 0 | BY29: =IF(U29="",0,U29) -> 0 | BZ29: =IF(P29="",0,P29) -> 0 | CA29: =IF(Q29="",0,Q29) -> 0 | CB29: =IF(L29="",0,L29) -> 0 | CC29: =IF(C29="",0,C29) -> 0 | CD29: =IF(D29="",0,D29) -> 0 | CE29: =IF(AN29="",0,AN29) -> 0 | CI29: =IF(AR29="",0,AR29) -> 0 | CJ29: =IF(BQ29="",0,BQ29) -> 0 | CK29: =IF(AB29="",0,AB29) -> 0 | CL29: =IF(Y29="",0,Y29) -> 0 | CM29: =IF(Z29="",0,Z29) -> 0 | CO29: =IF(G29="",0,G29) -> 0 | CP29: =MIS_Calc!$B$8 -> 135 | CQ29: =MIS_Calc!$B$9 -> 8 | CR29: =MIS_Calc!$B$10 -> 0.95 | CS29: =MIS_Calc!$B$11 -> 0.9
A30: Oct-26 | B30: 31 | C30: =IF('Complaints summary'!C17="","",'Complaints summary'!C17) | D30: =IF('Complaints summary'!F17="","",'Complaints summary'!F17) | E30: =IF('Complaints summary'!I17="","",'Complaints summary'!I17) | F30: =IF('Complaints summary'!D17="","",'Complaints summary'!D17) | G30: =IF(LPCD!C17="","",LPCD!C17/1000) | H30: =IF(LPCD!D17="","",LPCD!D17) -> 1354 | I30: =IF(LPCD!F17="","",LPCD!F17) | J30: =IF('Building wise water'!R38="","",'Building wise water'!R38) | K30: =IF('Building wise water'!R39="","",'Building wise water'!R39) | L30: =IF('Building wise water'!R33="","",'Building wise water'!R33) | M30: =IF('Building wise water'!R34="","",'Building wise water'!R34) | N30: =IF('Power data'!C16="","",'Power data'!C16) | O30: =IF('Power data'!D16="","",'Power data'!D16) | P30: =IF('Power data'!E16="","",'Power data'!E16) | Q30: =IF('Power data'!F16="","",'Power data'!F16) | R30: =IF('Power data'!G16="","",'Power data'!G16) | S30: =IF('Power data'!H16="","",'Power data'!H16) | T30: =IF('Power data'!I16="","",'Power data'!I16) | U30: =IF(EPI!D16="","",EPI!D16) | V30: =IF('Solar Power'!L32="","",'Solar Power'!L32) | W30: =IF('Solar Power'!C14="","",'Solar Power'!C14) | X30: =IF('Solar Power'!D14="","",'Solar Power'!D14) | Y30: =IF('DG Units Generated'!E17="","",'DG Units Generated'!E17) | Z30: =IF('DG Units Generated'!G17="","",'DG Units Generated'!G17) | AA30: =IF('DG Units Generated'!H17="","",'DG Units Generated'!H17) | AB30: =IF('HVAC consumption'!N17="","",'HVAC consumption'!N17) | AJ30: =IF('Technical manpower cost'!E61="","",'Technical manpower cost'!E61*1000) | AK30: =IF('Technical manpower cost'!F61="","",'Technical manpower cost'!F61*1000) | AL30: =IF(Attendance!C17="","",Attendance!C17) | AM30: =IF(Attendance!C17="","",Attendance!D17) | AN30: =IF(Attendance!E17="","",Attendance!E17) | AO30: =IF(Attendance!F17="","",Attendance!F17) | AP30: =IF(Attendance!C17="","",Attendance!I17) | AQ30: =IF('Monthly KPI Report'!S12="MISSING","",'Monthly KPI Report'!R12) | AR30: =IFERROR(N30/H30,"") | AS30: =IFERROR(Q30/H30,"") | AT30: =IFERROR(IF(OR(AB30="",H30=""),"",AB30/H30),"") | AV30: =IFERROR(S30/T30,"") | AW30: =IFERROR(J30*1000/(H30*$B30),"") | AX30: =IFERROR(K30*1000/(H30*$B30),"") | AY30: =IFERROR(L30*1000/(H30*$B30),"") | AZ30: =IFERROR(M30*1000/(H30*$B30),"") | BA30: =IFERROR(K30/(J30+K30),"") | BB30: =IFERROR(IF(OR(V30="",H30=""),"",V30/H30),"") | BC30: =IFERROR(IF(OR(V30="",N30=""),"",V30/N30),"") | BD30: =IFERROR(IF(OR(X30="",H30=""),"",X30/H30),"") | BH30: =IFERROR(C30*100/H30,"") | BI30: =IFERROR(D30/C30,"") | BJ30: =IFERROR(F30/C30,"") | BK30: =IFERROR(E30*1000/H30,"") | BL30: =IFERROR(AJ30/H30,"") | BM30: =IFERROR(AJ30/AK30,"") | BN30: =IFERROR(AO30*100/AL30,"") | BO30: =IFERROR(H30/AP30,"") | BP30: =IF(OR(Q30="",AJ30=""),"",Q30+AJ30) | BQ30: =IFERROR(IF(OR(BP30="",H30=""),"",BP30/H30),"") | BR30: =IFERROR(Y30/H30,"") | BT30: =IF(N30="",0,N30) -> 0 | BU30: =IF(V30="",0,V30) -> 0 | BV30: =IF(J30="",0,J30) -> 0 | BW30: =IF(K30="",0,K30) -> 0 | BX30: =IF(I30="",0,I30) -> 0 | BY30: =IF(U30="",0,U30) -> 0 | BZ30: =IF(P30="",0,P30) -> 0 | CA30: =IF(Q30="",0,Q30) -> 0 | CB30: =IF(L30="",0,L30) -> 0 | CC30: =IF(C30="",0,C30) -> 0 | CD30: =IF(D30="",0,D30) -> 0 | CE30: =IF(AN30="",0,AN30) -> 0 | CI30: =IF(AR30="",0,AR30) -> 0 | CJ30: =IF(BQ30="",0,BQ30) -> 0 | CK30: =IF(AB30="",0,AB30) -> 0 | CL30: =IF(Y30="",0,Y30) -> 0 | CM30: =IF(Z30="",0,Z30) -> 0 | CO30: =IF(G30="",0,G30) -> 0 | CP30: =MIS_Calc!$B$8 -> 135 | CQ30: =MIS_Calc!$B$9 -> 8 | CR30: =MIS_Calc!$B$10 -> 0.95 | CS30: =MIS_Calc!$B$11 -> 0.9
